Workbook
Name ______new1: #REF!
Name _____new1: #REF!
Name ___new1: #REF!
Name __new1: #REF!
Name _2004: #REF!
Name _2005: #REF!
Name _2006: #REF!
Name _2007: #REF!
Name _2008: #REF!
Name _2009: #REF!
Name _2010: #REF!
Name _2011: #REF!
Name _2012: #REF!
Name _2013: #REF!
Name _2013_: #REF!
Name _2014: #REF!
Name _2015: #REF!
Name _2016: #REF!
Name _2017: #REF!
Name _2018: #REF!
Name _2020: #REF!
Name _3000: #REF!
Name _3010: #REF!
Name _3019: #REF!
Name _3310: #REF!
Name _4320: #REF!
Name _4355: #REF!
Name _4405: #REF!
Name _4410: #REF!
Name _4445: #REF!
Name _4450: #REF!
Name _4452: #REF!
Name _4453: #REF!
Name _4480: #REF!
Name _4485: #REF!
Name _4496: #REF!
Name _4505: #REF!
Name _4555: #REF!
Name _4560: #REF!
Name _4710: #REF!
Name _4715: #REF!
Name _4830: #REF!
Name _4848: #REF!
Name _ADM2000: #REF!
Name _ADM2001: #REF!
Name _Bud02: #REF!
Name _Bud03: #REF!
Name _CAM96: #REF!
Name _CAM97: #REF!
Name _CAM98: #REF!
Name _DPU95: #REF!
Name _end1: IF([0]!Loan_Amount*[0]!Interest_Rate*[0]!Loan_Years*[0]!Loan_Start>0,1,0)
Name _EPU01: #REF!
Name _EPU02: #REF!
Name _EPU03: #REF!
Name _EPU04: #REF!
Name _EPU96: #REF!
Name _EPU97: #REF!
Name _EPU98: #REF!
Name _EPU99: #REF!

Sheet Pro Forma
B3: Base Assumptions | I3: Yr | Z3: 0 | AA3: 1 | AB3: 1 | AC3: 1 | AD3: 1 | AE3: 1 | AF3: 1 | AG3: 1 | AH3: 1 | AI3: 1 | AJ3: 1 | AK3: 1 | AL3: 1 | AM3: =AA3+1 | AN3: =AB3+1 | AO3: =AC3+1 | AP3: =AD3+1 | AQ3: =AE3+1 | AR3: =AF3+1 | AS3: =AG3+1 | AT3: =AH3+1 | ... FB3: =EP3+1
B4: Property Name: | C4: =Inputs!C81 | I4: Mo | Z4: 0 | AA4: =Z4+1 | AB4: =AA4+1 | AC4: =AB4+1 | AD4: =AC4+1 | AE4: =AD4+1 | AF4: =AE4+1 | AG4: =AF4+1 | AH4: =AG4+1 | ... FB4: =FA4+1
B5: Address: | C5: =Inputs!C82 | I5: Calendar Year | Z5: =YEAR(Z6) | AA5: =YEAR(AA6) | AB5: =YEAR(AB6) | AC5: =YEAR(AC6) | AD5: =YEAR(AD6) | AE5: =YEAR(AE6) | AF5: =YEAR(AF6) | AG5: =YEAR(AG6) | ... FB5: =YEAR(FB6)
B6: Returns Metrics | F6: Aequitas (LP) | G6: GP (Sponsor) | I6: Property Cash Flows | L6: Total | N6: Annual Cash Flow (Operating Year) | Z6: =D15 | AA6: =EOMONTH(Z6,0) | AB6: =EOMONTH(AA6,1) | AC6: =EOMONTH(AB6,1) | AD6: =EOMONTH(AC6,1) | AE6: =EOMONTH(AD6,1) | AF6: =EOMONTH(AE6,1) | AG6: =EOMONTH(AF6,1) | AH6: =EOMONTH(AG6,1) | AI6: =EOMONTH(AH6,1) | ... FB6: =EOMONTH(FA6,1)
B7: Deal-Level Return | C7: Unlevered | D7: Levered | E7: Partnership-Level | F7: =Inputs!C86 | G7: =1-F7 | I7: Pro Forma | N7: 0 | O7: =N7+1 | P7: =O7+1 | Q7: =P7+1 | R7: =Q7+1 | S7: =R7+1 | T7: =S7+1 | U7: =T7+1 | V7: =U7+1 | ... X7: =W7+1
B8: Net Profit | C8: =L98 | D8: =L115 | E8: Net Profit | F8: =L141 | G8: =L144 | I8: Growth Assumptions
B9: Peak Equity | C9: =L99 | D9: =L116 | E9: Peak Equity | F9: =-SUMIF(Z141:FB141,"<0",Z141:FB141) | G9: =-SUMIF(Z144:FB144,"<0",Z144:FB144) | I9: =B90 | N9: =SUMIF($Z$3:$FB$3,N$7,$Z9:$FB9) | O9: =SUMIF($Z$3:$FB$3,O$7,$Z9:$FB9) | P9: =SUMIF($Z$3:$FB$3,P$7,$Z9:$FB9) | Q9: =SUMIF($Z$3:$FB$3,Q$7,$Z9:$FB9) | R9: =SUMIF($Z$3:$FB$3,R$7,$Z9:$FB9) | S9: =SUMIF($Z$3:$FB$3,S$7,$Z9:$FB9) | T9: =SUMIF($Z$3:$FB$3,T$7,$Z9:$FB9) | U9: =SUMIF($Z$3:$FB$3,U$7,$Z9:$FB9) | ... X9: =SUMIF($Z$3:$FB$3,X$7,$Z9:$FB9) | Z9: 0 | AA9: =IFERROR(INDEX($C90:$G90,MATCH(YEAR(AA$6),$C$89:$G$89,0))/12,Z9) | AB9: =IFERROR(INDEX($C90:$G90,MATCH(YEAR(AB$6),$C$89:$G$89,0))/12,AA9) | AC9: =IFERROR(INDEX($C90:$G90,MATCH(YEAR(AC$6),$C$89:$G$89,0))/12,AB9) | AD9: =IFERROR(INDEX($C90:$G90,MATCH(YEAR(AD$6),$C$89:$G$89,0))/12,AC9) | AE9: =IFERROR(INDEX($C90:$G90,MATCH(YEAR(AE$6),$C$89:$G$89,0))/12,AD9) | AF9: =IFERROR(INDEX($C90:$G90,MATCH(YEAR(AF$6),$C$89:$G$89,0))/12,AE9) | AG9: =IFERROR(INDEX($C90:$G90,MATCH(YEAR(AG$6),$C$89:$G$89,0))/12,AF9) | AH9: =IFERROR(INDEX($C90:$G90,MATCH(YEAR(AH$6),$C$89:$G$89,0))/12,AG9) | ... FB9: =IFERROR(INDEX($C90:$G90,MATCH(YEAR(FB$6),$C$89:$G$89,0))/12,FA9)
B10: IRR | C10: =L100 | D10: =L117 | E10: IRR | F10: =L142 | G10: =L145 | I10: Compounded Rate | Z10: 1 | AA10: =Z10*(1+AA9) | AB10: =AA10*(1+AB9) | AC10: =AB10*(1+AC9) | AD10: =AC10*(1+AD9) | AE10: =AD10*(1+AE9) | AF10: =AE10*(1+AF9) | AG10: =AF10*(1+AG9) | AH10: =AG10*(1+AH9) | ... FB10: =FA10*(1+FB9)
B11: Equity Multiple | C11: =L101 | D11: =L118 | E11: Equity Multiple | F11: =L143 | G11: =L146 | I11: =B91 | N11: =SUMIF($Z$3:$FB$3,N$7,$Z11:$FB11) | O11: =SUMIF($Z$3:$FB$3,O$7,$Z11:$FB11) | P11: =SUMIF($Z$3:$FB$3,P$7,$Z11:$FB11) | Q11: =SUMIF($Z$3:$FB$3,Q$7,$Z11:$FB11) | R11: =SUMIF($Z$3:$FB$3,R$7,$Z11:$FB11) | S11: =SUMIF($Z$3:$FB$3,S$7,$Z11:$FB11) | T11: =SUMIF($Z$3:$FB$3,T$7,$Z11:$FB11) | U11: =SUMIF($Z$3:$FB$3,U$7,$Z11:$FB11) | ... X11: =SUMIF($Z$3:$FB$3,X$7,$Z11:$FB11) | Z11: 0 | AA11: =IFERROR(INDEX($C91:$G91,MATCH(YEAR(AA$6),$C$89:$G$89,0))/12,Z11) | AB11: =IFERROR(INDEX($C91:$G91,MATCH(YEAR(AB$6),$C$89:$G$89,0))/12,AA11) | AC11: =IFERROR(INDEX($C91:$G91,MATCH(YEAR(AC$6),$C$89:$G$89,0))/12,AB11) | AD11: =IFERROR(INDEX($C91:$G91,MATCH(YEAR(AD$6),$C$89:$G$89,0))/12,AC11) | AE11: =IFERROR(INDEX($C91:$G91,MATCH(YEAR(AE$6),$C$89:$G$89,0))/12,AD11) | AF11: =IFERROR(INDEX($C91:$G91,MATCH(YEAR(AF$6),$C$89:$G$89,0))/12,AE11) | AG11: =IFERROR(INDEX($C91:$G91,MATCH(YEAR(AG$6),$C$89:$G$89,0))/12,AF11) | AH11: =IFERROR(INDEX($C91:$G91,MATCH(YEAR(AH$6),$C$89:$G$89,0))/12,AG11) | ... FB11: =IFERROR(INDEX($C91:$G91,MATCH(YEAR(FB$6),$C$89:$G$89,0))/12,FA11)
I12: Compounded Rate | Z12: 1 | AA12: =Z12*(1+AA11) | AB12: =AA12*(1+AB11) | AC12: =AB12*(1+AC11) | AD12: =AC12*(1+AD11) | AE12: =AD12*(1+AE11) | AF12: =AE12*(1+AF11) | AG12: =AF12*(1+AG11) | AH12: =AG12*(1+AH11) | ... FB12: =FA12*(1+FB11)
B13: Timeline | I13: =B92 | N13: =SUMIF($Z$3:$FB$3,N$7,$Z13:$FB13) | O13: =SUMIF($Z$3:$FB$3,O$7,$Z13:$FB13) | P13: =SUMIF($Z$3:$FB$3,P$7,$Z13:$FB13) | Q13: =SUMIF($Z$3:$FB$3,Q$7,$Z13:$FB13) | R13: =SUMIF($Z$3:$FB$3,R$7,$Z13:$FB13) | S13: =SUMIF($Z$3:$FB$3,S$7,$Z13:$FB13) | T13: =SUMIF($Z$3:$FB$3,T$7,$Z13:$FB13) | U13: =SUMIF($Z$3:$FB$3,U$7,$Z13:$FB13) | ... X13: =SUMIF($Z$3:$FB$3,X$7,$Z13:$FB13) | Z13: 0 | AA13: =IFERROR(INDEX($C92:$G92,MATCH(YEAR(AA$6),$C$89:$G$89,0))/12,Z13) | AB13: =IFERROR(INDEX($C92:$G92,MATCH(YEAR(AB$6),$C$89:$G$89,0))/12,AA13) | AC13: =IFERROR(INDEX($C92:$G92,MATCH(YEAR(AC$6),$C$89:$G$89,0))/12,AB13) | AD13: =IFERROR(INDEX($C92:$G92,MATCH(YEAR(AD$6),$C$89:$G$89,0))/12,AC13) | AE13: =IFERROR(INDEX($C92:$G92,MATCH(YEAR(AE$6),$C$89:$G$89,0))/12,AD13) | AF13: =IFERROR(INDEX($C92:$G92,MATCH(YEAR(AF$6),$C$89:$G$89,0))/12,AE13) | AG13: =IFERROR(INDEX($C92:$G92,MATCH(YEAR(AG$6),$C$89:$G$89,0))/12,AF13) | AH13: =IFERROR(INDEX($C92:$G92,MATCH(YEAR(AH$6),$C$89:$G$89,0))/12,AG13) | ... FB13: =IFERROR(INDEX($C92:$G92,MATCH(YEAR(FB$6),$C$89:$G$89,0))/12,FA13)
C14: BOP Mo | D14: BOP Date | E14: Duration | F14: EOP Date | G14: EOP Mo | I14: Compounded Rate | Z14: 1 | AA14: =Z14*(1+AA13) | AB14: =AA14*(1+AB13) | AC14: =AB14*(1+AC13) | AD14: =AC14*(1+AD13) | AE14: =AD14*(1+AE13) | AF14: =AE14*(1+AF13) | AG14: =AF14*(1+AG13) | AH14: =AG14*(1+AH13) | ... FB14: =FA14*(1+FB13)
B15: Acquisition Date | C15: 0 | D15: =Inputs!C5 | E15: =Inputs!C6 | F15: =EOMONTH(D15,E15) | G15: =INDEX($Z$4:$FB$4,MATCH(F15,$Z$6:$FB$6,0)) | I15: =B93 | N15: =SUMIF($Z$3:$FB$3,N$7,$Z15:$FB15) | O15: =SUMIF($Z$3:$FB$3,O$7,$Z15:$FB15) | P15: =SUMIF($Z$3:$FB$3,P$7,$Z15:$FB15) | Q15: =SUMIF($Z$3:$FB$3,Q$7,$Z15:$FB15) | R15: =SUMIF($Z$3:$FB$3,R$7,$Z15:$FB15) | S15: =SUMIF($Z$3:$FB$3,S$7,$Z15:$FB15) | T15: =SUMIF($Z$3:$FB$3,T$7,$Z15:$FB15) | U15: =SUMIF($Z$3:$FB$3,U$7,$Z15:$FB15) | ... X15: =SUMIF($Z$3:$FB$3,X$7,$Z15:$FB15) | Z15: 0 | AA15: =IFERROR(INDEX($C93:$G93,MATCH(YEAR(AA$6),$C$89:$G$89,0))/12,Z15) | AB15: =IFERROR(INDEX($C93:$G93,MATCH(YEAR(AB$6),$C$89:$G$89,0))/12,AA15) | AC15: =IFERROR(INDEX($C93:$G93,MATCH(YEAR(AC$6),$C$89:$G$89,0))/12,AB15) | AD15: =IFERROR(INDEX($C93:$G93,MATCH(YEAR(AD$6),$C$89:$G$89,0))/12,AC15) | AE15: =IFERROR(INDEX($C93:$G93,MATCH(YEAR(AE$6),$C$89:$G$89,0))/12,AD15) | AF15: =IFERROR(INDEX($C93:$G93,MATCH(YEAR(AF$6),$C$89:$G$89,0))/12,AE15) | AG15: =IFERROR(INDEX($C93:$G93,MATCH(YEAR(AG$6),$C$89:$G$89,0))/12,AF15) | AH15: =IFERROR(INDEX($C93:$G93,MATCH(YEAR(AH$6),$C$89:$G$89,0))/12,AG15) | ... FB15: =IFERROR(INDEX($C93:$G93,MATCH(YEAR(FB$6),$C$89:$G$89,0))/12,FA15)
B16: Hold Period | C16: =INDEX($Z$4:$FB$4,MATCH(D16,$Z$6:$FB$6,0)) | D16: =EOMONTH(F15,0) | E16: =Inputs!C7 | F16: =EOMONTH(D16,E16-1) | G16: =INDEX($Z$4:$FB$4,MATCH(F16,$Z$6:$FB$6,0)) | I16: Compounded Rate | Z16: 1 | AA16: =Z16*(1+AA15) | AB16: =AA16*(1+AB15) | AC16: =AB16*(1+AC15) | AD16: =AC16*(1+AD15) | AE16: =AD16*(1+AE15) | AF16: =AE16*(1+AF15) | AG16: =AF16*(1+AG15) | AH16: =AG16*(1+AH15) | ... FB16: =FA16*(1+FB15)
B17: Refinance | C17: =INDEX($Z$4:$FB$4,MATCH(D17,$Z$6:$FB$6,0)) | D17: =EOMONTH(F16,0) | E17: 1 | F17: =EOMONTH(D17,E17-1) | G17: =INDEX($Z$4:$FB$4,MATCH(F17,$Z$6:$FB$6,0))
B18: =Inputs!C83 | C18: =INDEX($Z$4:$FB$4,MATCH(D18,$Z$6:$FB$6,0)) | D18: =EOMONTH(F17,0) | E18: =G18-C18 | F18: =EOMONTH(D15,B18*12-1) | G18: =INDEX($Z$4:$FB$4,MATCH(F18,$Z$6:$FB$6,0)) | I18: Rent Analysis
I19: Potential Gross MR Rent/Unit | Z19: =D75 | AA19: =Z19*(1+AA9) | AB19: =AA19*(1+AB9) | AC19: =AB19*(1+AC9) | AD19: =AC19*(1+AD9) | AE19: =AD19*(1+AE9) | AF19: =AE19*(1+AF9) | AG19: =AF19*(1+AG9) | AH19: =AG19*(1+AH9) | ... FB19: =FA19*(1+FB9)
B20: Valuation Analysis
B21: Entry Valuation | C21: Asking/Listing Price | D21: Aequitas Valuation | E21: Residual Analysis | F21: Refinance | G21: Exit | I21: Gross Potential Rent
B22: NOI (T-12) | C22: =Inputs!C8 | D22: =C22 | E22: NOI (T-12) | F22: =INDEX($Z$83:$FB$83,MATCH(C17,$Z$4:$FB$4,0)) | G22: =INDEX($Z$83:$FB$83,MATCH(G18,$Z$4:$FB$4,0)) | I22: Gross Potential Revenue | L22: =SUMIF($Z$4:$FB$4,"<="&$G$18,$Z22:$FB22) | N22: =SUMIF($Z$3:$FB$3,N$7,$Z22:$FB22) | O22: =SUMIF($Z$3:$FB$3,O$7,$Z22:$FB22) | P22: =SUMIF($Z$3:$FB$3,P$7,$Z22:$FB22) | Q22: =SUMIF($Z$3:$FB$3,Q$7,$Z22:$FB22) | R22: =SUMIF($Z$3:$FB$3,R$7,$Z22:$FB22) | S22: =SUMIF($Z$3:$FB$3,S$7,$Z22:$FB22) | T22: =SUMIF($Z$3:$FB$3,T$7,$Z22:$FB22) | U22: =SUMIF($Z$3:$FB$3,U$7,$Z22:$FB22) | ... X22: =SUMIF($Z$3:$FB$3,X$7,$Z22:$FB22) | Z22: 0 | AA22: =AA19*$C$75 | AB22: =AB19*$C$75 | AC22: =AC19*$C$75 | AD22: =AD19*$C$75 | AE22: =AE19*$C$75 | AF22: =AF19*$C$75 | AG22: =AG19*$C$75 | AH22: =AH19*$C$75 | ... FB22: =FB19*$C$75
B23: Cap Rate | C23: =C22/C24 | D23: =Inputs!C9 | E23: Cap Rate | F23: =C122 | G23: =F23 | I23: Loss-to-Lease | L23: =SUMIF($Z$4:$FB$4,"<="&$G$18,$Z23:$FB23) | N23: =SUMIF($Z$3:$FB$3,N$7,$Z23:$FB23) | O23: =SUMIF($Z$3:$FB$3,O$7,$Z23:$FB23) | P23: =SUMIF($Z$3:$FB$3,P$7,$Z23:$FB23) | Q23: =SUMIF($Z$3:$FB$3,Q$7,$Z23:$FB23) | R23: =SUMIF($Z$3:$FB$3,R$7,$Z23:$FB23) | S23: =SUMIF($Z$3:$FB$3,S$7,$Z23:$FB23) | T23: =SUMIF($Z$3:$FB$3,T$7,$Z23:$FB23) | U23: =SUMIF($Z$3:$FB$3,U$7,$Z23:$FB23) | ... X23: =SUMIF($Z$3:$FB$3,X$7,$Z23:$FB23) | Z23: 0 | AA23: =AA22*-IFERROR(INDEX($C$84:$G$84,MATCH(YEAR(AA6),$C$83:$G$83,0)),$G$84) | AB23: =AB22*-IFERROR(INDEX($C$84:$G$84,MATCH(YEAR(AB6),$C$83:$G$83,0)),$G$84) | AC23: =AC22*-IFERROR(INDEX($C$84:$G$84,MATCH(YEAR(AC6),$C$83:$G$83,0)),$G$84) | AD23: =AD22*-IFERROR(INDEX($C$84:$G$84,MATCH(YEAR(AD6),$C$83:$G$83,0)),$G$84) | AE23: =AE22*-IFERROR(INDEX($C$84:$G$84,MATCH(YEAR(AE6),$C$83:$G$83,0)),$G$84) | AF23: =AF22*-IFERROR(INDEX($C$84:$G$84,MATCH(YEAR(AF6),$C$83:$G$83,0)),$G$84) | AG23: =AG22*-IFERROR(INDEX($C$84:$G$84,MATCH(YEAR(AG6),$C$83:$G$83,0)),$G$84) | AH23: =AH22*-IFERROR(INDEX($C$84:$G$84,MATCH(YEAR(AH6),$C$83:$G$83,0)),$G$84) | ... FB23: =FB22*-IFERROR(INDEX($C$84:$G$84,MATCH(YEAR(FB6),$C$83:$G$83,0)),$G$84)
B24: Gross Value | C24: =Inputs!C84 | D24: =D22/D23 | E24: Gross Value | F24: =F22/F23 | G24: =G22/G23 | I24: Gross Potential Rent | L24: =SUMIF($Z$4:$FB$4,"<="&$G$18,$Z24:$FB24) | N24: =SUMIF($Z$3:$FB$3,N$7,$Z24:$FB24) | O24: =SUMIF($Z$3:$FB$3,O$7,$Z24:$FB24) | P24: =SUMIF($Z$3:$FB$3,P$7,$Z24:$FB24) | Q24: =SUMIF($Z$3:$FB$3,Q$7,$Z24:$FB24) | R24: =SUMIF($Z$3:$FB$3,R$7,$Z24:$FB24) | S24: =SUMIF($Z$3:$FB$3,S$7,$Z24:$FB24) | T24: =SUMIF($Z$3:$FB$3,T$7,$Z24:$FB24) | U24: =SUMIF($Z$3:$FB$3,U$7,$Z24:$FB24) | ... X24: =SUMIF($Z$3:$FB$3,X$7,$Z24:$FB24) | Z24: 0 | AA24: =SUM(AA22:AA23) | AB24: =SUM(AB22:AB23) | AC24: =SUM(AC22:AC23) | AD24: =SUM(AD22:AD23) | AE24: =SUM(AE22:AE23) | AF24: =SUM(AF22:AF23) | AG24: =SUM(AG22:AG23) | AH24: =SUM(AH22:AH23) | ... FB24: =SUM(FB22:FB23)
B25: $/Unit | C25: =C24/$C$75 | D25: =D24/$C$75 | E25: $/Unit | F25: =F24/$C$75 | G25: =G24/$C$75
C26: Delta | D26: =D24-C24 | E26: =Inputs!C10 | F26: =-$E26*F24 | G26: =-$E26*G24 | I26: Other Income
C27: $/Unit | D27: =D25-C25 | E27: Net Sales Proceeds | F27: =SUM(F24,F26) | G27: =SUM(G24,G26) | I27: RUBS | J27: =D78 | L27: =SUMIF($Z$4:$FB$4,"<="&$G$18,$Z27:$FB27) | N27: =SUMIF($Z$3:$FB$3,N$7,$Z27:$FB27) | O27: =SUMIF($Z$3:$FB$3,O$7,$Z27:$FB27) | P27: =SUMIF($Z$3:$FB$3,P$7,$Z27:$FB27) | Q27: =SUMIF($Z$3:$FB$3,Q$7,$Z27:$FB27) | R27: =SUMIF($Z$3:$FB$3,R$7,$Z27:$FB27) | S27: =SUMIF($Z$3:$FB$3,S$7,$Z27:$FB27) | T27: =SUMIF($Z$3:$FB$3,T$7,$Z27:$FB27) | U27: =SUMIF($Z$3:$FB$3,U$7,$Z27:$FB27) | ... X27: =SUMIF($Z$3:$FB$3,X$7,$Z27:$FB27) | Z27: 0 | AA27: =$J$27*AA53 | AB27: =$J$27*AB53 | AC27: =$J$27*AC53 | AD27: =$J$27*AD53 | AE27: =$J$27*AE53 | AF27: =$J$27*AF53 | AG27: =$J$27*AG53 | AH27: =$J$27*AH53 | ... FB27: =$J$27*FB53
I28: Parking Income | J28: =F79 | L28: =SUMIF($Z$4:$FB$4,"<="&$G$18,$Z28:$FB28) | N28: =SUMIF($Z$3:$FB$3,N$7,$Z28:$FB28) | O28: =SUMIF($Z$3:$FB$3,O$7,$Z28:$FB28) | P28: =SUMIF($Z$3:$FB$3,P$7,$Z28:$FB28) | Q28: =SUMIF($Z$3:$FB$3,Q$7,$Z28:$FB28) | R28: =SUMIF($Z$3:$FB$3,R$7,$Z28:$FB28) | S28: =SUMIF($Z$3:$FB$3,S$7,$Z28:$FB28) | T28: =SUMIF($Z$3:$FB$3,T$7,$Z28:$FB28) | U28: =SUMIF($Z$3:$FB$3,U$7,$Z28:$FB28) | ... X28: =SUMIF($Z$3:$FB$3,X$7,$Z28:$FB28) | Z28: 0 | AA28: =IFERROR($F$79*$E$79*AA12*(AA$4>=1),0) | AB28: =IFERROR($F$79*$E$79*AB12*(AB$4>=1),0) | AC28: =IFERROR($F$79*$E$79*AC12*(AC$4>=1),0) | AD28: =IFERROR($F$79*$E$79*AD12*(AD$4>=1),0) | AE28: =IFERROR($F$79*$E$79*AE12*(AE$4>=1),0) | AF28: =IFERROR($F$79*$E$79*AF12*(AF$4>=1),0) | AG28: =IFERROR($F$79*$E$79*AG12*(AG$4>=1),0) | AH28: =IFERROR($F$79*$E$79*AH12*(AH$4>=1),0) | ... FB28: =IFERROR($F$79*$E$79*FB12*(FB$4>=1),0)
B29: Sources & Uses at Closing | I29: Other Income | J29: =F80 | L29: =SUMIF($Z$4:$FB$4,"<="&$G$18,$Z29:$FB29) | N29: =SUMIF($Z$3:$FB$3,N$7,$Z29:$FB29) | O29: =SUMIF($Z$3:$FB$3,O$7,$Z29:$FB29) | P29: =SUMIF($Z$3:$FB$3,P$7,$Z29:$FB29) | Q29: =SUMIF($Z$3:$FB$3,Q$7,$Z29:$FB29) | R29: =SUMIF($Z$3:$FB$3,R$7,$Z29:$FB29) | S29: =SUMIF($Z$3:$FB$3,S$7,$Z29:$FB29) | T29: =SUMIF($Z$3:$FB$3,T$7,$Z29:$FB29) | U29: =SUMIF($Z$3:$FB$3,U$7,$Z29:$FB29) | ... X29: =SUMIF($Z$3:$FB$3,X$7,$Z29:$FB29) | Z29: 0 | AA29: =IFERROR($F$80*$E$80*AA12*(AA$4>=1),0) | AB29: =IFERROR($F$80*$E$80*AB12*(AB$4>=1),0) | AC29: =IFERROR($F$80*$E$80*AC12*(AC$4>=1),0) | AD29: =IFERROR($F$80*$E$80*AD12*(AD$4>=1),0) | AE29: =IFERROR($F$80*$E$80*AE12*(AE$4>=1),0) | AF29: =IFERROR($F$80*$E$80*AF12*(AF$4>=1),0) | AG29: =IFERROR($F$80*$E$80*AG12*(AG$4>=1),0) | AH29: =IFERROR($F$80*$E$80*AH12*(AH$4>=1),0) | ... FB29: =IFERROR($F$80*$E$80*FB12*(FB$4>=1),0)
B30: Sources | C30: % Total | D30: Closing | E30: % Total | F30: Refinance | G30: At Exit | I30: Total Other Income | L30: =SUMIF($Z$4:$FB$4,"<="&$G$18,$Z30:$FB30) | N30: =SUMIF($Z$3:$FB$3,N$7,$Z30:$FB30) | O30: =SUMIF($Z$3:$FB$3,O$7,$Z30:$FB30) | P30: =SUMIF($Z$3:$FB$3,P$7,$Z30:$FB30) | Q30: =SUMIF($Z$3:$FB$3,Q$7,$Z30:$FB30) | R30: =SUMIF($Z$3:$FB$3,R$7,$Z30:$FB30) | S30: =SUMIF($Z$3:$FB$3,S$7,$Z30:$FB30) | T30: =SUMIF($Z$3:$FB$3,T$7,$Z30:$FB30) | U30: =SUMIF($Z$3:$FB$3,U$7,$Z30:$FB30) | ... X30: =SUMIF($Z$3:$FB$3,X$7,$Z30:$FB30) | Z30: 0 | AA30: =SUM(AA27:AA29) | AB30: =SUM(AB27:AB29) | AC30: =SUM(AC27:AC29) | AD30: =SUM(AD27:AD29) | AE30: =SUM(AE27:AE29) | AF30: =SUM(AF27:AF29) | AG30: =SUM(AG27:AG29) | AH30: =SUM(AH27:AH29) | ... FB30: =SUM(FB27:FB29)
B31: GP Equity | C31: =D31/$D$34 | D31: =(D41-D46)*G7 | E31: =F31/$F$34 | F31: =(F34-F33)*G7 | G31: =(G34-G33)*G7
B32: Aequitas Equity | C32: =D32/$D$34 | D32: =(D41-D46)*F7 | E32: =F32/$F$34 | F32: =(F34-F33)*F7 | G32: =(G34-G33)*F7 | I32: Vacancy Loss | L32: =SUMIF($Z$4:$FB$4,"<="&$G$18,$Z32:$FB32) | N32: =SUMIF($Z$3:$FB$3,N$7,$Z32:$FB32) | O32: =SUMIF($Z$3:$FB$3,O$7,$Z32:$FB32) | P32: =SUMIF($Z$3:$FB$3,P$7,$Z32:$FB32) | Q32: =SUMIF($Z$3:$FB$3,Q$7,$Z32:$FB32) | R32: =SUMIF($Z$3:$FB$3,R$7,$Z32:$FB32) | S32: =SUMIF($Z$3:$FB$3,S$7,$Z32:$FB32) | T32: =SUMIF($Z$3:$FB$3,T$7,$Z32:$FB32) | U32: =SUMIF($Z$3:$FB$3,U$7,$Z32:$FB32) | ... X32: =SUMIF($Z$3:$FB$3,X$7,$Z32:$FB32) | Z32: 0 | AA32: =-IFERROR(INDEX($C85:$G85,MATCH(YEAR(AA$6),$C$83:$G$83,0)),$G$85)*(SUM(AA$24,AA$30)) | AB32: =-IFERROR(INDEX($C85:$G85,MATCH(YEAR(AB$6),$C$83:$G$83,0)),$G$85)*(SUM(AB$24,AB$30)) | AC32: =-IFERROR(INDEX($C85:$G85,MATCH(YEAR(AC$6),$C$83:$G$83,0)),$G$85)*(SUM(AC$24,AC$30)) | AD32: =-IFERROR(INDEX($C85:$G85,MATCH(YEAR(AD$6),$C$83:$G$83,0)),$G$85)*(SUM(AD$24,AD$30)) | AE32: =-IFERROR(INDEX($C85:$G85,MATCH(YEAR(AE$6),$C$83:$G$83,0)),$G$85)*(SUM(AE$24,AE$30)) | AF32: =-IFERROR(INDEX($C85:$G85,MATCH(YEAR(AF$6),$C$83:$G$83,0)),$G$85)*(SUM(AF$24,AF$30)) | AG32: =-IFERROR(INDEX($C85:$G85,MATCH(YEAR(AG$6),$C$83:$G$83,0)),$G$85)*(SUM(AG$24,AG$30)) | AH32: =-IFERROR(INDEX($C85:$G85,MATCH(YEAR(AH$6),$C$83:$G$83,0)),$G$85)*(SUM(AH$24,AH$30)) | ... FB32: =-IFERROR(INDEX($C85:$G85,MATCH(YEAR(FB$6),$C$83:$G$83,0)),$G$85)*(SUM(FB$24,FB$30))
B33: Debt | C33: =D33/$D$34 | D33: =D46 | E33: =F33/$F$34 | F33: =G46 | G33: =INDEX($Z$164:$FB$164,MATCH(G18,$Z$4:$FB$4,0)) | I33: Bad Debt | J33: =C86 | L33: =SUMIF($Z$4:$FB$4,"<="&$G$18,$Z33:$FB33) | N33: =SUMIF($Z$3:$FB$3,N$7,$Z33:$FB33) | O33: =SUMIF($Z$3:$FB$3,O$7,$Z33:$FB33) | P33: =SUMIF($Z$3:$FB$3,P$7,$Z33:$FB33) | Q33: =SUMIF($Z$3:$FB$3,Q$7,$Z33:$FB33) | R33: =SUMIF($Z$3:$FB$3,R$7,$Z33:$FB33) | S33: =SUMIF($Z$3:$FB$3,S$7,$Z33:$FB33) | T33: =SUMIF($Z$3:$FB$3,T$7,$Z33:$FB33) | U33: =SUMIF($Z$3:$FB$3,U$7,$Z33:$FB33) | ... X33: =SUMIF($Z$3:$FB$3,X$7,$Z33:$FB33) | Z33: 0 | AA33: =-IFERROR(INDEX($C86:$G86,MATCH(YEAR(AA$6),$C$83:$G$83,0)),$G$86)*(SUM(AA$24,AA$30)) | AB33: =-IFERROR(INDEX($C86:$G86,MATCH(YEAR(AB$6),$C$83:$G$83,0)),$G$86)*(SUM(AB$24,AB$30)) | AC33: =-IFERROR(INDEX($C86:$G86,MATCH(YEAR(AC$6),$C$83:$G$83,0)),$G$86)*(SUM(AC$24,AC$30)) | AD33: =-IFERROR(INDEX($C86:$G86,MATCH(YEAR(AD$6),$C$83:$G$83,0)),$G$86)*(SUM(AD$24,AD$30)) | AE33: =-IFERROR(INDEX($C86:$G86,MATCH(YEAR(AE$6),$C$83:$G$83,0)),$G$86)*(SUM(AE$24,AE$30)) | AF33: =-IFERROR(INDEX($C86:$G86,MATCH(YEAR(AF$6),$C$83:$G$83,0)),$G$86)*(SUM(AF$24,AF$30)) | AG33: =-IFERROR(INDEX($C86:$G86,MATCH(YEAR(AG$6),$C$83:$G$83,0)),$G$86)*(SUM(AG$24,AG$30)) | AH33: =-IFERROR(INDEX($C86:$G86,MATCH(YEAR(AH$6),$C$83:$G$83,0)),$G$86)*(SUM(AH$24,AH$30)) | ... FB33: =-IFERROR(INDEX($C86:$G86,MATCH(YEAR(FB$6),$C$83:$G$83,0)),$G$86)*(SUM(FB$24,FB$30))
B34: Total | C34: =D34/$D$34 | D34: =SUM(D31:D33) | E34: =F34/$F$34 | F34: =F24 | G34: =G24 | I34: Concessions | J34: =C87 | L34: =SUMIF($Z$4:$FB$4,"<="&$G$18,$Z34:$FB34) | N34: =SUMIF($Z$3:$FB$3,N$7,$Z34:$FB34) | O34: =SUMIF($Z$3:$FB$3,O$7,$Z34:$FB34) | P34: =SUMIF($Z$3:$FB$3,P$7,$Z34:$FB34) | Q34: =SUMIF($Z$3:$FB$3,Q$7,$Z34:$FB34) | R34: =SUMIF($Z$3:$FB$3,R$7,$Z34:$FB34) | S34: =SUMIF($Z$3:$FB$3,S$7,$Z34:$FB34) | T34: =SUMIF($Z$3:$FB$3,T$7,$Z34:$FB34) | U34: =SUMIF($Z$3:$FB$3,U$7,$Z34:$FB34) | ... X34: =SUMIF($Z$3:$FB$3,X$7,$Z34:$FB34) | Z34: 0 | AA34: =-IFERROR(INDEX($C87:$G87,MATCH(YEAR(AA$6),$C$83:$G$83,0)),$G$87)*(SUM(AA$24,AA$30)) | AB34: =-IFERROR(INDEX($C87:$G87,MATCH(YEAR(AB$6),$C$83:$G$83,0)),$G$87)*(SUM(AB$24,AB$30)) | AC34: =-IFERROR(INDEX($C87:$G87,MATCH(YEAR(AC$6),$C$83:$G$83,0)),$G$87)*(SUM(AC$24,AC$30)) | AD34: =-IFERROR(INDEX($C87:$G87,MATCH(YEAR(AD$6),$C$83:$G$83,0)),$G$87)*(SUM(AD$24,AD$30)) | AE34: =-IFERROR(INDEX($C87:$G87,MATCH(YEAR(AE$6),$C$83:$G$83,0)),$G$87)*(SUM(AE$24,AE$30)) | AF34: =-IFERROR(INDEX($C87:$G87,MATCH(YEAR(AF$6),$C$83:$G$83,0)),$G$87)*(SUM(AF$24,AF$30)) | AG34: =-IFERROR(INDEX($C87:$G87,MATCH(YEAR(AG$6),$C$83:$G$83,0)),$G$87)*(SUM(AG$24,AG$30)) | AH34: =-IFERROR(INDEX($C87:$G87,MATCH(YEAR(AH$6),$C$83:$G$83,0)),$G$87)*(SUM(AH$24,AH$30)) | ... FB34: =-IFERROR(INDEX($C87:$G87,MATCH(YEAR(FB$6),$C$83:$G$83,0)),$G$87)*(SUM(FB$24,FB$30))
I35: Model Unit Loss | L35: =SUMIF($Z$4:$FB$4,"<="&$G$18,$Z35:$FB35) | N35: =SUMIF($Z$3:$FB$3,N$7,$Z35:$FB35) | O35: =SUMIF($Z$3:$FB$3,O$7,$Z35:$FB35) | P35: =SUMIF($Z$3:$FB$3,P$7,$Z35:$FB35) | Q35: =SUMIF($Z$3:$FB$3,Q$7,$Z35:$FB35) | R35: =SUMIF($Z$3:$FB$3,R$7,$Z35:$FB35) | S35: =SUMIF($Z$3:$FB$3,S$7,$Z35:$FB35) | T35: =SUMIF($Z$3:$FB$3,T$7,$Z35:$FB35) | U35: =SUMIF($Z$3:$FB$3,U$7,$Z35:$FB35) | ... X35: =SUMIF($Z$3:$FB$3,X$7,$Z35:$FB35) | Z35: =(-IFERROR(INDEX($C88:$G88,MATCH(YEAR(Z$6),$C$83:$G$83,0)),$G$88)*Z19)*(Z4>=1) | AA35: =(-IFERROR(INDEX($C88:$G88,MATCH(YEAR(AA$6),$C$83:$G$83,0)),$G$88)*AA19)*(AA4>=1) | AB35: =(-IFERROR(INDEX($C88:$G88,MATCH(YEAR(AB$6),$C$83:$G$83,0)),$G$88)*AB19)*(AB4>=1) | AC35: =(-IFERROR(INDEX($C88:$G88,MATCH(YEAR(AC$6),$C$83:$G$83,0)),$G$88)*AC19)*(AC4>=1) | AD35: =(-IFERROR(INDEX($C88:$G88,MATCH(YEAR(AD$6),$C$83:$G$83,0)),$G$88)*AD19)*(AD4>=1) | AE35: =(-IFERROR(INDEX($C88:$G88,MATCH(YEAR(AE$6),$C$83:$G$83,0)),$G$88)*AE19)*(AE4>=1) | AF35: =(-IFERROR(INDEX($C88:$G88,MATCH(YEAR(AF$6),$C$83:$G$83,0)),$G$88)*AF19)*(AF4>=1) | AG35: =(-IFERROR(INDEX($C88:$G88,MATCH(YEAR(AG$6),$C$83:$G$83,0)),$G$88)*AG19)*(AG4>=1) | ... FB35: =(-IFERROR(INDEX($C88:$G88,MATCH(YEAR(FB$6),$C$83:$G$83,0)),$G$88)*FB19)*(FB4>=1)
B36: Uses | C36: $/Unit | D36: Total | E36: At Closing | F36: Start Month | G36: Duration | I36: Total Vacancy & Collection | L36: =SUMIF($Z$4:$FB$4,"<="&$G$18,$Z36:$FB36) | N36: =SUMIF($Z$3:$FB$3,N$7,$Z36:$FB36) | O36: =SUMIF($Z$3:$FB$3,O$7,$Z36:$FB36) | P36: =SUMIF($Z$3:$FB$3,P$7,$Z36:$FB36) | Q36: =SUMIF($Z$3:$FB$3,Q$7,$Z36:$FB36) | R36: =SUMIF($Z$3:$FB$3,R$7,$Z36:$FB36) | S36: =SUMIF($Z$3:$FB$3,S$7,$Z36:$FB36) | T36: =SUMIF($Z$3:$FB$3,T$7,$Z36:$FB36) | U36: =SUMIF($Z$3:$FB$3,U$7,$Z36:$FB36) | ... X36: =SUMIF($Z$3:$FB$3,X$7,$Z36:$FB36) | Z36: =SUM(Z32:Z35) | AA36: =SUM(AA32:AA35) | AB36: =SUM(AB32:AB35) | AC36: =SUM(AC32:AC35) | AD36: =SUM(AD32:AD35) | AE36: =SUM(AE32:AE35) | AF36: =SUM(AF32:AF35) | AG36: =SUM(AG32:AG35) | ... FB36: =SUM(FB32:FB35)
B37: Acquisition Price | C37: =D37/$C$75 | D37: =D24 | E37: =Inputs!C12 | F37: =Inputs!C16 | G37: =Inputs!C20
B38: =Inputs!C11 | C38: =D38/$C$75 | D38: =B38*D37 | E38: =Inputs!C13 | F38: =Inputs!C17 | G38: =Inputs!C21 | I38: Effective Gross Income | L38: =SUMIF($Z$4:$FB$4,"<="&$G$18,$Z38:$FB38) | N38: =SUMIF($Z$3:$FB$3,N$7,$Z38:$FB38) | O38: =SUMIF($Z$3:$FB$3,O$7,$Z38:$FB38) | P38: =SUMIF($Z$3:$FB$3,P$7,$Z38:$FB38) | Q38: =SUMIF($Z$3:$FB$3,Q$7,$Z38:$FB38) | R38: =SUMIF($Z$3:$FB$3,R$7,$Z38:$FB38) | S38: =SUMIF($Z$3:$FB$3,S$7,$Z38:$FB38) | T38: =SUMIF($Z$3:$FB$3,T$7,$Z38:$FB38) | U38: =SUMIF($Z$3:$FB$3,U$7,$Z38:$FB38) | ... X38: =SUMIF($Z$3:$FB$3,X$7,$Z38:$FB38) | Z38: =SUM(Z24,Z30,Z36) | AA38: =SUM(AA24,AA30,AA36) | AB38: =SUM(AB24,AB30,AB36) | AC38: =SUM(AC24,AC30,AC36) | AD38: =SUM(AD24,AD30,AD36) | AE38: =SUM(AE24,AE30,AE36) | AF38: =SUM(AF24,AF30,AF36) | AG38: =SUM(AG24,AG30,AG36) | ... FB38: =SUM(FB24,FB30,FB36)
B39: Working Capital/Reserve | C39: =D39/$C$75 | D39: =Inputs!C85 | E39: =Inputs!C14 | F39: =Inputs!C18 | G39: =Inputs!C22
B40: Financing Costs | C40: =D40/$C$75 | D40: =D49 | E40: =Inputs!C15 | F40: =Inputs!C19 | G40: =Inputs!C23 | I40: Operating Expenses
B41: Total | C41: =D41/$C$75 | D41: =SUM(D37:D40) | I41: Controllable Expenses | J41: $/Unit/Yr | L41: Total
I42: Payroll | J42: =Inputs!C72 | L42: =SUMIF($Z$4:$FB$4,"<="&$G$18,$Z42:$FB42) | N42: =SUMIF($Z$3:$FB$3,N$7,$Z42:$FB42) | O42: =SUMIF($Z$3:$FB$3,O$7,$Z42:$FB42) | P42: =SUMIF($Z$3:$FB$3,P$7,$Z42:$FB42) | Q42: =SUMIF($Z$3:$FB$3,Q$7,$Z42:$FB42) | R42: =SUMIF($Z$3:$FB$3,R$7,$Z42:$FB42) | S42: =SUMIF($Z$3:$FB$3,S$7,$Z42:$FB42) | T42: =SUMIF($Z$3:$FB$3,T$7,$Z42:$FB42) | U42: =SUMIF($Z$3:$FB$3,U$7,$Z42:$FB42) | ... X42: =SUMIF($Z$3:$FB$3,X$7,$Z42:$FB42) | Z42: 0 | AA42: =$J42/12*AA$14*$C$75 | AB42: =$J42/12*AB$14*$C$75 | AC42: =$J42/12*AC$14*$C$75 | AD42: =$J42/12*AD$14*$C$75 | AE42: =$J42/12*AE$14*$C$75 | AF42: =$J42/12*AF$14*$C$75 | AG42: =$J42/12*AG$14*$C$75 | AH42: =$J42/12*AH$14*$C$75 | ... FB42: =$J42/12*FB$14*$C$75
B43: Financing Assumptions | I43: Admin | J43: =Inputs!C73 | L43: =SUMIF($Z$4:$FB$4,"<="&$G$18,$Z43:$FB43) | N43: =SUMIF($Z$3:$FB$3,N$7,$Z43:$FB43) | O43: =SUMIF($Z$3:$FB$3,O$7,$Z43:$FB43) | P43: =SUMIF($Z$3:$FB$3,P$7,$Z43:$FB43) | Q43: =SUMIF($Z$3:$FB$3,Q$7,$Z43:$FB43) | R43: =SUMIF($Z$3:$FB$3,R$7,$Z43:$FB43) | S43: =SUMIF($Z$3:$FB$3,S$7,$Z43:$FB43) | T43: =SUMIF($Z$3:$FB$3,T$7,$Z43:$FB43) | U43: =SUMIF($Z$3:$FB$3,U$7,$Z43:$FB43) | ... X43: =SUMIF($Z$3:$FB$3,X$7,$Z43:$FB43) | Z43: 0 | AA43: =$J43/12*AA$14*$C$75 | AB43: =$J43/12*AB$14*$C$75 | AC43: =$J43/12*AC$14*$C$75 | AD43: =$J43/12*AD$14*$C$75 | AE43: =$J43/12*AE$14*$C$75 | AF43: =$J43/12*AF$14*$C$75 | AG43: =$J43/12*AG$14*$C$75 | AH43: =$J43/12*AH$14*$C$75 | ... FB43: =$J43/12*FB$14*$C$75
B44: Senior Financing | C44: Senior Financing | F44: Refinance | I44: Marketing | J44: =Inputs!C74 | L44: =SUMIF($Z$4:$FB$4,"<="&$G$18,$Z44:$FB44) | N44: =SUMIF($Z$3:$FB$3,N$7,$Z44:$FB44) | O44: =SUMIF($Z$3:$FB$3,O$7,$Z44:$FB44) | P44: =SUMIF($Z$3:$FB$3,P$7,$Z44:$FB44) | Q44: =SUMIF($Z$3:$FB$3,Q$7,$Z44:$FB44) | R44: =SUMIF($Z$3:$FB$3,R$7,$Z44:$FB44) | S44: =SUMIF($Z$3:$FB$3,S$7,$Z44:$FB44) | T44: =SUMIF($Z$3:$FB$3,T$7,$Z44:$FB44) | U44: =SUMIF($Z$3:$FB$3,U$7,$Z44:$FB44) | ... X44: =SUMIF($Z$3:$FB$3,X$7,$Z44:$FB44) | Z44: 0 | AA44: =$J44/12*AA$14*$C$75 | AB44: =$J44/12*AB$14*$C$75 | AC44: =$J44/12*AC$14*$C$75 | AD44: =$J44/12*AD$14*$C$75 | AE44: =$J44/12*AE$14*$C$75 | AF44: =$J44/12*AF$14*$C$75 | AG44: =$J44/12*AG$14*$C$75 | AH44: =$J44/12*AH$14*$C$75 | ... FB44: =$J44/12*FB$14*$C$75
B45: Lender | D45: TBD | E45: Lender | G45: TBD | I45: R&M | J45: =Inputs!C75 | L45: =SUMIF($Z$4:$FB$4,"<="&$G$18,$Z45:$FB45) | N45: =SUMIF($Z$3:$FB$3,N$7,$Z45:$FB45) | O45: =SUMIF($Z$3:$FB$3,O$7,$Z45:$FB45) | P45: =SUMIF($Z$3:$FB$3,P$7,$Z45:$FB45) | Q45: =SUMIF($Z$3:$FB$3,Q$7,$Z45:$FB45) | R45: =SUMIF($Z$3:$FB$3,R$7,$Z45:$FB45) | S45: =SUMIF($Z$3:$FB$3,S$7,$Z45:$FB45) | T45: =SUMIF($Z$3:$FB$3,T$7,$Z45:$FB45) | U45: =SUMIF($Z$3:$FB$3,U$7,$Z45:$FB45) | ... X45: =SUMIF($Z$3:$FB$3,X$7,$Z45:$FB45) | Z45: 0 | AA45: =$J45/12*AA$14*$C$75 | AB45: =$J45/12*AB$14*$C$75 | AC45: =$J45/12*AC$14*$C$75 | AD45: =$J45/12*AD$14*$C$75 | AE45: =$J45/12*AE$14*$C$75 | AF45: =$J45/12*AF$14*$C$75 | AG45: =$J45/12*AG$14*$C$75 | AH45: =$J45/12*AH$14*$C$75 | ... FB45: =$J45/12*FB$14*$C$75
B46: Loan Proceeds | C46: =D46/D41 | D46: =Inputs!C67 | E46: Loan Proceeds | F46: DSCR | G46: =INDEX($G$52:$G$54,MATCH(F46,$E$52:$E$54,0)) | I46: Contract Service | J46: =Inputs!C76 | L46: =SUMIF($Z$4:$FB$4,"<="&$G$18,$Z46:$FB46) | N46: =SUMIF($Z$3:$FB$3,N$7,$Z46:$FB46) | O46: =SUMIF($Z$3:$FB$3,O$7,$Z46:$FB46) | P46: =SUMIF($Z$3:$FB$3,P$7,$Z46:$FB46) | Q46: =SUMIF($Z$3:$FB$3,Q$7,$Z46:$FB46) | R46: =SUMIF($Z$3:$FB$3,R$7,$Z46:$FB46) | S46: =SUMIF($Z$3:$FB$3,S$7,$Z46:$FB46) | T46: =SUMIF($Z$3:$FB$3,T$7,$Z46:$FB46) | U46: =SUMIF($Z$3:$FB$3,U$7,$Z46:$FB46) | ... X46: =SUMIF($Z$3:$FB$3,X$7,$Z46:$FB46) | Z46: 0 | AA46: =$J46/12*AA$14*$C$75 | AB46: =$J46/12*AB$14*$C$75 | AC46: =$J46/12*AC$14*$C$75 | AD46: =$J46/12*AD$14*$C$75 | AE46: =$J46/12*AE$14*$C$75 | AF46: =$J46/12*AF$14*$C$75 | AG46: =$J46/12*AG$14*$C$75 | AH46: =$J46/12*AH$14*$C$75 | ... FB46: =$J46/12*FB$14*$C$75
B47: Term | C47: =E16 | D47: =EOMONTH(D15,C47-1) | E47: Term | F47: =Inputs!C69 | G47: =EOMONTH(D47,F47-1) | I47: Turnover | J47: =Inputs!C77 | L47: =SUMIF($Z$4:$FB$4,"<="&$G$18,$Z47:$FB47) | N47: =SUMIF($Z$3:$FB$3,N$7,$Z47:$FB47) | O47: =SUMIF($Z$3:$FB$3,O$7,$Z47:$FB47) | P47: =SUMIF($Z$3:$FB$3,P$7,$Z47:$FB47) | Q47: =SUMIF($Z$3:$FB$3,Q$7,$Z47:$FB47) | R47: =SUMIF($Z$3:$FB$3,R$7,$Z47:$FB47) | S47: =SUMIF($Z$3:$FB$3,S$7,$Z47:$FB47) | T47: =SUMIF($Z$3:$FB$3,T$7,$Z47:$FB47) | U47: =SUMIF($Z$3:$FB$3,U$7,$Z47:$FB47) | ... X47: =SUMIF($Z$3:$FB$3,X$7,$Z47:$FB47) | Z47: 0 | AA47: =$J47/12*AA$14*$C$75 | AB47: =$J47/12*AB$14*$C$75 | AC47: =$J47/12*AC$14*$C$75 | AD47: =$J47/12*AD$14*$C$75 | AE47: =$J47/12*AE$14*$C$75 | AF47: =$J47/12*AF$14*$C$75 | AG47: =$J47/12*AG$14*$C$75 | AH47: =$J47/12*AH$14*$C$75 | ... FB47: =$J47/12*FB$14*$C$75
B48: Interest Rate | C48: Fixed | D48: =Inputs!C68 | E48: Interest Rate | F48: Fixed | G48: =C118 | I48: Other | J48: =Inputs!C78 | L48: =SUMIF($Z$4:$FB$4,"<="&$G$18,$Z48:$FB48) | N48: =SUMIF($Z$3:$FB$3,N$7,$Z48:$FB48) | O48: =SUMIF($Z$3:$FB$3,O$7,$Z48:$FB48) | P48: =SUMIF($Z$3:$FB$3,P$7,$Z48:$FB48) | Q48: =SUMIF($Z$3:$FB$3,Q$7,$Z48:$FB48) | R48: =SUMIF($Z$3:$FB$3,R$7,$Z48:$FB48) | S48: =SUMIF($Z$3:$FB$3,S$7,$Z48:$FB48) | T48: =SUMIF($Z$3:$FB$3,T$7,$Z48:$FB48) | U48: =SUMIF($Z$3:$FB$3,U$7,$Z48:$FB48) | ... X48: =SUMIF($Z$3:$FB$3,X$7,$Z48:$FB48) | Z48: 0 | AA48: =$J48/12*AA$14*$C$75 | AB48: =$J48/12*AB$14*$C$75 | AC48: =$J48/12*AC$14*$C$75 | AD48: =$J48/12*AD$14*$C$75 | AE48: =$J48/12*AE$14*$C$75 | AF48: =$J48/12*AF$14*$C$75 | AG48: =$J48/12*AG$14*$C$75 | AH48: =$J48/12*AH$14*$C$75 | ... FB48: =$J48/12*FB$14*$C$75
B49: Financing Costs | C49: =Inputs!C79 | D49: =C49*D46 | E49: Financing Costs | F49: =Inputs!C70 | G49: =F49*G46 | I49: Total Controllable Opex | L49: =SUMIF($Z$4:$FB$4,"<="&$G$18,$Z49:$FB49) | N49: =SUMIF($Z$3:$FB$3,N$7,$Z49:$FB49) | O49: =SUMIF($Z$3:$FB$3,O$7,$Z49:$FB49) | P49: =SUMIF($Z$3:$FB$3,P$7,$Z49:$FB49) | Q49: =SUMIF($Z$3:$FB$3,Q$7,$Z49:$FB49) | R49: =SUMIF($Z$3:$FB$3,R$7,$Z49:$FB49) | S49: =SUMIF($Z$3:$FB$3,S$7,$Z49:$FB49) | T49: =SUMIF($Z$3:$FB$3,T$7,$Z49:$FB49) | U49: =SUMIF($Z$3:$FB$3,U$7,$Z49:$FB49) | ... X49: =SUMIF($Z$3:$FB$3,X$7,$Z49:$FB49) | Z49: =SUM(Z42:Z48) | AA49: =SUM(AA42:AA48) | AB49: =SUM(AB42:AB48) | AC49: =SUM(AC42:AC48) | AD49: =SUM(AD42:AD48) | AE49: =SUM(AE42:AE48) | AF49: =SUM(AF42:AF48) | AG49: =SUM(AG42:AG48) | ... FB49: =SUM(FB42:FB48)
B50: IO Periods/Amortization | C50: =Inputs!C80 | D50: =PMT(D48/12,360,-D46,0,) | E50: IO Periods/Amortization | F50: =Inputs!C71 | G50: =PMT(G48/12,360,-G46,0,)
B51: Debt Metrics | E51: Debt Metrics | I51: Non-controllable Expenses | J51: =J41 | L51: Total
B52: DSCR | D52: =C22/(PMT(6%/12,360,-D46,0)*12) | E52: DSCR | F52: 1.25 | G52: =PV(G48/12,F47,-F22/12/F52) | I52: Insurance | J52: =Inputs!C60 | L52: =SUMIF($Z$4:$FB$4,"<="&$G$18,$Z52:$FB52) | N52: =SUMIF($Z$3:$FB$3,N$7,$Z52:$FB52) | O52: =SUMIF($Z$3:$FB$3,O$7,$Z52:$FB52) | P52: =SUMIF($Z$3:$FB$3,P$7,$Z52:$FB52) | Q52: =SUMIF($Z$3:$FB$3,Q$7,$Z52:$FB52) | R52: =SUMIF($Z$3:$FB$3,R$7,$Z52:$FB52) | S52: =SUMIF($Z$3:$FB$3,S$7,$Z52:$FB52) | T52: =SUMIF($Z$3:$FB$3,T$7,$Z52:$FB52) | U52: =SUMIF($Z$3:$FB$3,U$7,$Z52:$FB52) | ... X52: =SUMIF($Z$3:$FB$3,X$7,$Z52:$FB52) | Z52: 0 | AA52: =$J52/12*AA$14*$C$75 | AB52: =$J52/12*AB$14*$C$75 | AC52: =$J52/12*AC$14*$C$75 | AD52: =$J52/12*AD$14*$C$75 | AE52: =$J52/12*AE$14*$C$75 | AF52: =$J52/12*AF$14*$C$75 | AG52: =$J52/12*AG$14*$C$75 | AH52: =$J52/12*AH$14*$C$75 | ... FB52: =$J52/12*FB$14*$C$75
B53: DY | D53: =C22/D46 | E53: DY | F53: 0.09 | G53: =F22/F53 | I53: Utilities | J53: =Inputs!C61 | L53: =SUMIF($Z$4:$FB$4,"<="&$G$18,$Z53:$FB53) | N53: =SUMIF($Z$3:$FB$3,N$7,$Z53:$FB53) | O53: =SUMIF($Z$3:$FB$3,O$7,$Z53:$FB53) | P53: =SUMIF($Z$3:$FB$3,P$7,$Z53:$FB53) | Q53: =SUMIF($Z$3:$FB$3,Q$7,$Z53:$FB53) | R53: =SUMIF($Z$3:$FB$3,R$7,$Z53:$FB53) | S53: =SUMIF($Z$3:$FB$3,S$7,$Z53:$FB53) | T53: =SUMIF($Z$3:$FB$3,T$7,$Z53:$FB53) | U53: =SUMIF($Z$3:$FB$3,U$7,$Z53:$FB53) | ... X53: =SUMIF($Z$3:$FB$3,X$7,$Z53:$FB53) | Z53: 0 | AA53: =$J53/12*AA$14*$C$75 | AB53: =$J53/12*AB$14*$C$75 | AC53: =$J53/12*AC$14*$C$75 | AD53: =$J53/12*AD$14*$C$75 | AE53: =$J53/12*AE$14*$C$75 | AF53: =$J53/12*AF$14*$C$75 | AG53: =$J53/12*AG$14*$C$75 | AH53: =$J53/12*AH$14*$C$75 | ... FB53: =$J53/12*FB$14*$C$75
E54: LTV | F54: 0.65 | G54: =F54*F24 | I54: =Inputs!C62 | J54: =SUM(AA54:AL54)/C75 | L54: =SUMIF($Z$4:$FB$4,"<="&$G$18,$Z54:$FB54) | N54: =SUMIF($Z$3:$FB$3,N$7,$Z54:$FB54) | O54: =SUMIF($Z$3:$FB$3,O$7,$Z54:$FB54) | P54: =SUMIF($Z$3:$FB$3,P$7,$Z54:$FB54) | Q54: =SUMIF($Z$3:$FB$3,Q$7,$Z54:$FB54) | R54: =SUMIF($Z$3:$FB$3,R$7,$Z54:$FB54) | S54: =SUMIF($Z$3:$FB$3,S$7,$Z54:$FB54) | T54: =SUMIF($Z$3:$FB$3,T$7,$Z54:$FB54) | U54: =SUMIF($Z$3:$FB$3,U$7,$Z54:$FB54) | ... X54: =SUMIF($Z$3:$FB$3,X$7,$Z54:$FB54) | Z54: =($I$54*Z38) | AA54: =($I$54*AA38) | AB54: =($I$54*AB38) | AC54: =($I$54*AC38) | AD54: =($I$54*AD38) | AE54: =($I$54*AE38) | AF54: =($I$54*AF38) | AG54: =($I$54*AG38) | ... FB54: =($I$54*FB38)
B55: FALSE | G55: =G46-D46 | I55: Property Tax | J55: =Inputs!C63 | L55: =SUMIF($Z$4:$FB$4,"<="&$G$18,$Z55:$FB55) | N55: =SUMIF($Z$3:$FB$3,N$7,$Z55:$FB55) | O55: =SUMIF($Z$3:$FB$3,O$7,$Z55:$FB55) | P55: =SUMIF($Z$3:$FB$3,P$7,$Z55:$FB55) | Q55: =SUMIF($Z$3:$FB$3,Q$7,$Z55:$FB55) | R55: =SUMIF($Z$3:$FB$3,R$7,$Z55:$FB55) | S55: =SUMIF($Z$3:$FB$3,S$7,$Z55:$FB55) | T55: =SUMIF($Z$3:$FB$3,T$7,$Z55:$FB55) | U55: =SUMIF($Z$3:$FB$3,U$7,$Z55:$FB55) | ... X55: =SUMIF($Z$3:$FB$3,X$7,$Z55:$FB55) | Z55: 0 | AA55: =$J55/12*AA$14*$C$75 | AB55: =$J55/12*AB$14*$C$75 | AC55: =$J55/12*AC$14*$C$75 | AD55: =$J55/12*AD$14*$C$75 | AE55: =$J55/12*AE$14*$C$75 | AF55: =$J55/12*AF$14*$C$75 | AG55: =$J55/12*AG$14*$C$75 | AH55: =$J55/12*AH$14*$C$75 | ... FB55: =$J55/12*FB$14*$C$75
I56: Total Non-controllable Opex | L56: =SUMIF($Z$4:$FB$4,"<="&$G$18,$Z56:$FB56) | N56: =SUMIF($Z$3:$FB$3,N$7,$Z56:$FB56) | O56: =SUMIF($Z$3:$FB$3,O$7,$Z56:$FB56) | P56: =SUMIF($Z$3:$FB$3,P$7,$Z56:$FB56) | Q56: =SUMIF($Z$3:$FB$3,Q$7,$Z56:$FB56) | R56: =SUMIF($Z$3:$FB$3,R$7,$Z56:$FB56) | S56: =SUMIF($Z$3:$FB$3,S$7,$Z56:$FB56) | T56: =SUMIF($Z$3:$FB$3,T$7,$Z56:$FB56) | U56: =SUMIF($Z$3:$FB$3,U$7,$Z56:$FB56) | ... X56: =SUMIF($Z$3:$FB$3,X$7,$Z56:$FB56) | Z56: =SUM(Z52:Z55) | AA56: =SUM(AA52:AA55) | AB56: =SUM(AB52:AB55) | AC56: =SUM(AC52:AC55) | AD56: =SUM(AD52:AD55) | AE56: =SUM(AE52:AE55) | AF56: =SUM(AF52:AF55) | AG56: =SUM(AG52:AG55) | ... FB56: =SUM(FB52:FB55)
B57: Pro Forma
B58: TRUE | C58: Unit Count | D58: Rent/Unit | E58: Average Size | F58: Rent PSF | G58: Annual Total | I58: Total Opex | L58: =SUMIF($Z$4:$FB$4,"<="&$G$18,$Z58:$FB58) | N58: =SUMIF($Z$3:$FB$3,N$7,$Z58:$FB58) | O58: =SUMIF($Z$3:$FB$3,O$7,$Z58:$FB58) | P58: =SUMIF($Z$3:$FB$3,P$7,$Z58:$FB58) | Q58: =SUMIF($Z$3:$FB$3,Q$7,$Z58:$FB58) | R58: =SUMIF($Z$3:$FB$3,R$7,$Z58:$FB58) | S58: =SUMIF($Z$3:$FB$3,S$7,$Z58:$FB58) | T58: =SUMIF($Z$3:$FB$3,T$7,$Z58:$FB58) | U58: =SUMIF($Z$3:$FB$3,U$7,$Z58:$FB58) | ... X58: =SUMIF($Z$3:$FB$3,X$7,$Z58:$FB58) | Z58: =SUM(Z49,Z56) | AA58: =SUM(AA49,AA56) | AB58: =SUM(AB49,AB56) | AC58: =SUM(AC49,AC56) | AD58: =SUM(AD49,AD56) | AE58: =SUM(AE49,AE56) | AF58: =SUM(AF49,AF56) | AG58: =SUM(AG49,AG56) | ... FB58: =SUM(FB49,FB56)
B59: =Inputs!B96 | C59: =Inputs!C96 | D59: =Inputs!D96 | E59: =Inputs!E96 | F59: =IFERROR(+D59/E59,0) | G59: =D59*C59*12 | I59: Opex Margin | Z59: =IFERROR(Z58/SUM(Z24,Z30),0) | AA59: =IFERROR(AA58/SUM(AA24,AA30),0) | AB59: =IFERROR(AB58/SUM(AB24,AB30),0) | AC59: =IFERROR(AC58/SUM(AC24,AC30),0) | AD59: =IFERROR(AD58/SUM(AD24,AD30),0) | AE59: =IFERROR(AE58/SUM(AE24,AE30),0) | AF59: =IFERROR(AF58/SUM(AF24,AF30),0) | AG59: =IFERROR(AG58/SUM(AG24,AG30),0) | ... FB59: =IFERROR(FB58/SUM(FB24,FB30),0)
B60: =Inputs!B97 | C60: =Inputs!C97 | D60: =Inputs!D97 | E60: =Inputs!E97 | F60: =IFERROR(+D60/E60,0) | G60: =D60*C60*12
B61: =Inputs!B98 | C61: =Inputs!C98 | D61: =Inputs!D98 | E61: =Inputs!E98 | F61: =IFERROR(+D61/E61,0) | G61: =D61*C61*12
B62: =Inputs!B99 | C62: =Inputs!C99 | D62: =Inputs!D99 | E62: =Inputs!E99 | F62: =IFERROR(+D62/E62,0) | G62: =D62*C62*12
B63: =Inputs!B100 | C63: =Inputs!C100 | D63: =Inputs!D100 | E63: =Inputs!E100 | F63: =IFERROR(+D63/E63,0) | G63: =D63*C63*12
B64: =Inputs!B101 | C64: =Inputs!C101 | D64: =Inputs!D101 | E64: =Inputs!E101 | F64: =IFERROR(+D64/E64,0) | G64: =D64*C64*12
B65: =Inputs!B102 | C65: =Inputs!C102 | D65: =Inputs!D102 | E65: =Inputs!E102 | F65: =IFERROR(+D65/E65,0) | G65: =D65*C65*12
B66: =Inputs!B103 | C66: =Inputs!C103 | D66: =Inputs!D103 | E66: =Inputs!E103 | F66: =IFERROR(+D66/E66,0) | G66: =D66*C66*12
B67: =Inputs!B104 | C67: =Inputs!C104 | D67: =Inputs!D104 | E67: =Inputs!E104 | F67: =IFERROR(+D67/E67,0) | G67: =D67*C67*12
B68: =Inputs!B105 | C68: =Inputs!C105 | D68: =Inputs!D105 | E68: =Inputs!E105 | F68: =IFERROR(+D68/E68,0) | G68: =D68*C68*12
B69: =Inputs!B106 | C69: =Inputs!C106 | D69: =Inputs!D106 | E69: =Inputs!E106 | F69: =IFERROR(+D69/E69,0) | G69: =D69*C69*12
B70: =Inputs!B107 | C70: =Inputs!C107 | D70: =Inputs!D107 | E70: =Inputs!E107 | F70: =IFERROR(+D70/E70,0) | G70: =D70*C70*12
B71: =Inputs!B108 | C71: =Inputs!C108 | D71: =Inputs!D108 | E71: =Inputs!E108 | F71: =IFERROR(+D71/E71,0) | G71: =D71*C71*12
B72: =Inputs!B109 | C72: =Inputs!C109 | D72: =Inputs!D109 | E72: =Inputs!E109 | F72: =IFERROR(+D72/E72,0) | G72: =D72*C72*12
B73: =Inputs!B110 | C73: =Inputs!C110 | D73: =Inputs!D110 | E73: =Inputs!E110 | F73: =IFERROR(+D73/E73,0) | G73: =D73*C73*12 | I73: Resi NOI | L73: =SUMIF($Z$4:$FB$4,"<="&$G$18,$Z73:$FB73) | N73: =SUMIF($Z$3:$FB$3,N$7,$Z73:$FB73) | O73: =SUMIF($Z$3:$FB$3,O$7,$Z73:$FB73) | P73: =SUMIF($Z$3:$FB$3,P$7,$Z73:$FB73) | Q73: =SUMIF($Z$3:$FB$3,Q$7,$Z73:$FB73) | R73: =SUMIF($Z$3:$FB$3,R$7,$Z73:$FB73) | S73: =SUMIF($Z$3:$FB$3,S$7,$Z73:$FB73) | T73: =SUMIF($Z$3:$FB$3,T$7,$Z73:$FB73) | U73: =SUMIF($Z$3:$FB$3,U$7,$Z73:$FB73) | ... X73: =SUMIF($Z$3:$FB$3,X$7,$Z73:$FB73) | Z73: =Z38-Z58 | AA73: =AA38-AA58 | AB73: =AB38-AB58 | AC73: =AC38-AC58 | AD73: =AD38-AD58 | AE73: =AE38-AE58 | AF73: =AF38-AF58 | AG73: =AG38-AG58 | ... FB73: =FB38-FB58
B74: =Inputs!B111 | C74: =Inputs!C111 | D74: =Inputs!D111 | E74: =Inputs!E111 | F74: =IFERROR(+D74/E74,0) | G74: =D74*C74*12
B75: Total/Avg | C75: =SUM(C59:C74) | D75: =SUMPRODUCT(D59:D74,$C$59:$C$74)/$C$75 | E75: =SUMPRODUCT(E59:E74,$C$59:$C$74)/$C$75 | F75: =SUMPRODUCT(F59:F74,$C$59:$C$74)/$C$75 | G75: =D75*C75*12 | I75: Capital Expenditures | J75: =J51
I76: Capital Expenditures | J76: =C121 | L76: =SUMIF($Z$4:$FB$4,"<="&$G$18,$Z76:$FB76) | N76: =SUMIF($Z$3:$FB$3,N$7,$Z76:$FB76) | O76: =SUMIF($Z$3:$FB$3,O$7,$Z76:$FB76) | P76: =SUMIF($Z$3:$FB$3,P$7,$Z76:$FB76) | Q76: =SUMIF($Z$3:$FB$3,Q$7,$Z76:$FB76) | R76: =SUMIF($Z$3:$FB$3,R$7,$Z76:$FB76) | S76: =SUMIF($Z$3:$FB$3,S$7,$Z76:$FB76) | T76: =SUMIF($Z$3:$FB$3,T$7,$Z76:$FB76) | U76: =SUMIF($Z$3:$FB$3,U$7,$Z76:$FB76) | ... X76: =SUMIF($Z$3:$FB$3,X$7,$Z76:$FB76) | Z76: 0 | AA76: =$J76/12*AA$14*$C$75 | AB76: =$J76/12*AB$14*$C$75 | AC76: =$J76/12*AC$14*$C$75 | AD76: =$J76/12*AD$14*$C$75 | AE76: =$J76/12*AE$14*$C$75 | AF76: =$J76/12*AF$14*$C$75 | AG76: =$J76/12*AG$14*$C$75 | AH76: =$J76/12*AH$14*$C$75 | ... FB76: =$J76/12*FB$14*$C$75
B77: Other Income | D77: % | E77: Count | F77: $ / Unit / Mo | G77: Annual Total | I77: Total Capex | L77: =SUMIF($Z$4:$FB$4,"<="&$G$18,$Z77:$FB77) | N77: =SUMIF($Z$3:$FB$3,N$7,$Z77:$FB77) | O77: =SUMIF($Z$3:$FB$3,O$7,$Z77:$FB77) | P77: =SUMIF($Z$3:$FB$3,P$7,$Z77:$FB77) | Q77: =SUMIF($Z$3:$FB$3,Q$7,$Z77:$FB77) | R77: =SUMIF($Z$3:$FB$3,R$7,$Z77:$FB77) | S77: =SUMIF($Z$3:$FB$3,S$7,$Z77:$FB77) | T77: =SUMIF($Z$3:$FB$3,T$7,$Z77:$FB77) | U77: =SUMIF($Z$3:$FB$3,U$7,$Z77:$FB77) | ... X77: =SUMIF($Z$3:$FB$3,X$7,$Z77:$FB77) | Z77: 0 | AA77: =SUM(AA76:AA76) | AB77: =SUM(AB76:AB76) | AC77: =SUM(AC76:AC76) | AD77: =SUM(AD76:AD76) | AE77: =SUM(AE76:AE76) | AF77: =SUM(AF76:AF76) | AG77: =SUM(AG76:AG76) | AH77: =SUM(AH76:AH76) | ... FB77: =SUM(FB76:FB76)
B78: RUBS | D78: =Inputs!C87 | E78: =$C$75 | F78: =IFERROR(G78/E78/12,0) | G78: =J53*C75*D78
B79: Parking | E79: =$C$75 | F79: =Inputs!C88 | G79: =F79*E79*12 | I79: NOI After Cap Reserve | L79: =SUMIF($Z$4:$FB$4,"<="&$G$18,$Z79:$FB79) | N79: =SUMIF($Z$3:$FB$3,N$7,$Z79:$FB79) | O79: =SUMIF($Z$3:$FB$3,O$7,$Z79:$FB79) | P79: =SUMIF($Z$3:$FB$3,P$7,$Z79:$FB79) | Q79: =SUMIF($Z$3:$FB$3,Q$7,$Z79:$FB79) | R79: =SUMIF($Z$3:$FB$3,R$7,$Z79:$FB79) | S79: =SUMIF($Z$3:$FB$3,S$7,$Z79:$FB79) | T79: =SUMIF($Z$3:$FB$3,T$7,$Z79:$FB79) | U79: =SUMIF($Z$3:$FB$3,U$7,$Z79:$FB79) | ... X79: =SUMIF($Z$3:$FB$3,X$7,$Z79:$FB79) | Z79: =(Z73-Z77)*(Z4<=$G$18) | AA79: =(AA73-AA77)*(AA4<=$G$18) | AB79: =(AB73-AB77)*(AB4<=$G$18) | AC79: =(AC73-AC77)*(AC4<=$G$18) | AD79: =(AD73-AD77)*(AD4<=$G$18) | AE79: =(AE73-AE77)*(AE4<=$G$18) | AF79: =(AF73-AF77)*(AF4<=$G$18) | AG79: =(AG73-AG77)*(AG4<=$G$18) | ... FB79: =(FB73-FB77)*(FB4<=$G$18)
B80: Other | D80: =G80/$G$75 | E80: =$C$75 | F80: =Inputs!C89 | G80: =E80*F80*12 | N80: =IFERROR(N79/N38,0) | O80: =IFERROR(O79/O38,0) | P80: =IFERROR(P79/P38,0) | Q80: =IFERROR(Q79/Q38,0) | R80: =IFERROR(R79/R38,0) | S80: =IFERROR(S79/S38,0) | T80: =IFERROR(T79/T38,0) | U80: =IFERROR(U79/U38,0) | ... X80: =IFERROR(X79/X38,0)
B81: Total Other Income | D81: =G81/$G$75 | G81: =SUM(G78:G80) | I81: Operating Shortfall | L81: =SUMIF($Z$4:$FB$4,"<="&$G$18,$Z81:$FB81) | N81: =SUMIF($Z$3:$FB$3,N$7,$Z81:$FB81) | O81: =SUMIF($Z$3:$FB$3,O$7,$Z81:$FB81) | P81: =SUMIF($Z$3:$FB$3,P$7,$Z81:$FB81) | Q81: =SUMIF($Z$3:$FB$3,Q$7,$Z81:$FB81) | R81: =SUMIF($Z$3:$FB$3,R$7,$Z81:$FB81) | S81: =SUMIF($Z$3:$FB$3,S$7,$Z81:$FB81) | T81: =SUMIF($Z$3:$FB$3,T$7,$Z81:$FB81) | U81: =SUMIF($Z$3:$FB$3,U$7,$Z81:$FB81) | ... X81: =SUMIF($Z$3:$FB$3,X$7,$Z81:$FB81) | Z81: =IF(Z6<=$F$18,MIN(Z79,0),0) | AA81: =AA79*(AA79<0) | AB81: =AB79*(AB79<0) | AC81: =AC79*(AC79<0) | AD81: =AD79*(AD79<0) | AE81: =AE79*(AE79<0) | AF81: =AF79*(AF79<0) | AG81: =AG79*(AG79<0) | AH81: =AH79*(AH79<0) | ... FB81: =FB79*(FB79<0)
B83: Income Adjustments | C83: =IF(MONTH(D15)=12,YEAR(D15)+1,YEAR(D15)) | D83: =C83+1 | E83: =D83+1 | F83: =E83+1 | G83: =F83+1 | I83: TTM NOI | L83: =INDEX($Z$83:$FB$83,MATCH(G18,$Z$4:$FB$4,0)) | N83: =SUMIF($Z$3:$FB$3,N$7,$Z83:$FB83) | O83: =SUMIF($Z$3:$FB$3,O$7,$Z83:$FB83) | P83: =SUMIF($Z$3:$FB$3,P$7,$Z83:$FB83) | Q83: =SUMIF($Z$3:$FB$3,Q$7,$Z83:$FB83) | R83: =SUMIF($Z$3:$FB$3,R$7,$Z83:$FB83) | S83: =SUMIF($Z$3:$FB$3,S$7,$Z83:$FB83) | T83: =SUMIF($Z$3:$FB$3,T$7,$Z83:$FB83) | U83: =SUMIF($Z$3:$FB$3,U$7,$Z83:$FB83) | ... X83: =SUMIF($Z$3:$FB$3,X$7,$Z83:$FB83) | Z83: =IF(Z$4>12,SUM(OFFSET(Z79,,,,-12)),0) | AA83: =IF(AA$4>12,SUM(OFFSET(AA79,,,,-12)),0) | AB83: =IF(AB$4>12,SUM(OFFSET(AB79,,,,-12)),0) | AC83: =IF(AC$4>12,SUM(OFFSET(AC79,,,,-12)),0) | AD83: =IF(AD$4>12,SUM(OFFSET(AD79,,,,-12)),0) | AE83: =IF(AE$4>12,SUM(OFFSET(AE79,,,,-12)),0) | AF83: =IF(AF$4>12,SUM(OFFSET(AF79,,,,-12)),0) | AG83: =IF(AG$4>12,SUM(OFFSET(AG79,,,,-12)),0) | ... FB83: =IF(FB$4>12,SUM(OFFSET(FB79,,,,-12)),0)
B84: Loss to Lease | C84: =Inputs!C24 | D84: =Inputs!C29 | E84: =Inputs!C34 | F84: =Inputs!C39 | G84: =Inputs!C44 | I84: Cap Rate | L84: =SUMIF($Z$4:$FB$4,"<="&$G$18,$Z84:$FB84) | N84: =SUMIF($Z$3:$FB$3,N$7,$Z84:$FB84) | O84: =SUMIF($Z$3:$FB$3,O$7,$Z84:$FB84) | P84: =SUMIF($Z$3:$FB$3,P$7,$Z84:$FB84) | Q84: =SUMIF($Z$3:$FB$3,Q$7,$Z84:$FB84) | R84: =SUMIF($Z$3:$FB$3,R$7,$Z84:$FB84) | S84: =SUMIF($Z$3:$FB$3,S$7,$Z84:$FB84) | T84: =SUMIF($Z$3:$FB$3,T$7,$Z84:$FB84) | U84: =SUMIF($Z$3:$FB$3,U$7,$Z84:$FB84) | ... X84: =SUMIF($Z$3:$FB$3,X$7,$Z84:$FB84) | Z84: =(Z4=$G$18)*$G$23 | AA84: =(AA4=$G$18)*$G$23 | AB84: =(AB4=$G$18)*$G$23 | AC84: =(AC4=$G$18)*$G$23 | AD84: =(AD4=$G$18)*$G$23 | AE84: =(AE4=$G$18)*$G$23 | AF84: =(AF4=$G$18)*$G$23 | AG84: =(AG4=$G$18)*$G$23 | ... FB84: =(FB4=$G$18)*$G$23
B85: Vacancy Loss | C85: =Inputs!C25 | D85: =Inputs!C30 | E85: =Inputs!C35 | F85: =Inputs!C40 | G85: =Inputs!C45 | I85: Gross Sales Proceeds | L85: =SUMIF($Z$4:$FB$4,"<="&$G$18,$Z85:$FB85) | N85: =SUMIF($Z$3:$FB$3,N$7,$Z85:$FB85) | O85: =SUMIF($Z$3:$FB$3,O$7,$Z85:$FB85) | P85: =SUMIF($Z$3:$FB$3,P$7,$Z85:$FB85) | Q85: =SUMIF($Z$3:$FB$3,Q$7,$Z85:$FB85) | R85: =SUMIF($Z$3:$FB$3,R$7,$Z85:$FB85) | S85: =SUMIF($Z$3:$FB$3,S$7,$Z85:$FB85) | T85: =SUMIF($Z$3:$FB$3,T$7,$Z85:$FB85) | U85: =SUMIF($Z$3:$FB$3,U$7,$Z85:$FB85) | ... X85: =SUMIF($Z$3:$FB$3,X$7,$Z85:$FB85) | Z85: =IFERROR(Z83/Z84,0) | AA85: =IFERROR(AA83/AA84,0) | AB85: =IFERROR(AB83/AB84,0) | AC85: =IFERROR(AC83/AC84,0) | AD85: =IFERROR(AD83/AD84,0) | AE85: =IFERROR(AE83/AE84,0) | AF85: =IFERROR(AF83/AF84,0) | AG85: =IFERROR(AG83/AG84,0) | ... FB85: =IFERROR(FB83/FB84,0)
B86: Bad Debt | C86: =Inputs!C26 | D86: =Inputs!C31 | E86: =Inputs!C36 | F86: =Inputs!C41 | G86: =Inputs!C46 | I86: $/Unit | L86: =SUMIF($Z$4:$FB$4,"<="&$G$18,$Z86:$FB86) | Z86: =Z85/$C$75 | AA86: =AA85/$C$75 | AB86: =AB85/$C$75 | AC86: =AC85/$C$75 | AD86: =AD85/$C$75 | AE86: =AE85/$C$75 | AF86: =AF85/$C$75 | AG86: =AG85/$C$75 | ... FB86: =FB85/$C$75
B87: Concessions | C87: =Inputs!C27 | D87: =Inputs!C32 | E87: =Inputs!C37 | F87: =Inputs!C42 | G87: =Inputs!C47
B88: Model Units | C88: =Inputs!C28 | D88: =Inputs!C33 | E88: =Inputs!C38 | F88: =Inputs!C43 | G88: =Inputs!C48 | I88: Sales Costs | L88: =SUMIF($Z$4:$FB$4,"<="&$G$18,$Z88:$FB88) | N88: =SUMIF($Z$3:$FB$3,N$7,$Z88:$FB88) | O88: =SUMIF($Z$3:$FB$3,O$7,$Z88:$FB88) | P88: =SUMIF($Z$3:$FB$3,P$7,$Z88:$FB88) | Q88: =SUMIF($Z$3:$FB$3,Q$7,$Z88:$FB88) | R88: =SUMIF($Z$3:$FB$3,R$7,$Z88:$FB88) | S88: =SUMIF($Z$3:$FB$3,S$7,$Z88:$FB88) | T88: =SUMIF($Z$3:$FB$3,T$7,$Z88:$FB88) | U88: =SUMIF($Z$3:$FB$3,U$7,$Z88:$FB88) | ... X88: =SUMIF($Z$3:$FB$3,X$7,$Z88:$FB88) | Z88: =Z85*-$E$26 | AA88: =AA85*-$E$26 | AB88: =AB85*-$E$26 | AC88: =AC85*-$E$26 | AD88: =AD85*-$E$26 | AE88: =AE85*-$E$26 | AF88: =AF85*-$E$26 | AG88: =AG85*-$E$26 | ... FB88: =FB85*-$E$26
B89: Growth Assumptions | C89: =IF(MONTH(D15)=12,YEAR(D15)+1,YEAR(D15)) | D89: =C89+1 | E89: =D89+1 | F89: =E89+1 | G89: =F89+1 | I89: Net Sales Proceeds | L89: =SUMIF($Z$4:$FB$4,"<="&$G$18,$Z89:$FB89) | N89: =SUMIF($Z$3:$FB$3,N$7,$Z89:$FB89) | O89: =SUMIF($Z$3:$FB$3,O$7,$Z89:$FB89) | P89: =SUMIF($Z$3:$FB$3,P$7,$Z89:$FB89) | Q89: =SUMIF($Z$3:$FB$3,Q$7,$Z89:$FB89) | R89: =SUMIF($Z$3:$FB$3,R$7,$Z89:$FB89) | S89: =SUMIF($Z$3:$FB$3,S$7,$Z89:$FB89) | T89: =SUMIF($Z$3:$FB$3,T$7,$Z89:$FB89) | U89: =SUMIF($Z$3:$FB$3,U$7,$Z89:$FB89) | ... X89: =SUMIF($Z$3:$FB$3,X$7,$Z89:$FB89) | Z89: =SUM(Z85,Z88) | AA89: =SUM(AA85,AA88) | AB89: =SUM(AB85,AB88) | AC89: =SUM(AC85,AC88) | AD89: =SUM(AD85,AD88) | AE89: =SUM(AE85,AE88) | AF89: =SUM(AF85,AF88) | AG89: =SUM(AG85,AG88) | ... FB89: =SUM(FB85,FB88)
B90: Market Rent | C90: =C119 | D90: =C90 | E90: =D90 | F90: =E90 | G90: =F90
B91: Other Income | C91: =C90 | D91: =C91 | E91: =D91 | F91: =E91 | G91: =F91 | I91: Unlevered Cash Flow
B92: Operating Expenses | C92: =C120 | D92: =C92 | E92: =D92 | F92: =E92 | G92: =F92 | I92: NOI | L92: =SUMIF($Z$4:$FB$4,"<="&$G$18,$Z92:$FB92) | N92: =SUMIF($Z$3:$FB$3,N$7,$Z92:$FB92) | O92: =SUMIF($Z$3:$FB$3,O$7,$Z92:$FB92) | P92: =SUMIF($Z$3:$FB$3,P$7,$Z92:$FB92) | Q92: =SUMIF($Z$3:$FB$3,Q$7,$Z92:$FB92) | R92: =SUMIF($Z$3:$FB$3,R$7,$Z92:$FB92) | S92: =SUMIF($Z$3:$FB$3,S$7,$Z92:$FB92) | T92: =SUMIF($Z$3:$FB$3,T$7,$Z92:$FB92) | U92: =SUMIF($Z$3:$FB$3,U$7,$Z92:$FB92) | ... X92: =SUMIF($Z$3:$FB$3,X$7,$Z92:$FB92) | Z92: =Z79*(Z4<=$G$18) | AA92: =AA79*(AA4<=$G$18) | AB92: =AB79*(AB4<=$G$18) | AC92: =AC79*(AC4<=$G$18) | AD92: =AD79*(AD4<=$G$18) | AE92: =AE79*(AE4<=$G$18) | AF92: =AF79*(AF4<=$G$18) | AG92: =AG79*(AG4<=$G$18) | ... FB92: =FB79*(FB4<=$G$18)
B93: Property Taxes | C93: =C92 | D93: =C93 | E93: =D93 | F93: =E93 | G93: =F93 | I93: Net Sales Proceeds | L93: =SUMIF($Z$4:$FB$4,"<="&$G$18,$Z93:$FB93) | N93: =SUMIF($Z$3:$FB$3,N$7,$Z93:$FB93) | O93: =SUMIF($Z$3:$FB$3,O$7,$Z93:$FB93) | P93: =SUMIF($Z$3:$FB$3,P$7,$Z93:$FB93) | Q93: =SUMIF($Z$3:$FB$3,Q$7,$Z93:$FB93) | R93: =SUMIF($Z$3:$FB$3,R$7,$Z93:$FB93) | S93: =SUMIF($Z$3:$FB$3,S$7,$Z93:$FB93) | T93: =SUMIF($Z$3:$FB$3,T$7,$Z93:$FB93) | U93: =SUMIF($Z$3:$FB$3,U$7,$Z93:$FB93) | ... X93: =SUMIF($Z$3:$FB$3,X$7,$Z93:$FB93) | Z93: =Z89 | AA93: =AA89 | AB93: =AB89 | AC93: =AC89 | AD93: =AD89 | AE93: =AE89 | AF93: =AF89 | AG93: =AG89 | ... FB93: =FB89
I94: =B37 | L94: =SUMIF($Z$4:$FB$4,"<="&$G$18,$Z94:$FB94) | N94: =SUMIF($Z$3:$FB$3,N$7,$Z94:$FB94) | O94: =SUMIF($Z$3:$FB$3,O$7,$Z94:$FB94) | P94: =SUMIF($Z$3:$FB$3,P$7,$Z94:$FB94) | Q94: =SUMIF($Z$3:$FB$3,Q$7,$Z94:$FB94) | R94: =SUMIF($Z$3:$FB$3,R$7,$Z94:$FB94) | S94: =SUMIF($Z$3:$FB$3,S$7,$Z94:$FB94) | T94: =SUMIF($Z$3:$FB$3,T$7,$Z94:$FB94) | U94: =SUMIF($Z$3:$FB$3,U$7,$Z94:$FB94) | ... X94: =SUMIF($Z$3:$FB$3,X$7,$Z94:$FB94) | Z94: =IF(Z$4=0,-$D37*$E37,-($D37*(1-$E37))/$G37*(Z$4>=$F37)*(Z$4<=($F37+$G37-1))) | AA94: =IF(AA$4=0,-$D37*$E37,-($D37*(1-$E37))/$G37*(AA$4>=$F37)*(AA$4<=($F37+$G37-1))) | AB94: =IF(AB$4=0,-$D37*$E37,-($D37*(1-$E37))/$G37*(AB$4>=$F37)*(AB$4<=($F37+$G37-1))) | AC94: =IF(AC$4=0,-$D37*$E37,-($D37*(1-$E37))/$G37*(AC$4>=$F37)*(AC$4<=($F37+$G37-1))) | AD94: =IF(AD$4=0,-$D37*$E37,-($D37*(1-$E37))/$G37*(AD$4>=$F37)*(AD$4<=($F37+$G37-1))) | AE94: =IF(AE$4=0,-$D37*$E37,-($D37*(1-$E37))/$G37*(AE$4>=$F37)*(AE$4<=($F37+$G37-1))) | AF94: =IF(AF$4=0,-$D37*$E37,-($D37*(1-$E37))/$G37*(AF$4>=$F37)*(AF$4<=($F37+$G37-1))) | AG94: =IF(AG$4=0,-$D37*$E37,-($D37*(1-$E37))/$G37*(AG$4>=$F37)*(AG$4<=($F37+$G37-1))) | ... FB94: =IF(FB$4=0,-$D37*$E37,-($D37*(1-$E37))/$G37*(FB$4>=$F37)*(FB$4<=($F37+$G37-1)))
B95: Property Taxes | I95: Closing Costs | L95: =SUMIF($Z$4:$FB$4,"<="&$G$18,$Z95:$FB95) | N95: =SUMIF($Z$3:$FB$3,N$7,$Z95:$FB95) | O95: =SUMIF($Z$3:$FB$3,O$7,$Z95:$FB95) | P95: =SUMIF($Z$3:$FB$3,P$7,$Z95:$FB95) | Q95: =SUMIF($Z$3:$FB$3,Q$7,$Z95:$FB95) | R95: =SUMIF($Z$3:$FB$3,R$7,$Z95:$FB95) | S95: =SUMIF($Z$3:$FB$3,S$7,$Z95:$FB95) | T95: =SUMIF($Z$3:$FB$3,T$7,$Z95:$FB95) | U95: =SUMIF($Z$3:$FB$3,U$7,$Z95:$FB95) | ... X95: =SUMIF($Z$3:$FB$3,X$7,$Z95:$FB95) | Z95: =IF(Z$4=0,-$D38*$E38,-($D38*(1-$E38))/$G38*(Z$4>=$F38)*(Z$4<=($F38+$G38-1))) | AA95: =IF(AA$4=0,-$D38*$E38,-($D38*(1-$E38))/$G38*(AA$4>=$F38)*(AA$4<=($F38+$G38-1))) | AB95: =IF(AB$4=0,-$D38*$E38,-($D38*(1-$E38))/$G38*(AB$4>=$F38)*(AB$4<=($F38+$G38-1))) | AC95: =IF(AC$4=0,-$D38*$E38,-($D38*(1-$E38))/$G38*(AC$4>=$F38)*(AC$4<=($F38+$G38-1))) | AD95: =IF(AD$4=0,-$D38*$E38,-($D38*(1-$E38))/$G38*(AD$4>=$F38)*(AD$4<=($F38+$G38-1))) | AE95: =IF(AE$4=0,-$D38*$E38,-($D38*(1-$E38))/$G38*(AE$4>=$F38)*(AE$4<=($F38+$G38-1))) | AF95: =IF(AF$4=0,-$D38*$E38,-($D38*(1-$E38))/$G38*(AF$4>=$F38)*(AF$4<=($F38+$G38-1))) | AG95: =IF(AG$4=0,-$D38*$E38,-($D38*(1-$E38))/$G38*(AG$4>=$F38)*(AG$4<=($F38+$G38-1))) | ... FB95: =IF(FB$4=0,-$D38*$E38,-($D38*(1-$E38))/$G38*(FB$4>=$F38)*(FB$4<=($F38+$G38-1)))
D96: Current | E96: Next Buyer | F96: Note | I96: Other Cost | L96: =SUMIF($Z$4:$FB$4,"<="&$G$18,$Z96:$FB96) | N96: =SUMIF($Z$3:$FB$3,N$7,$Z96:$FB96) | O96: =SUMIF($Z$3:$FB$3,O$7,$Z96:$FB96) | P96: =SUMIF($Z$3:$FB$3,P$7,$Z96:$FB96) | Q96: =SUMIF($Z$3:$FB$3,Q$7,$Z96:$FB96) | R96: =SUMIF($Z$3:$FB$3,R$7,$Z96:$FB96) | S96: =SUMIF($Z$3:$FB$3,S$7,$Z96:$FB96) | T96: =SUMIF($Z$3:$FB$3,T$7,$Z96:$FB96) | U96: =SUMIF($Z$3:$FB$3,U$7,$Z96:$FB96) | ... X96: =SUMIF($Z$3:$FB$3,X$7,$Z96:$FB96) | Z96: =IF(Z$4=0,-$D39*$E39,-($D39*(1-$E39))/$G39*(Z$4>=$F39)*(Z$4<=($F39+$G39-1))) | AA96: =IF(AA$4=0,-$D39*$E39,-($D39*(1-$E39))/$G39*(AA$4>=$F39)*(AA$4<=($F39+$G39-1))) | AB96: =IF(AB$4=0,-$D39*$E39,-($D39*(1-$E39))/$G39*(AB$4>=$F39)*(AB$4<=($F39+$G39-1))) | AC96: =IF(AC$4=0,-$D39*$E39,-($D39*(1-$E39))/$G39*(AC$4>=$F39)*(AC$4<=($F39+$G39-1))) | AD96: =IF(AD$4=0,-$D39*$E39,-($D39*(1-$E39))/$G39*(AD$4>=$F39)*(AD$4<=($F39+$G39-1))) | AE96: =IF(AE$4=0,-$D39*$E39,-($D39*(1-$E39))/$G39*(AE$4>=$F39)*(AE$4<=($F39+$G39-1))) | AF96: =IF(AF$4=0,-$D39*$E39,-($D39*(1-$E39))/$G39*(AF$4>=$F39)*(AF$4<=($F39+$G39-1))) | AG96: =IF(AG$4=0,-$D39*$E39,-($D39*(1-$E39))/$G39*(AG$4>=$F39)*(AG$4<=($F39+$G39-1))) | ... FB96: =IF(FB$4=0,-$D39*$E39,-($D39*(1-$E39))/$G39*(FB$4>=$F39)*(FB$4<=($F39+$G39-1)))
B97: Assessed Value | D97: =Inputs!C49 | E97: =Inputs!C52 | I97: Unlevered Cash Flow | L97: =SUMIF($Z$4:$FB$4,"<="&$G$18,$Z97:$FB97) | N97: =SUMIF($Z$3:$FB$3,N$7,$Z97:$FB97) | O97: =SUMIF($Z$3:$FB$3,O$7,$Z97:$FB97) | P97: =SUMIF($Z$3:$FB$3,P$7,$Z97:$FB97) | Q97: =SUMIF($Z$3:$FB$3,Q$7,$Z97:$FB97) | R97: =SUMIF($Z$3:$FB$3,R$7,$Z97:$FB97) | S97: =SUMIF($Z$3:$FB$3,S$7,$Z97:$FB97) | T97: =SUMIF($Z$3:$FB$3,T$7,$Z97:$FB97) | U97: =SUMIF($Z$3:$FB$3,U$7,$Z97:$FB97) | ... X97: =SUMIF($Z$3:$FB$3,X$7,$Z97:$FB97) | Z97: =SUM(Z92:Z96) | AA97: =SUM(AA92:AA96) | AB97: =SUM(AB92:AB96) | AC97: =SUM(AC92:AC96) | AD97: =SUM(AD92:AD96) | AE97: =SUM(AE92:AE96) | AF97: =SUM(AF92:AF96) | AG97: =SUM(AG92:AG96) | ... FB97: =SUM(FB92:FB96)
B98: Assessed Value/Unit | D98: =Inputs!C50 | E98: =Inputs!C53 | J98: Net Profit | L98: =L97
B99: Assessment % | D99: =Inputs!C51 | E99: =Inputs!C54 | J99: Peak Equity | L99: =SUMIF(Z97:FB97,"<0",Z97:FB97) | Z99: =IF(Z$4=0,-$D37*$E37,($D37-$Z94)/$G37)*(Z$4>=$F$37)*(Z$4<=($F37+$G37-1)) | AA99: =IF(AA$4=0,-$D37*$E37,($D37-$Z94)/$G37)*(AA$4>=$F$37)*(AA$4<=($F37+$G37-1)) | AB99: =IF(AB$4=0,-$D37*$E37,($D37-$Z94)/$G37)*(AB$4>=$F$37)*(AB$4<=($F37+$G37-1)) | AC99: =IF(AC$4=0,-$D37*$E37,($D37-$Z94)/$G37)*(AC$4>=$F$37)*(AC$4<=($F37+$G37-1))
B100: Millage Rate | D100: =Inputs!C91 | E100: =Inputs!C91 | J100: IRR | L100: =(1+IRR(Z97:FB97,0))^12-1
B101: Special Assessment | D101: =Inputs!C92 | E101: =Inputs!C92 | J101: Equity Multiple | L101: =(L98-L99)/-L99
B102: Total Property Tax | D102: =D97*D100 | E102: =E97*E100
B103: Total Property Tax/Unit | D103: =D102/$C$75 | E103: =E102/$C$75 | I103: Levered Cash Flow
...

Sheet Inputs
B3: Item | C3: Value
B4: Acquisition Date BOP Mo | C4: 0
B5: Acquisition Date BOP Date | C5: 46174
B6: Acquisition Date Duration | C6: 0
B7: Senior/Bridge Loan Term (Months) | C7: 24
B8: NOI T-12 | C8: 557219.86
B9: Cap Rate Aequitas Valuation | C9: 0.083167144
B10: Total Sales Cost | C10: 0.02
B11: Closing Costs | C11: 0.0075
B12: Acquisition Price at Closing | C12: 1
B13: Closing Costs at Closing | C13: 1
B14: Working Capital/Reserve at Closing | C14: 1
B15: Financing Costs at Closing | C15: 1
... B80: Senior IO Periods/Amortization | C80: 24
B81: Property Name | C81: Milestone and Trails Portfolio
B82: Property Address | C82: 5070 Warm Springs Rd & 4531 Milgen Rd, Columbus, GA
B83: Hold Period (Years) | C83: 10
B84: Purchase Price | C84: 6700000
B85: Working Capital/Reserve Amount | C85: 495432.59
B86: LP Equity Share | C86: 0.85
B87: RUBS % | C87: 0.7
B88: Parking $/Unit/Mo | C88: 0
B89: Other Income $/Unit/Mo | C89: 75
B90: Pari Passu (1=Yes, 0=No) | C90: 0
B91: Millage Rate | C91: 0.018926798
B92: Special Assessment | C92: 0
B94: Unit Mix
B95: Unit Type | C95: Count | D95: Rent/Unit | E95: Avg Size
B96: 2bd/2ba - 5070 | C96: 32 | D96: 1230.39 | E96: 1100
B97: 2bd/2ba - 4531 | C97: 24 | D97: 1241.67 | E97: 1250
C98: 0 | D98: 0 | E98: 0
C99: 0 | D99: 0 | E99: 0
C100: 0 | D100: 0 | E100: 0
C101: 0 | D101: 0 | E101: 0
C102: 0 | D102: 0 | E102: 0
C103: 0 | D103: 0 | E103: 0
C104: 0 | D104: 0 | E104: 0
C105: 0 | D105: 0 | E105: 0
C106: 0 | D106: 0 | E106: 0
C107: 0 | D107: 0 | E107: 0
C108: 0 | D108: 0 | E108: 0
C109: 0 | D109: 0 | E109: 0
... C111: 0 | D111: 0 | E111: 0
