Workbook
Name ______new1: #REF!
Name _____new1: #REF!
Name ___new1: #REF!
Name __new1: #REF!
Name _2004: #REF!
Name _2005: #REF!
Name _2006: #REF!
Name _2007: #REF!
Name _2008: #REF!
Name _2009: #REF!
Name _2010: #REF!
Name _2011: #REF!
Name _2012: #REF!
Name _2013: #REF!
Name _2013_: #REF!
Name _2014: #REF!
Name _2015: #REF!
Name _2016: #REF!
Name _2017: #REF!
Name _2018: #REF!
Name _2020: #REF!
Name _3000: #REF!
Name _3010: #REF!
Name _3019: #REF!
Name _3310: #REF!
Name _4320: #REF!
Name _4355: #REF!
Name _4405: #REF!
Name _4410: #REF!
Name _4445: #REF!
Name _4450: #REF!
Name _4452: #REF!
Name _4453: #REF!
Name _4480: #REF!
Name _4485: #REF!
Name _4496: #REF!
Name _4505: #REF!
Name _4555: #REF!
Name _4560: #REF!
Name _4710: #REF!
Name _4715: #REF!
Name _4830: #REF!
Name _4848: #REF!
Name _ADM2000: #REF!
Name _ADM2001: #REF!
Name _Bud02: #REF!
Name _Bud03: #REF!
Name _CAM96: #REF!
Name _CAM97: #REF!
Name _CAM98: #REF!
Name _DPU95: #REF!
Name _end1: IF([0]!Loan_Amount*[0]!Interest_Rate*[0]!Loan_Years*[0]!Loan_Start>0,1,0)
Name _EPU01: #REF!
Name _EPU02: #REF!
Name _EPU03: #REF!
Name _EPU04: #REF!
Name _EPU96: #REF!
Name _EPU97: #REF!
Name _EPU98: #REF!
Name _EPU99: #REF!

Sheet Underwriting
E1: Mo | F1: =F53 -> 0 | G1: =G53 -> 1 | H1: =H53 -> 2 | I1: =I53 -> 3 | J1: =J53 -> 4 | K1: =K53 -> 5 | L1: =L53 -> 6 | M1: =M53 -> 7 | ... FD1: =FD53 -> 154
E2: Date | F2: =F55 -> 46203 | G2: =G55 -> 46234 | H2: =H55 -> 46265 | I2: =I55 -> 46295 | J2: =J55 -> 46326 | K2: =K55 -> 46356 | L2: =L55 -> 46387 | M2: =M55 -> 46418 | ... FD2: =FD55 -> 50890
C3: Base Assumptions
C4: # | D4: 101 | AN4: Under Construction
C5: Property Name: | D5: 1424 Wake Forest Dr
C6: Address: | D6: 1424 Wake Forest Dr, Davis, CA | AN6: In Lease Up
C7: Timeline | K7: Income Analysis | S7: ACF Analysis | AH7: Sensitivities - Aequitas IRR/EM
E8: BOP Mo | F8: BOP Date | G8: Duration | H8: EOP Date | I8: EOP Mo | K8: MR Unit Breakdown | N8: Unit Count | O8: Rent/Unit | P8: Average Size | Q8: Rent PSF | U8: Pro Forma | AA8: Historical Financials | AH8: Senior Loan Interest Rate | AI8: =AJ8+0.25% -> 0.0775 | AJ8: =AK8+0.25% -> 0.075 | AK8: =AL8+0.25% -> 0.0725 | AL8: 0.07 | AM8: =AL8-0.25% -> 0.0675 | AN8: =AM8-0.25% -> 0.065 | AO8: =AN8-0.25% -> 0.0625
C9: Acquisition Date | E9: 0 | F9: 46203 | G9: 1 | H9: =EOMONTH(F9,E9) -> 46203 | I9: =INDEX($F$53:$FV$53,MATCH(H9,$F$55:$FV$55,0)) -> 0 | K9: Studio | N9: 0 | O9: 0 | P9: 0 | Q9: =IFERROR(+O9/P9,0) -> 0 | U9: Untrended | V9: $/Unit | W9: Refinance | X9: $/Unit | Y9: At Exit | Z9: $/Unit | AA9: T-3 | AB9: $/Unit | AC9: T-6 | AD9: $/Unit | AE9: T-12 | AF9: $/Unit | AH9: =CONCATENATE(TEXT($G$48,"0.00%")," / ",TEXT($G$49,"0.00x")) -> 16.80% / 2.40x | AI9: 15.30% / 2.36x | AJ9: 15.77% / 2.37x | AK9: 16.27% / 2.39x | AL9: 16.80% / 2.40x | AM9: 17.37% / 2.42x | AN9: 17.98% / 2.44x | AO9: 18.63% / 2.45x
C10: Hold Period | E10: =INDEX($F$53:$FV$53,MATCH(F10,$F$55:$FV$55,0)) -> 1 | F10: =EOMONTH(H9,1) -> 46234 | G10: 36 | H10: =EOMONTH(F10,G10-1) -> 47299 | I10: =INDEX($F$53:$FV$53,MATCH(H10,$F$55:$FV$55,0)) -> 36 | K10: 1 Bedroom | N10: 63 | O10: 1900 | P10: 766 | Q10: =IFERROR(+O10/P10,0) -> 2.4804178 | S10: Potential Market Rent | U10: =V10*$N$13*12 -> 1436400 | V10: =O13 -> 1900 | W10: =SUM(OFFSET(F71,0,$G$16,1,-12)) -> 1550119.4 | X10: =W10/$N$13 -> 24605.07 | Y10: =SUM(OFFSET(F71,0,$I$16,1,-12)) -> 1800644.7 | Z10: =Y10/$N$13 -> 28581.662 | AA10: 0 | AB10: =AA10/$N$13 -> 0 | AC10: 0 | AD10: =AC10/$N$13 -> 0 | AE10: 0 | AF10: =AE10/$N$13 -> 0 | AH10: General Inflation | AI10: =AJ10+0.25% -> 0.0375 | AJ10: =AK10+0.25% -> 0.035 | AK10: =AL10+0.25% -> 0.0325 | AL10: 0.03 | AM10: =AL10-0.5% -> 0.025 | AN10: =AM10-0.5% -> 0.02 | AO10: =AN10-0.5% -> 0.015
C11: Refinance | E11: =INDEX($F$53:$FV$53,MATCH(F11,$F$55:$FV$55,0)) -> 36 | F11: =EOMONTH(H10,0) -> 47299 | G11: 1 | H11: =EOMONTH(F11,G11-1) -> 47299 | I11: =INDEX($F$53:$FV$53,MATCH(H11,$F$55:$FV$55,0)) -> 36 | K11: 2 Bedroom | N11: 0 | O11: 0 | P11: 0 | Q11: =IFERROR(+O11/P11,0) -> 0 | S11: Loss to Lease | U11: 0 | V11: =U11/$N$13 -> 0 | W11: =SUM(OFFSET(F72,0,$G$16,1,-12)) -> -19376.493 | X11: =W11/$N$13 -> -307.56338 | Y11: =SUM(OFFSET(F72,0,$I$16,1,-12)) -> -22508.059 | Z11: =Y11/$N$13 -> -357.27078 | AA11: 0 | AB11: =AA11/$N$13 -> 0 | AC11: 0 | AD11: =AC11/$N$13 -> 0 | AE11: 0 | AF11: =AE11/$N$13 -> 0 | AH11: =CONCATENATE(TEXT($G$48,"0.00%")," / ",TEXT($G$49,"0.00x")) -> 16.80% / 2.40x | AI11: 18.49% / 2.61x | AJ11: 17.93% / 2.54x | AK11: 17.37% / 2.47x | AL11: 16.80% / 2.40x | AM11: 15.66% / 2.27x | AN11: 14.50% / 2.14x | AO11: 13.32% / 2.02x
C12: Hold Period | D12: 8 | E12: =INDEX($F$53:$FV$53,MATCH(F12,$F$55:$FV$55,0)) -> 37 | F12: =EOMONTH(H11,1) -> 47330 | G12: =I12-E12+1 -> 60 | H12: =EOMONTH(F9,D12*12) -> 49125 | I12: =INDEX($F$53:$FV$53,MATCH(H12,$F$55:$FV$55,0)) -> 96 | K12: 3 Bedroom | N12: 0 | O12: 0 | P12: 0 | Q12: =IFERROR(+O12/P12,0) -> 0 | S12: Gross Potential Rent | U12: =SUM(U10:U11) -> 1436400 | V12: =SUM(V10:V11) -> 1900 | W12: =SUM(W10:W11) -> 1530742.9 | X12: =W12/$N$13 -> 24297.507 | Y12: =SUM(Y10:Y11) -> 1778136.7 | Z12: =Y12/$N$13 -> 28224.392 | AA12: =SUM(AA10:AA11) -> 0 | AB12: =AA12/$N$13 -> 0 | AC12: =SUM(AC10:AC11) -> 0 | AD12: =AC12/$N$13 -> 0 | AE12: =SUM(AE10:AE11) -> 0 | AF12: =AE12/$N$13 -> 0 | AH12: Cap Reserve ($/Unit) | AI12: 500 | AJ12: =AI12+250 -> 750 | AK12: =AJ12+250 -> 1000 | AL12: =AK12+250 -> 1250 | AM12: =AL12+250 -> 1500 | AN12: =AM12+250 -> 1750 | AO12: =AN12+250 -> 2000
K13: Total/Avg (MR+BMR) | N13: =SUM(N9:N12) -> 63 | O13: =SUMPRODUCT(O9:O12,$N$9:$N$12)/$N$13 -> 1900 | P13: =SUMPRODUCT(P9:P12,$N$9:$N$12)/$N$13 -> 766 | Q13: =SUMPRODUCT(Q9:Q12,$N$9:$N$12)/$N$13 -> 2.4804178 | AH13: =CONCATENATE(TEXT($G$48,"0.00%")," / ",TEXT($G$49,"0.00x")) -> 16.80% / 2.40x | AI13: 16.80% / 2.40x | AJ13: 15.90% / 2.33x | AK13: 15.00% / 2.25x | AL13: 14.10% / 2.17x | AM13: 13.20% / 2.09x | AN13: 12.29% / 2.02x | AO13: 11.38% / 1.94x
C14: Valuation Analysis | S14: =K16 -> RUBS | U14: =U38*$N$16 -> 0 | V14: =U14/$N$13 -> 0 | W14: =SUM(OFFSET(F76,0,$G$16,1,-12)) -> 0 | X14: =W14/$N$13 -> 0 | Y14: =SUM(OFFSET(F76,0,$I$16,1,-12)) -> 0 | Z14: =Y14/$N$13 -> 0 | AA14: 0 | AB14: =AA14/$N$13 -> 0 | AC14: 0 | AD14: =AC14/$N$13 -> 0 | AE14: 0 | AF14: =AE14/$N$13 -> 0
C15: Entry/Equity Valuation | E15: Residual Analysi: | F15: Refinance | G15: $/Unit | H15: Exit | I15: $/Unit | K15: Other Income | N15: % | O15: Count | P15: $ / Unit / Mo | Q15: Annual Total | S15: =K17 -> Parking | U15: =O17*P17*12 -> 0 | V15: =U15/$N$13 -> 0 | W15: =SUM(OFFSET(F77,0,$G$16,1,-12)) -> 0 | X15: =W15/$N$13 -> 0 | Y15: =SUM(OFFSET(F77,0,$I$16,1,-12)) -> 0 | Z15: =Y15/$N$13 -> 0 | AA15: 0 | AB15: =AA15/$N$13 -> 0 | AC15: 0 | AD15: =AC15/$N$13 -> 0 | AE15: 0 | AF15: =AE15/$N$13 -> 0 | AH15: Inputs | AI15: Values
C16: TTM EBITDA/NOI | D16: 796926.06 | E16: Date | Month | F16: =F11 -> 47299 | G16: =E11 -> 36 | H16: =H12 -> 49125 | I16: =I12 -> 96 | K16: RUBS | N16: 0 | O16: =$N$13 -> 63 | P16: =IFERROR(Q16/O16,0) -> 0 | Q16: =N16*U38 -> 0 | S16: =K18 -> Other | U16: =Q18 -> 0 | V16: =U16/$N$13 -> 0 | W16: =SUM(OFFSET(F78,0,$G$16,1,-12)) -> 0 | X16: =W16/$N$13 -> 0 | Y16: =SUM(OFFSET(F78,0,$I$16,1,-12)) -> 0 | Z16: =Y16/$N$13 -> 0 | AA16: 0 | AB16: =AA16/$N$13 -> 0 | AC16: 0 | AD16: =AC16/$N$13 -> 0 | AE16: 0 | AF16: =AE16/$N$13 -> 0 | AH16: Senior Loan Interest Rate | AI16: 0.07
C17: Capex Reserve | D17: 0 | E17: NOI (TTM) | F17: =INDEX($F$122:$FV$122,MATCH(G16,$F$53:$FV$53,0)) -> 842257.03 | H17: =INDEX($F$122:$FV$122,MATCH(I16,$F$53:$FV$53,0)) -> 978379.9 | K17: Parking | O17: =$N$13 -> 63 | P17: 0 | Q17: =P17*O17*12 -> 0 | S17: Total Other Income | U17: =SUM(U14:U16) -> 0 | V17: =SUM(V14:V16) -> 0 | W17: =SUM(W14:W16) -> 0 | X17: =W17/$N$13 -> 0 | Y17: =SUM(Y14:Y16) -> 0 | Z17: =Y17/$N$13 -> 0 | AA17: =SUM(AA14:AA16) -> 0 | AB17: =AA17/$N$13 -> 0 | AC17: =SUM(AC14:AC16) -> 0 | AD17: =AC17/$N$13 -> 0 | AE17: =SUM(AE14:AE16) -> 0 | AF17: =AE17/$N$13 -> 0 | AH17: General Inflation | AI17: 0.03
C18: Adjusted EBITDA/NOI | D18: =D16-D17 -> 796926.06 | E18: Cap Rate | F18: 0.06 | H18: =F18 -> 0.06 | K18: Other | N18: =Q18/U10 -> 0 | O18: =$N$13 -> 63 | P18: 0 | Q18: =O18*P18*12 -> 0 | AH18: Cap Reserve ($/Unit) | AI18: 500
C19: Cap Rate | D19: 0.069949623 | E19: Gross Value | F19: =F17/F18 -> 14037617 | G19: =F19/$N$13 -> 222819.32 | H19: =H17/H18 -> 16306332 | I19: =H19/$N$13 -> 258830.66 | K19: Total Other Income | Q19: =SUM(Q16:Q18) -> 0 | S19: =K23 -> Vacancy Loss | U19: =-SUM($U$12,$U$17)*$M23 -> -71820 | V19: =U19/$N$13 -> -1140 | W19: =SUM(OFFSET(F81,0,$G$16,1,-12)) -> -76537.147 | X19: =W19/$N$13 -> -1214.8753 | Y19: =SUM(OFFSET(F81,0,$I$16,1,-12)) -> -88906.834 | Z19: =Y19/$N$13 -> -1411.2196 | AA19: 0 | AB19: =AA19/$N$13 -> 0 | AC19: 0 | AD19: =AC19/$N$13 -> 0 | AE19: 0 | AF19: =AE19/$N$13 -> 0
C20: Gross Value | D20: =D18/D19 -> 11392857 | E20: Value Adjustments | F20: 0 | H20: 0 | S20: =K24 -> Bad Debt | U20: =-SUM($U$12,$U$17)*$M24 -> -3591 | V20: =U20/$N$13 -> -57 | W20: =SUM(OFFSET(F82,0,$G$16,1,-12)) -> -3826.8573 | X20: =W20/$N$13 -> -60.743767 | Y20: =SUM(OFFSET(F82,0,$I$16,1,-12)) -> -4445.3417 | Z20: =Y20/$N$13 -> -70.560979 | AA20: 0 | AB20: =AA20/$N$13 -> 0 | AC20: 0 | AD20: =AC20/$N$13 -> 0 | AE20: 0 | AF20: =AE20/$N$13 -> 0
C21: $/Unit | D21: =D20/N13 -> 180839 | E21: Net Gross Value | F21: =F19+F20 -> 14037617 | G21: =F21/$N$13 -> 222819.32 | H21: =H19+H20 -> 16306332 | I21: =H21/$N$13 -> 258830.66 | K21: Income Adjustments | M21: =IF(MONTH(F9)=12,YEAR(F9)+1,YEAR(F9)) -> 2026 | N21: =M21+1 -> 2027 | O21: =N21+1 -> 2028 | P21: =O21+1 -> 2029 | Q21: =P21+1 -> 2030 | S21: =K25 -> Concessions | U21: =-SUM($U$12,$U$17)*$M25 -> -3591 | V21: =U21/$N$13 -> -57 | W21: =SUM(OFFSET(F83,0,$G$16,1,-12)) -> -3826.8573 | X21: =W21/$N$13 -> -60.743767 | Y21: =SUM(OFFSET(F83,0,$I$16,1,-12)) -> -4445.3417 | Z21: =Y21/$N$13 -> -70.560979 | AA21: 0 | AB21: =AA21/$N$13 -> 0 | AC21: 0 | AD21: =AC21/$N$13 -> 0 | AE21: 0 | AF21: =AE21/$N$13 -> 0
K22: Loss to Lease | M22: 0.0125 | N22: 0.0125 | O22: 0.0125 | P22: 0.0125 | Q22: 0.0125 | S22: =K26 -> Model Units | U22: =-O13*M26*12 -> 0 | V22: =U22/$N$13 -> 0 | W22: =SUM(OFFSET(F84,0,$G$16,1,-12)) -> 0 | X22: =W22/$N$13 -> 0 | Y22: =SUM(OFFSET(F84,0,$I$16,1,-12)) -> 0 | Z22: =Y22/$N$13 -> 0 | AA22: 0 | AB22: =AA22/$N$13 -> 0 | AC22: 0 | AD22: =AC22/$N$13 -> 0 | AE22: 0 | AF22: =AE22/$N$13 -> 0
C23: Less: Deferred Capex | D23: 0 | E23: Sales Costs | F23: Total | G23: $/Unit | H23: Total | I23: $/Unit | K23: Vacancy Loss | M23: 0.05 | N23: 0.05 | O23: 0.05 | P23: 0.05 | Q23: 0.05 | S23: Total Income Adjustments | U23: =SUM(U19:U22) -> -79002 | V23: =SUM(V19:V22) -> -1254 | W23: =SUM(W19:W22) -> -84190.861 | X23: =W23/$N$13 -> -1336.3629 | Y23: =SUM(Y19:Y22) -> -97797.517 | Z23: =Y23/$N$13 -> -1552.3415 | AA23: =SUM(AA19:AA22) -> 0 | AB23: =AA23/$N$13 -> 0 | AC23: =SUM(AC19:AC22) -> 0 | AD23: =AC23/$N$13 -> 0 | AE23: =SUM(AE19:AE22) -> 0 | AF23: =AE23/$N$13 -> 0
C24: Less: Outstanding Debt | D24: 6266071.4 | E24: 0.0025 | F24: =F$21*$E24 -> 35094.043 | G24: =F24/$N$13 -> 557.0483 | H24: =H$21*$E24 -> 40765.829 | I24: =H24/$N$13 -> 647.07666 | K24: Bad Debt | M24: 0.0025 | N24: 0.0025 | O24: 0.0025 | P24: 0.0025 | Q24: 0.0025
C25: Equity Value | D25: =D20-SUM(D23:D24) -> 5126785.7 | E25: 0.0025 | F25: =F$21*$E25 -> 35094.043 | G25: =F25/$N$13 -> 557.0483 | H25: =H$21*$E25 -> 40765.829 | I25: =H25/$N$13 -> 647.07666 | K25: Concessions | M25: 0.0025 | N25: 0.0025 | O25: 0.0025 | P25: 0.0025 | Q25: 0.0025 | S25: EGI | U25: =SUM(U12,U17,U23) -> 1357398 | V25: =SUM(V12,V17,V23) -> 646 | W25: =SUM(W12,W17,W23) -> 1446552.1 | X25: =SUM(X12,X17,X23) -> 22961.144 | Y25: =SUM(Y12,Y17,Y23) -> 1680339.2 | Z25: =SUM(Z12,Z17,Z23) -> 26672.05 | AA25: =SUM(AA12,AA17,AA23) -> 0 | AB25: =SUM(AB12,AB17,AB23) -> 0 | ... AF25: =SUM(AF12,AF17,AF23) -> 0
C26: Aequitas Equity Contributions | D26: =D25*D46 -> 769017.86 | E26: 0.0025 | F26: =F$21*$E26 -> 35094.043 | G26: =F26/$N$13 -> 557.0483 | H26: =H$21*$E26 -> 40765.829 | I26: =H26/$N$13 -> 647.07666 | K26: Model Units | M26: 0 | N26: 0 | O26: 0 | P26: 0 | Q26: 0
C27: Closing Costs % | D27: 0.01 | E27: 0.0025 | F27: =F$21*$E27 -> 35094.043 | G27: =F27/$N$13 -> 557.0483 | H27: =H$21*$E27 -> 40765.829 | I27: =H27/$N$13 -> 647.07666 | K27: Growth Assumptions | M27: =IF(MONTH(F9)=12,YEAR(F9)+1,YEAR(F9)) -> 2026 | N27: =M27+1 -> 2027 | O27: =N27+1 -> 2028 | P27: =O27+1 -> 2029 | Q27: =P27+1 -> 2030 | S27: Opex
C28: Closing Costs $ | D28: =D27*D20 -> 113928.57 | E28: =SUM(E24:E27) -> 0.01 | F28: =SUM(F24:F27) -> 140376.17 | G28: =F28/$N$13 -> 2228.1932 | H28: =SUM(H24:H27) -> 163063.32 | I28: =H28/$N$13 -> 2588.3066 | K28: Market Rent | M28: =AI17 -> 0.03 | N28: =M28 -> 0.03 | O28: =N28 -> 0.03 | P28: =O28 -> 0.03 | Q28: =P28 -> 0.03 | S28: Payroll | U28: =V28*$N$13 -> 431550 | V28: 6850 | W28: =SUM(OFFSET(F91,0,$G$16,1,-12)) -> 465715.7 | X28: =W28/$N$13 -> 7392.3128 | Y28: =SUM(OFFSET(F91,0,$I$16,1,-12)) -> 540983.18 | Z28: =Y28/$N$13 -> 8587.0346 | AA28: 0 | AB28: =AA28/$N$13 -> 0 | AC28: 0 | AD28: =AC28/$N$13 -> 0 | AE28: 0 | AF28: =AE28/$N$13 -> 0
E29: Net Sales Proceeds | F29: =F21-F28 -> 13897241 | G29: =G21-G28 -> 220591.13 | H29: =H21-H28 -> 16143268 | I29: =I21-I28 -> 256242.36 | K29: Other Income | M29: =M28 -> 0.03 | N29: =M29 -> 0.03 | O29: =N29 -> 0.03 | P29: =O29 -> 0.03 | Q29: =P29 -> 0.03 | S29: Admin | U29: =V29*$N$13 -> 0 | V29: 0 | W29: =SUM(OFFSET(F92,0,$G$16,1,-12)) -> 0 | X29: =W29/$N$13 -> 0 | Y29: =SUM(OFFSET(F92,0,$I$16,1,-12)) -> 0 | Z29: =Y29/$N$13 -> 0 | AA29: 0 | AB29: =AA29/$N$13 -> 0 | AC29: 0 | AD29: =AC29/$N$13 -> 0 | AE29: 0 | AF29: =AE29/$N$13 -> 0
K30: Operating Expenses | M30: =M29 -> 0.03 | N30: =M30 -> 0.03 | O30: =N30 -> 0.03 | P30: =O30 -> 0.03 | Q30: =P30 -> 0.03 | S30: Marketing | U30: =V30*$N$13 -> 0 | V30: 0 | W30: =SUM(OFFSET(F93,0,$G$16,1,-12)) -> 0 | X30: =W30/$N$13 -> 0 | Y30: =SUM(OFFSET(F93,0,$I$16,1,-12)) -> 0 | Z30: =Y30/$N$13 -> 0 | AA30: 0 | AB30: =AA30/$N$13 -> 0 | AC30: 0 | AD30: =AC30/$N$13 -> 0 | AE30: 0 | AF30: =AE30/$N$13 -> 0
C31: Financing Assumptions | K31: Property Taxes | M31: =M30 -> 0.03 | N31: =M31 -> 0.03 | O31: =N31 -> 0.03 | P31: =O31 -> 0.03 | Q31: =P31 -> 0.03 | S31: R&M | U31: =V31*$N$13 -> 0 | V31: 0 | W31: =SUM(OFFSET(F94,0,$G$16,1,-12)) -> 0 | X31: =W31/$N$13 -> 0 | Y31: =SUM(OFFSET(F94,0,$I$16,1,-12)) -> 0 | Z31: =Y31/$N$13 -> 0 | AA31: 0 | AB31: =AA31/$N$13 -> 0 | AC31: 0 | AD31: =AC31/$N$13 -> 0 | AE31: 0 | AF31: =AE31/$N$13 -> 0
C32: Senior Financing | E32: Senior Financing | H32: Refinance | S32: Contract Service | U32: =V32*$N$13 -> 0 | V32: 0 | W32: =SUM(OFFSET(F95,0,$G$16,1,-12)) -> 0 | X32: =W32/$N$13 -> 0 | Y32: =SUM(OFFSET(F95,0,$I$16,1,-12)) -> 0 | Z32: =Y32/$N$13 -> 0 | AA32: 0 | AB32: =AA32/$N$13 -> 0 | AC32: 0 | AD32: =AC32/$N$13 -> 0 | AE32: 0 | AF32: =AE32/$N$13 -> 0
C33: Lender | F33: TBD | G33: Lender | I33: TBD | K33: Property Taxes | S33: Turnover | U33: =V33*$N$13 -> 0 | V33: 0 | W33: =SUM(OFFSET(F96,0,$G$16,1,-12)) -> 0 | X33: =W33/$N$13 -> 0 | Y33: =SUM(OFFSET(F96,0,$I$16,1,-12)) -> 0 | Z33: =Y33/$N$13 -> 0 | AA33: 0 | AB33: =AA33/$N$13 -> 0 | AC33: 0 | AD33: =AC33/$N$13 -> 0 | AE33: 0 | AF33: =AE33/$N$13 -> 0
C34: Loan Proceeds | E34: 0.55 | F34: 6266071.4 | G34: Loan Proceeds | H34: DSCR | I34: =INDEX($I$40:$I$42,MATCH(H34,$G$40:$G$42,0)) -> 8883611.7 | M34: Current | N34: Next Buyer | O34: Note | S34: Other | U34: =V34*$N$13 -> 0 | V34: 0 | W34: =SUM(OFFSET(F97,0,$G$16,1,-12)) -> 0 | X34: =W34/$N$13 -> 0 | Y34: =SUM(OFFSET(F97,0,$I$16,1,-12)) -> 0 | Z34: =Y34/$N$13 -> 0 | AA34: 0 | AB34: =AA34/$N$13 -> 0 | AC34: 0 | AD34: =AC34/$N$13 -> 0 | AE34: 0 | AF34: =AE34/$N$13 -> 0
C35: Term | E35: 36 | F35: =EOMONTH(F9,E35) -> 47299 | G35: Term | H35: 360 | I35: =EOMONTH(F35,H35-1) -> 58226 | K35: Assessed Value | M35: 0 | N35: 0 | S35: Total Controllable Expenses | U35: =SUM(U28:U34) -> 431550 | V35: =SUM(V28:V34) -> 6850 | W35: =SUM(W28:W34) -> 465715.7 | X35: =SUM(X28:X34) -> 7392.3128 | Y35: =SUM(Y28:Y34) -> 540983.18 | Z35: =SUM(Z28:Z34) -> 8587.0346 | AA35: =SUM(AA28:AA34) -> 0 | AB35: =AA35/$N$13 -> 0 | AC35: =SUM(AC28:AC34) -> 0 | AD35: =AC35/$N$13 -> 0 | AE35: =SUM(AE28:AE34) -> 0 | AF35: =AE35/$N$13 -> 0
C36: Interest Rate | E36: Fixed | F36: =AI16 -> 0.07 | G36: Interest Rate | H36: Fixed | I36: =F36-0.5% -> 0.065 | K36: Assessed Value/Unit | M36: 0 | N36: 0
C37: Financing Costs | E37: 0.01 | F37: =E37*F34 -> 62660.714 | G37: Financing Costs | H37: 0.005 | I37: =H37*I34 -> 44418.058 | K37: Assessment % | M37: 1 | N37: =M37 -> 1 | S37: Insurance | U37: =V37*$N$13 -> 12600 | V37: 200 | W37: =SUM(OFFSET(F101,0,$G$16,1,-12)) -> 13597.539 | X37: =W37/$N$13 -> 215.83395 | Y37: =SUM(OFFSET(F101,0,$I$16,1,-12)) -> 15795.129 | Z37: =Y37/$N$13 -> 250.71634 | AA37: 0 | AB37: =AA37/$N$13 -> 0 | AC37: 0 | AD37: =AC37/$N$13 -> 0 | AE37: 0 | AF37: =AE37/$N$13 -> 0 | AI37: 1 | AJ37: =AI37*(1+AJ31) -> 1 | AK37: =AJ37*(1+AK31) -> 1 | AL37: =AK37*(1+AL31) -> 1 | AM37: =AL37*(1+AM31) -> 1 | AN37: =AM37*(1+AN31) -> 1
C38: IO Periods/Amortization | E38: 0 | F38: =PMT(F36/12,360,-F34,0,) -> 41688.33 | G38: IO Periods/Amortization | H38: 24 | I38: =PMT(I36/12,360,-I34,0,) -> 56150.469 | K38: Millage Rate | M38: 0.018926798 | N38: 0.018926798 | S38: Utilities | U38: =V38*$N$13 -> 0 | V38: 0 | W38: =SUM(OFFSET(F102,0,$G$16,1,-12)) -> 0 | X38: =W38/$N$13 -> 0 | Y38: =SUM(OFFSET(F102,0,$I$16,1,-12)) -> 0 | Z38: =Y38/$N$13 -> 0 | AA38: 0 | AB38: =AA38/$N$13 -> 0 | AC38: 0 | AD38: =AC38/$N$13 -> 0 | AE38: 0 | AF38: =AE38/$N$13 -> 0
C39: Debt Metrics | G39: Debt Metrics | K39: Special Assessment | M39: 0 | N39: 0 | S39: Management Fee | T39: 0.03 | U39: =T39*U25 -> 40721.94 | V39: =U39/N13 -> 646.38 | W39: =SUM(OFFSET(F103,0,$G$16,1,-12)) -> 43396.562 | X39: =W39/$N$13 -> 688.83432 | Y39: =SUM(OFFSET(F103,0,$I$16,1,-12)) -> 50410.175 | Z39: =Y39/$N$13 -> 800.1615 | AA39: 0 | AB39: =AA39/$N$13 -> 0 | AC39: 0 | AD39: =AC39/$N$13 -> 0 | AE39: 0 | AF39: =AE39/$N$13 -> 0
C40: DSCR | F40: =U48/(PMT(6%/12,360,-F34,0)*12) -> 1.7677289 | G40: DSCR | H40: 1.25 | I40: =PV(I36/12,H35,-F17/12/H40) -> 8883611.7 | K40: Total Property Tax | M40: =M35*M38 -> 0 | N40: =N35*N38 -> 0 | S40: Property Tax | U40: =V40*$N$13 -> 44100 | V40: 700 | W40: =SUM(OFFSET(F104,0,$G$16,1,-12)) -> 47591.386 | X40: =W40/$N$13 -> 755.41882 | Y40: =SUM(OFFSET(F104,0,$I$16,1,-12)) -> 55282.952 | Z40: =Y40/$N$13 -> 877.50718 | AA40: 0 | AB40: =AA40/$N$13 -> 0 | AC40: 0 | AD40: =AC40/$N$13 -> 0 | AE40: 0 | AF40: =AE40/$N$13 -> 0
C41: DY | F41: =U48/F34 -> 0.12718113 | G41: DY | H41: 0.09 | I41: =F17/H41 -> 9358411.5 | K41: Total Property Tax/Unit | M41: =M40/$N$13 -> 0 | N41: =N40/$N$13 -> 0 | S41: Total Non-controllable Expenses | U41: =SUM(U37:U40) -> 97421.94 | V41: =SUM(V37:V40) -> 1546.38 | W41: =SUM(W37:W40) -> 104585.49 | X41: =W41/$N$13 -> 1660.0871 | Y41: =SUM(Y37:Y40) -> 121488.26 | Z41: =Y41/$N$13 -> 1928.385 | AA41: =SUM(AA37:AA40) -> 0 | AB41: =AA41/$N$13 -> 0 | AC41: =SUM(AC37:AC40) -> 0 | AD41: =AC41/$N$13 -> 0 | AE41: =SUM(AE37:AE40) -> 0 | AF41: =AE41/$N$13 -> 0
G42: LTV | H42: 0.65 | I42: =H42*F21 -> 9124451.2 | S42: Total Opex | U42: =SUM(U35,U41) -> 528971.94 | V42: =SUM(V35,V41) -> 8396.38 | W42: =SUM(W35,W41) -> 570301.19 | X42: =W42/$N$13 -> 9052.3999 | Y42: =SUM(Y35,Y41) -> 662471.43 | Z42: =Y42/$N$13 -> 10515.42 | AA42: =SUM(AA35,AA41) -> 0 | AB42: =AA42/$N$13 -> 0 | AC42: =SUM(AC35,AC41) -> 0 | AD42: =AC42/$N$13 -> 0 | AE42: =SUM(AE35,AE41) -> 0 | AF42: =AE42/$N$13 -> 0
S43: Opex Margin | U43: =U42/U25 -> 0.38969554 | W43: =W42/W25 -> 0.39424864 | Y43: =Y42/Y25 -> 0.39424864
C44: Waterfall | F44: Returns Metrics
D45: Aequitas | E45: Partner | G45: Aequitas Return | S45: NOI | U45: =U25-U42 -> 828426.06 | V45: =V25+V42 -> 9042.38 | W45: =W25-W42 -> 876250.88 | X45: =W45/$N$13 -> 13908.744 | Y45: =Y25-Y42 -> 1017867.7 | Z45: =Y45/$N$13 -> 16156.631 | AA45: =AA25-AA42 -> 0 | AB45: =AA45/$N$13 -> 0 | AC45: =AC25-AC42 -> 0 | AD45: =AC45/$N$13 -> 0 | AE45: =AE25-AE42 -> 0 | AF45: =AE45/$N$13 -> 0
C46: Equity Investment | D46: 0.15 | E46: =1-D46 -> 0.85 | F46: Net Profit | G46: =E160 -> 1116018.9
C47: 0 | D47: 0 | E47: =1-D47 -> 1 | F47: Peak Equity | G47: =E161 -> -795506.25 | S47: Cap Reserve | U47: =V47*$N$13 -> 31500 | V47: =AI18 -> 500 | W47: =SUM(OFFSET(F116,0,$G$16,1,-12)) -> 33993.847 | X47: =W47/$N$13 -> 539.58487 | Y47: =SUM(OFFSET(F116,0,$I$16,1,-12)) -> 39487.823 | Z47: =Y47/$N$13 -> 626.79084 | AA47: 0 | AB47: =AA47/$N$13 -> 0 | AC47: 0 | AD47: =AC47/$N$13 -> 0 | AE47: 0 | AF47: =AE47/$N$13 -> 0
C48: Thereafter | D48: 0.15 | E48: =1-D48 -> 0.85 | F48: IRR | G48: =E162 -> 0.16801554 | S48: NOI after Cap Reserve | U48: =U45-U47 -> 796926.06 | V48: =V45-V47 -> 8542.38 | W48: =W45-W47 -> 842257.03 | X48: =W48/$N$13 -> 13369.159 | Y48: =Y45-Y47 -> 978379.9 | Z48: =Y48/$N$13 -> 15529.84 | AA48: =AA45-AA47 -> 0 | AB48: =AA48/$N$13 -> 0 | AC48: =AC45-AC47 -> 0 | AD48: =AC48/$N$13 -> 0 | AE48: =AE45-AE47 -> 0 | AF48: =AE48/$N$13 -> 0
F49: Equity Multiple | G49: =E163 -> 2.402904 | S49: YOC | U49: =U48/$D$20 -> 0.069949623 | W49: =W48/$D$20 -> 0.073928517 | Y49: =Y48/$D$20 -> 0.085876606
C50: FALSE | S50: % Growth | W50: =W48/U48-1 -> 0.056882281 | Y50: =Y48/W48-1 -> 0.16161678
C52: Yr | F52: 0 | G52: 1 | H52: 1 | I52: 1 | J52: 1 | K52: 1 | L52: 1 | M52: 1 | N52: 1 | O52: 1 | P52: 1 | Q52: 1 | R52: 1 | S52: =G52+1 -> 2 | T52: =H52+1 -> 2 | U52: =I52+1 -> 2 | V52: =J52+1 -> 2 | W52: =K52+1 -> 2 | X52: =L52+1 -> 2 | Y52: =M52+1 -> 2 | Z52: =N52+1 -> 2 | ... FF52: =ET52+1 -> 13 | FH52: Annual Cash Flow
C53: Mo | F53: 0 | G53: =F53+1 -> 1 | H53: =G53+1 -> 2 | I53: =H53+1 -> 3 | J53: =I53+1 -> 4 | K53: =J53+1 -> 5 | L53: =K53+1 -> 6 | M53: =L53+1 -> 7 | N53: =M53+1 -> 8 | ... FF53: =FE53+1 -> 156
C54: Calendar Year | F54: =YEAR(F55) -> 2026 | G54: =YEAR(G55) -> 2026 | H54: =YEAR(H55) -> 2026 | I54: =YEAR(I55) -> 2026 | J54: =YEAR(J55) -> 2026 | K54: =YEAR(K55) -> 2026 | L54: =YEAR(L55) -> 2026 | M54: =YEAR(M55) -> 2027 | ... FF54: =YEAR(FF55) -> 2039 | FH54: =YEAR(F9) -> 2026 | FI54: =FH54+1 -> 2027 | FJ54: =FI54+1 -> 2028 | FK54: =FJ54+1 -> 2029 | FL54: =FK54+1 -> 2030 | FM54: =FL54+1 -> 2031 | FN54: =FM54+1 -> 2032 | FO54: =FN54+1 -> 2033 | FP54: =FO54+1 -> 2034 | ... FU54: =FT54+1 -> 2039
C55: Property Cash Flows | E55: Total | F55: =F9 -> 46203 | G55: =EOMONTH(F55,1) -> 46234 | H55: =EOMONTH(G55,1) -> 46265 | I55: =EOMONTH(H55,1) -> 46295 | J55: =EOMONTH(I55,1) -> 46326 | K55: =EOMONTH(J55,1) -> 46356 | L55: =EOMONTH(K55,1) -> 46387 | M55: =EOMONTH(L55,1) -> 46418 | N55: =EOMONTH(M55,1) -> 46446 | ... FF55: =EOMONTH(FE55,1) -> 50951
C56: Pro Forma
C57: Growth Assumptions
C58: =K28 -> Market Rent | F58: 0 | G58: =IFERROR(INDEX($M28:$Q28,MATCH(YEAR(G$55),$M$27:$Q$27,0))/12,F58) -> 0.0025 | H58: =IFERROR(INDEX($M28:$Q28,MATCH(YEAR(H$55),$M$27:$Q$27,0))/12,G58) -> 0.0025 | I58: =IFERROR(INDEX($M28:$Q28,MATCH(YEAR(I$55),$M$27:$Q$27,0))/12,H58) -> 0.0025 | J58: =IFERROR(INDEX($M28:$Q28,MATCH(YEAR(J$55),$M$27:$Q$27,0))/12,I58) -> 0.0025 | K58: =IFERROR(INDEX($M28:$Q28,MATCH(YEAR(K$55),$M$27:$Q$27,0))/12,J58) -> 0.0025 | L58: =IFERROR(INDEX($M28:$Q28,MATCH(YEAR(L$55),$M$27:$Q$27,0))/12,K58) -> 0.0025 | M58: =IFERROR(INDEX($M28:$Q28,MATCH(YEAR(M$55),$M$27:$Q$27,0))/12,L58) -> 0.0025 | N58: =IFERROR(INDEX($M28:$Q28,MATCH(YEAR(N$55),$M$27:$Q$27,0))/12,M58) -> 0.0025 | ... FF58: =IFERROR(INDEX($M28:$Q28,MATCH(YEAR(FF$55),$M$27:$Q$27,0))/12,FE58) -> 0.0025 | FH58: =IFERROR(INDEX($M28:$Q28,MATCH(YEAR(FH$55),$M$27:$Q$27,0))/12,EZ58) -> 0.0025 | FM58: =IFERROR(INDEX($M28:$Q28,MATCH(YEAR(FM$55),$M$27:$Q$27,0))/12,FA58) -> 0.0025 | FN58: =IFERROR(INDEX($M28:$Q28,MATCH(YEAR(FN$55),$M$27:$Q$27,0))/12,FB58) -> 0.0025 | FO58: =IFERROR(INDEX($M28:$Q28,MATCH(YEAR(FO$55),$M$27:$Q$27,0))/12,FC58) -> 0.0025 | FP58: =IFERROR(INDEX($M28:$Q28,MATCH(YEAR(FP$55),$M$27:$Q$27,0))/12,FD58) -> 0.0025
C59: Compounded Rate | F59: 1 | G59: =F59*(1+G58) -> 1.0025 | H59: =G59*(1+H58) -> 1.0050062 | I59: =H59*(1+I58) -> 1.0075188 | J59: =I59*(1+J58) -> 1.0100376 | K59: =J59*(1+K58) -> 1.0125627 | L59: =K59*(1+L58) -> 1.0150941 | M59: =L59*(1+M58) -> 1.0176318 | N59: =M59*(1+N58) -> 1.0201759 | ... FF59: =FE59*(1+FF58) -> 1.4762621 | FH59: =EZ59*(1+FH58) -> 1.4579465 | FM59: =FA59*(1+FM58) -> 1.4615913 | FN59: =FB59*(1+FN58) -> 1.4652453 | FO59: =FC59*(1+FO58) -> 1.4689084 | FP59: =FD59*(1+FP58) -> 1.4725807
C60: =K29 -> Other Income | F60: 0 | G60: =IFERROR(INDEX($M29:$Q29,MATCH(YEAR(G$55),$M$27:$Q$27,0))/12,F60) -> 0.0025 | H60: =IFERROR(INDEX($M29:$Q29,MATCH(YEAR(H$55),$M$27:$Q$27,0))/12,G60) -> 0.0025 | I60: =IFERROR(INDEX($M29:$Q29,MATCH(YEAR(I$55),$M$27:$Q$27,0))/12,H60) -> 0.0025 | J60: =IFERROR(INDEX($M29:$Q29,MATCH(YEAR(J$55),$M$27:$Q$27,0))/12,I60) -> 0.0025 | K60: =IFERROR(INDEX($M29:$Q29,MATCH(YEAR(K$55),$M$27:$Q$27,0))/12,J60) -> 0.0025 | L60: =IFERROR(INDEX($M29:$Q29,MATCH(YEAR(L$55),$M$27:$Q$27,0))/12,K60) -> 0.0025 | M60: =IFERROR(INDEX($M29:$Q29,MATCH(YEAR(M$55),$M$27:$Q$27,0))/12,L60) -> 0.0025 | N60: =IFERROR(INDEX($M29:$Q29,MATCH(YEAR(N$55),$M$27:$Q$27,0))/12,M60) -> 0.0025 | ... FF60: =IFERROR(INDEX($M29:$Q29,MATCH(YEAR(FF$55),$M$27:$Q$27,0))/12,FE60) -> 0.0025 | FH60: =IFERROR(INDEX($M29:$Q29,MATCH(YEAR(FH$55),$M$27:$Q$27,0))/12,EZ60) -> 0.0025 | FM60: =IFERROR(INDEX($M29:$Q29,MATCH(YEAR(FM$55),$M$27:$Q$27,0))/12,FA60) -> 0.0025 | FN60: =IFERROR(INDEX($M29:$Q29,MATCH(YEAR(FN$55),$M$27:$Q$27,0))/12,FB60) -> 0.0025 | FO60: =IFERROR(INDEX($M29:$Q29,MATCH(YEAR(FO$55),$M$27:$Q$27,0))/12,FC60) -> 0.0025 | FP60: =IFERROR(INDEX($M29:$Q29,MATCH(YEAR(FP$55),$M$27:$Q$27,0))/12,FD60) -> 0.0025
C61: Compounded Rate | F61: 1 | G61: =F61*(1+G60) -> 1.0025 | H61: =G61*(1+H60) -> 1.0050062 | I61: =H61*(1+I60) -> 1.0075188 | J61: =I61*(1+J60) -> 1.0100376 | K61: =J61*(1+K60) -> 1.0125627 | L61: =K61*(1+L60) -> 1.0150941 | M61: =L61*(1+M60) -> 1.0176318 | N61: =M61*(1+N60) -> 1.0201759 | ... FF61: =FE61*(1+FF60) -> 1.4762621 | FH61: =EZ61*(1+FH60) -> 1.4579465 | FM61: =FA61*(1+FM60) -> 1.4615913 | FN61: =FB61*(1+FN60) -> 1.4652453 | FO61: =FC61*(1+FO60) -> 1.4689084 | FP61: =FD61*(1+FP60) -> 1.4725807
C62: =K30 -> Operating Expenses | F62: 0 | G62: =IFERROR(INDEX($M30:$Q30,MATCH(YEAR(G$55),$M$27:$Q$27,0))/12,F62) -> 0.0025 | H62: =IFERROR(INDEX($M30:$Q30,MATCH(YEAR(H$55),$M$27:$Q$27,0))/12,G62) -> 0.0025 | I62: =IFERROR(INDEX($M30:$Q30,MATCH(YEAR(I$55),$M$27:$Q$27,0))/12,H62) -> 0.0025 | J62: =IFERROR(INDEX($M30:$Q30,MATCH(YEAR(J$55),$M$27:$Q$27,0))/12,I62) -> 0.0025 | K62: =IFERROR(INDEX($M30:$Q30,MATCH(YEAR(K$55),$M$27:$Q$27,0))/12,J62) -> 0.0025 | L62: =IFERROR(INDEX($M30:$Q30,MATCH(YEAR(L$55),$M$27:$Q$27,0))/12,K62) -> 0.0025 | M62: =IFERROR(INDEX($M30:$Q30,MATCH(YEAR(M$55),$M$27:$Q$27,0))/12,L62) -> 0.0025 | N62: =IFERROR(INDEX($M30:$Q30,MATCH(YEAR(N$55),$M$27:$Q$27,0))/12,M62) -> 0.0025 | ... FF62: =IFERROR(INDEX($M30:$Q30,MATCH(YEAR(FF$55),$M$27:$Q$27,0))/12,FE62) -> 0.0025 | FH62: =IFERROR(INDEX($M30:$Q30,MATCH(YEAR(FH$55),$M$27:$Q$27,0))/12,EZ62) -> 0.0025 | FM62: =IFERROR(INDEX($M30:$Q30,MATCH(YEAR(FM$55),$M$27:$Q$27,0))/12,FA62) -> 0.0025 | FN62: =IFERROR(INDEX($M30:$Q30,MATCH(YEAR(FN$55),$M$27:$Q$27,0))/12,FB62) -> 0.0025 | FO62: =IFERROR(INDEX($M30:$Q30,MATCH(YEAR(FO$55),$M$27:$Q$27,0))/12,FC62) -> 0.0025 | FP62: =IFERROR(INDEX($M30:$Q30,MATCH(YEAR(FP$55),$M$27:$Q$27,0))/12,FD62) -> 0.0025
C63: Compounded Rate | F63: 1 | G63: =F63*(1+G62) -> 1.0025 | H63: =G63*(1+H62) -> 1.0050062 | I63: =H63*(1+I62) -> 1.0075188 | J63: =I63*(1+J62) -> 1.0100376 | K63: =J63*(1+K62) -> 1.0125627 | L63: =K63*(1+L62) -> 1.0150941 | M63: =L63*(1+M62) -> 1.0176318 | N63: =M63*(1+N62) -> 1.0201759 | ... FF63: =FE63*(1+FF62) -> 1.4762621 | FH63: =EZ63*(1+FH62) -> 1.4579465 | FM63: =FA63*(1+FM62) -> 1.4615913 | FN63: =FB63*(1+FN62) -> 1.4652453 | FO63: =FC63*(1+FO62) -> 1.4689084 | FP63: =FD63*(1+FP62) -> 1.4725807
C64: =K31 -> Property Taxes | F64: 0 | G64: =IFERROR(INDEX($M31:$Q31,MATCH(YEAR(G$55),$M$27:$Q$27,0))/12,F64) -> 0.0025 | H64: =IFERROR(INDEX($M31:$Q31,MATCH(YEAR(H$55),$M$27:$Q$27,0))/12,G64) -> 0.0025 | I64: =IFERROR(INDEX($M31:$Q31,MATCH(YEAR(I$55),$M$27:$Q$27,0))/12,H64) -> 0.0025 | J64: =IFERROR(INDEX($M31:$Q31,MATCH(YEAR(J$55),$M$27:$Q$27,0))/12,I64) -> 0.0025 | K64: =IFERROR(INDEX($M31:$Q31,MATCH(YEAR(K$55),$M$27:$Q$27,0))/12,J64) -> 0.0025 | L64: =IFERROR(INDEX($M31:$Q31,MATCH(YEAR(L$55),$M$27:$Q$27,0))/12,K64) -> 0.0025 | M64: =IFERROR(INDEX($M31:$Q31,MATCH(YEAR(M$55),$M$27:$Q$27,0))/12,L64) -> 0.0025 | N64: =IFERROR(INDEX($M31:$Q31,MATCH(YEAR(N$55),$M$27:$Q$27,0))/12,M64) -> 0.0025 | ... FF64: =IFERROR(INDEX($M31:$Q31,MATCH(YEAR(FF$55),$M$27:$Q$27,0))/12,FE64) -> 0.0025 | FH64: =IFERROR(INDEX($M31:$Q31,MATCH(YEAR(FH$55),$M$27:$Q$27,0))/12,EZ64) -> 0.0025 | FM64: =IFERROR(INDEX($M31:$Q31,MATCH(YEAR(FM$55),$M$27:$Q$27,0))/12,FA64) -> 0.0025 | FN64: =IFERROR(INDEX($M31:$Q31,MATCH(YEAR(FN$55),$M$27:$Q$27,0))/12,FB64) -> 0.0025 | FO64: =IFERROR(INDEX($M31:$Q31,MATCH(YEAR(FO$55),$M$27:$Q$27,0))/12,FC64) -> 0.0025 | FP64: =IFERROR(INDEX($M31:$Q31,MATCH(YEAR(FP$55),$M$27:$Q$27,0))/12,FD64) -> 0.0025
C65: Compounded Rate | F65: 1 | G65: =F65*(1+G64) -> 1.0025 | H65: =G65*(1+H64) -> 1.0050062 | I65: =H65*(1+I64) -> 1.0075188 | J65: =I65*(1+J64) -> 1.0100376 | K65: =J65*(1+K64) -> 1.0125627 | L65: =K65*(1+L64) -> 1.0150941 | M65: =L65*(1+M64) -> 1.0176318 | N65: =M65*(1+N64) -> 1.0201759 | ... FF65: =FE65*(1+FF64) -> 1.4762621 | FH65: =EZ65*(1+FH64) -> 1.4579465 | FM65: =FA65*(1+FM64) -> 1.4615913 | FN65: =FB65*(1+FN64) -> 1.4652453 | FO65: =FC65*(1+FO64) -> 1.4689084 | FP65: =FD65*(1+FP64) -> 1.4725807
C67: Rent Analysis
C68: Potential Gross MR Rent/Unit | F68: =O13 -> 1900 | G68: =F68*(1+G58) -> 1904.75 | H68: =G68*(1+H58) -> 1909.5119 | I68: =H68*(1+I58) -> 1914.2857 | J68: =I68*(1+J58) -> 1919.0714 | K68: =J68*(1+K58) -> 1923.869 | L68: =K68*(1+L58) -> 1928.6787 | M68: =L68*(1+M58) -> 1933.5004 | N68: =M68*(1+N58) -> 1938.3342 | ... FF68: =FE68*(1+FF58) -> 2804.8981 | FH68: =EZ68*(1+FH58) -> 2770.0983 | FM68: =FA68*(1+FM58) -> 2777.0235 | FN68: =FB68*(1+FN58) -> 2783.9661 | FO68: =FC68*(1+FO58) -> 2790.926 | FP68: =FD68*(1+FP58) -> 2797.9033
C70: Gross Potential Rent
C71: Gross Potential Revenue (Market Rate Units) | E71: =SUM(F71:FF71) -> 22860440 | F71: 0 | G71: =G68*$N$13 -> 119999.25 | H71: =H68*$N$13 -> 120299.25 | I71: =I68*$N$13 -> 120600 | J71: =J68*$N$13 -> 120901.5 | K71: =K68*$N$13 -> 121203.75 | L71: =L68*$N$13 -> 121506.76 | M71: =M68*$N$13 -> 121810.53 | N71: =N68*$N$13 -> 122115.05 | ... FF71: =FF68*$N$13 -> 176708.58 | FH71: =SUMIF($F$54:$FF$54,FH$54,$F71:$FF71) -> 724510.5 | FI71: =SUMIF($F$54:$FF$54,FI$54,$F71:$FF71) -> 1481993.5 | FJ71: =SUMIF($F$54:$FF$54,FJ$54,$F71:$FF71) -> 1527069.7 | FK71: =SUMIF($F$54:$FF$54,FK$54,$F71:$FF71) -> 1573517 | FL71: =SUMIF($F$54:$FF$54,FL$54,$F71:$FF71) -> 1621377.1 | FM71: =SUMIF($F$54:$FF$54,FM$54,$F71:$FF71) -> 1670692.8 | FN71: =SUMIF($F$54:$FF$54,FN$54,$F71:$FF71) -> 1721508.5 | FO71: =SUMIF($F$54:$FF$54,FO$54,$F71:$FF71) -> 1773869.8 | ... FU71: =SUMIF($F$54:$FF$54,FU$54,$F71:$FF71) -> 1053663.4
C72: Loss-to-Lease (Market Rate Units) | E72: =SUM(F72:FF72) -> -285755.5 | F72: 0 | G72: =G71*-IFERROR(INDEX($M$22:$Q$22,MATCH(YEAR(G55),$M$21:$Q$21,0)),$Q$22) -> -1499.9906 | H72: =H71*-IFERROR(INDEX($M$22:$Q$22,MATCH(YEAR(H55),$M$21:$Q$21,0)),$Q$22) -> -1503.7406 | I72: =I71*-IFERROR(INDEX($M$22:$Q$22,MATCH(YEAR(I55),$M$21:$Q$21,0)),$Q$22) -> -1507.5 | J72: =J71*-IFERROR(INDEX($M$22:$Q$22,MATCH(YEAR(J55),$M$21:$Q$21,0)),$Q$22) -> -1511.2687 | K72: =K71*-IFERROR(INDEX($M$22:$Q$22,MATCH(YEAR(K55),$M$21:$Q$21,0)),$Q$22) -> -1515.0469 | L72: =L71*-IFERROR(INDEX($M$22:$Q$22,MATCH(YEAR(L55),$M$21:$Q$21,0)),$Q$22) -> -1518.8345 | M72: =M71*-IFERROR(INDEX($M$22:$Q$22,MATCH(YEAR(M55),$M$21:$Q$21,0)),$Q$22) -> -1522.6316 | N72: =N71*-IFERROR(INDEX($M$22:$Q$22,MATCH(YEAR(N55),$M$21:$Q$21,0)),$Q$22) -> -1526.4382 | ... FF72: =FF71*-IFERROR(INDEX($M$22:$Q$22,MATCH(YEAR(FF55),$M$21:$Q$21,0)),$Q$22) -> -2208.8572 | FH72: =SUMIF($F$54:$FF$54,FH$54,$F72:$FF72) -> -9056.3812 | FI72: =SUMIF($F$54:$FF$54,FI$54,$F72:$FF72) -> -18524.919 | FJ72: =SUMIF($F$54:$FF$54,FJ$54,$F72:$FF72) -> -19088.372 | FK72: =SUMIF($F$54:$FF$54,FK$54,$F72:$FF72) -> -19668.963 | FL72: =SUMIF($F$54:$FF$54,FL$54,$F72:$FF72) -> -20267.213 | FM72: =SUMIF($F$54:$FF$54,FM$54,$F72:$FF72) -> -20883.66 | FN72: =SUMIF($F$54:$FF$54,FN$54,$F72:$FF72) -> -21518.856 | FO72: =SUMIF($F$54:$FF$54,FO$54,$F72:$FF72) -> -22173.373 | ... FU72: =SUMIF($F$54:$FF$54,FU$54,$F72:$FF72) -> -13170.792
C73: Gross Potential Rent | E73: =SUM(F73:FF73) -> 22574684 | F73: 0 | G73: =SUM(G71:G72) -> 118499.26 | H73: =SUM(H71:H72) -> 118795.51 | I73: =SUM(I71:I72) -> 119092.5 | J73: =SUM(J71:J72) -> 119390.23 | K73: =SUM(K71:K72) -> 119688.7 | L73: =SUM(L71:L72) -> 119987.92 | M73: =SUM(M71:M72) -> 120287.89 | N73: =SUM(N71:N72) -> 120588.61 | ... FF73: =SUM(FF71:FF72) -> 174499.72 | FH73: =SUMIF($F$54:$FF$54,FH$54,$F73:$FF73) -> 715454.12 | FI73: =SUMIF($F$54:$FF$54,FI$54,$F73:$FF73) -> 1463468.6 | FJ73: =SUMIF($F$54:$FF$54,FJ$54,$F73:$FF73) -> 1507981.4 | FK73: =SUMIF($F$54:$FF$54,FK$54,$F73:$FF73) -> 1553848.1 | FL73: =SUMIF($F$54:$FF$54,FL$54,$F73:$FF73) -> 1601109.8 | FM73: =SUMIF($F$54:$FF$54,FM$54,$F73:$FF73) -> 1649809.1 | FN73: =SUMIF($F$54:$FF$54,FN$54,$F73:$FF73) -> 1699989.6 | FO73: =SUMIF($F$54:$FF$54,FO$54,$F73:$FF73) -> 1751696.5 | ... FU73: =SUMIF($F$54:$FF$54,FU$54,$F73:$FF73) -> 1040492.6
C75: Other Income
C76: RUBS | D76: =N16 -> 0 | E76: =SUM(F76:FF76) -> 0 | F76: 0 | G76: =$D$76*G102 -> 0 | H76: =$D$76*H102 -> 0 | I76: =$D$76*I102 -> 0 | J76: =$D$76*J102 -> 0 | K76: =$D$76*K102 -> 0 | L76: =$D$76*L102 -> 0 | M76: =$D$76*M102 -> 0 | N76: =$D$76*N102 -> 0 | ... FF76: =$D$76*FF102 -> 0 | FH76: =SUMIF($F$54:$FF$54,FH$54,$F76:$FF76) -> 0 | FI76: =SUMIF($F$54:$FF$54,FI$54,$F76:$FF76) -> 0 | FJ76: =SUMIF($F$54:$FF$54,FJ$54,$F76:$FF76) -> 0 | FK76: =SUMIF($F$54:$FF$54,FK$54,$F76:$FF76) -> 0 | FL76: =SUMIF($F$54:$FF$54,FL$54,$F76:$FF76) -> 0 | FM76: =SUMIF($F$54:$FF$54,FM$54,$F76:$FF76) -> 0 | FN76: =SUMIF($F$54:$FF$54,FN$54,$F76:$FF76) -> 0 | FO76: =SUMIF($F$54:$FF$54,FO$54,$F76:$FF76) -> 0 | ... FU76: =SUMIF($F$54:$FF$54,FU$54,$F76:$FF76) -> 0
C77: Parking Income | D77: =P17 -> 0 | E77: =SUM(F77:FF77) -> 0 | F77: 0 | G77: =IFERROR($P$17*$O$17*G61*(G55>=$F$13),0) -> 0 | H77: =IFERROR($P$17*$O$17*H61*(H55>=$F$13),0) -> 0 | I77: =IFERROR($P$17*$O$17*I61*(I55>=$F$13),0) -> 0 | J77: =IFERROR($P$17*$O$17*J61*(J55>=$F$13),0) -> 0 | K77: =IFERROR($P$17*$O$17*K61*(K55>=$F$13),0) -> 0 | L77: =IFERROR($P$17*$O$17*L61*(L55>=$F$13),0) -> 0 | M77: =IFERROR($P$17*$O$17*M61*(M55>=$F$13),0) -> 0 | N77: =IFERROR($P$17*$O$17*N61*(N55>=$F$13),0) -> 0 | ... FF77: =IFERROR($P$17*$O$17*FF61*(FF55>=$F$13),0) -> 0 | FH77: =SUMIF($F$54:$FF$54,FH$54,$F77:$FF77) -> 0 | FI77: =SUMIF($F$54:$FF$54,FI$54,$F77:$FF77) -> 0 | FJ77: =SUMIF($F$54:$FF$54,FJ$54,$F77:$FF77) -> 0 | FK77: =SUMIF($F$54:$FF$54,FK$54,$F77:$FF77) -> 0 | FL77: =SUMIF($F$54:$FF$54,FL$54,$F77:$FF77) -> 0 | FM77: =SUMIF($F$54:$FF$54,FM$54,$F77:$FF77) -> 0 | FN77: =SUMIF($F$54:$FF$54,FN$54,$F77:$FF77) -> 0 | FO77: =SUMIF($F$54:$FF$54,FO$54,$F77:$FF77) -> 0 | ... FU77: =SUMIF($F$54:$FF$54,FU$54,$F77:$FF77) -> 0
C78: Other Income | D78: =P18 -> 0 | E78: =SUM(F78:FF78) -> 0 | F78: 0 | G78: =IFERROR($P$18*$O$18*G61*(G55>=$F$13),0) -> 0 | H78: =IFERROR($P$18*$O$18*H61*(H55>=$F$13),0) -> 0 | I78: =IFERROR($P$18*$O$18*I61*(I55>=$F$13),0) -> 0 | J78: =IFERROR($P$18*$O$18*J61*(J55>=$F$13),0) -> 0 | K78: =IFERROR($P$18*$O$18*K61*(K55>=$F$13),0) -> 0 | L78: =IFERROR($P$18*$O$18*L61*(L55>=$F$13),0) -> 0 | M78: =IFERROR($P$18*$O$18*M61*(M55>=$F$13),0) -> 0 | N78: =IFERROR($P$18*$O$18*N61*(N55>=$F$13),0) -> 0 | ... FF78: =IFERROR($P$18*$O$18*FF61*(FF55>=$F$13),0) -> 0 | FH78: =SUMIF($F$54:$FF$54,FH$54,$F78:$FF78) -> 0 | FI78: =SUMIF($F$54:$FF$54,FI$54,$F78:$FF78) -> 0 | FJ78: =SUMIF($F$54:$FF$54,FJ$54,$F78:$FF78) -> 0 | FK78: =SUMIF($F$54:$FF$54,FK$54,$F78:$FF78) -> 0 | FL78: =SUMIF($F$54:$FF$54,FL$54,$F78:$FF78) -> 0 | FM78: =SUMIF($F$54:$FF$54,FM$54,$F78:$FF78) -> 0 | FN78: =SUMIF($F$54:$FF$54,FN$54,$F78:$FF78) -> 0 | FO78: =SUMIF($F$54:$FF$54,FO$54,$F78:$FF78) -> 0 | ... FU78: =SUMIF($F$54:$FF$54,FU$54,$F78:$FF78) -> 0
C79: Total Other Income | E79: =SUM(F79:FF79) -> 0 | F79: 0 | G79: =SUM(G76:G78) -> 0 | H79: =SUM(H76:H78) -> 0 | I79: =SUM(I76:I78) -> 0 | J79: =SUM(J76:J78) -> 0 | K79: =SUM(K76:K78) -> 0 | L79: =SUM(L76:L78) -> 0 | M79: =SUM(M76:M78) -> 0 | N79: =SUM(N76:N78) -> 0 | ... FF79: =SUM(FF76:FF78) -> 0 | FH79: =SUMIF($F$54:$FF$54,FH$54,$F79:$FF79) -> 0 | FI79: =SUMIF($F$54:$FF$54,FI$54,$F79:$FF79) -> 0 | FJ79: =SUMIF($F$54:$FF$54,FJ$54,$F79:$FF79) -> 0 | FK79: =SUMIF($F$54:$FF$54,FK$54,$F79:$FF79) -> 0 | FL79: =SUMIF($F$54:$FF$54,FL$54,$F79:$FF79) -> 0 | FM79: =SUMIF($F$54:$FF$54,FM$54,$F79:$FF79) -> 0 | FN79: =SUMIF($F$54:$FF$54,FN$54,$F79:$FF79) -> 0 | FO79: =SUMIF($F$54:$FF$54,FO$54,$F79:$FF79) -> 0 | ... FU79: =SUMIF($F$54:$FF$54,FU$54,$F79:$FF79) -> 0
C81: Vacancy Loss | E81: =SUM(F81:FF81) -> -1128734.2 | F81: 0 | G81: =-IFERROR(INDEX($M23:$Q23,MATCH(YEAR(G$55),$M$21:$Q$21,0)),$Q$23)*(SUM(G$73,G$79)) -> -5924.963 | H81: =-IFERROR(INDEX($M23:$Q23,MATCH(YEAR(H$55),$M$21:$Q$21,0)),$Q$23)*(SUM(H$73,H$79)) -> -5939.7754 | I81: =-IFERROR(INDEX($M23:$Q23,MATCH(YEAR(I$55),$M$21:$Q$21,0)),$Q$23)*(SUM(I$73,I$79)) -> -5954.6248 | J81: =-IFERROR(INDEX($M23:$Q23,MATCH(YEAR(J$55),$M$21:$Q$21,0)),$Q$23)*(SUM(J$73,J$79)) -> -5969.5114 | K81: =-IFERROR(INDEX($M23:$Q23,MATCH(YEAR(K$55),$M$21:$Q$21,0)),$Q$23)*(SUM(K$73,K$79)) -> -5984.4352 | L81: =-IFERROR(INDEX($M23:$Q23,MATCH(YEAR(L$55),$M$21:$Q$21,0)),$Q$23)*(SUM(L$73,L$79)) -> -5999.3962 | M81: =-IFERROR(INDEX($M23:$Q23,MATCH(YEAR(M$55),$M$21:$Q$21,0)),$Q$23)*(SUM(M$73,M$79)) -> -6014.3947 | N81: =-IFERROR(INDEX($M23:$Q23,MATCH(YEAR(N$55),$M$21:$Q$21,0)),$Q$23)*(SUM(N$73,N$79)) -> -6029.4307 | ... FF81: =-IFERROR(INDEX($M23:$Q23,MATCH(YEAR(FF$55),$M$21:$Q$21,0)),$Q$23)*(SUM(FF$73,FF$79)) -> -8724.986 | FH81: =SUMIF($F$54:$FF$54,FH$54,$F81:$FF81) -> -35772.706 | FI81: =SUMIF($F$54:$FF$54,FI$54,$F81:$FF81) -> -73173.428 | FJ81: =SUMIF($F$54:$FF$54,FJ$54,$F81:$FF81) -> -75399.068 | FK81: =SUMIF($F$54:$FF$54,FK$54,$F81:$FF81) -> -77692.403 | FL81: =SUMIF($F$54:$FF$54,FL$54,$F81:$FF81) -> -80055.492 | FM81: =SUMIF($F$54:$FF$54,FM$54,$F81:$FF81) -> -82490.456 | FN81: =SUMIF($F$54:$FF$54,FN$54,$F81:$FF81) -> -84999.482 | FO81: =SUMIF($F$54:$FF$54,FO$54,$F81:$FF81) -> -87584.823 | ... FU81: =SUMIF($F$54:$FF$54,FU$54,$F81:$FF81) -> -52024.628
C82: Bad Debt | D82: =M24 -> 0.0025 | E82: =SUM(F82:FF82) -> -56436.711 | F82: 0 | G82: =-IFERROR(INDEX($M24:$Q24,MATCH(YEAR(G$55),$M$21:$Q$21,0)),$Q$24)*(SUM(G$73,G$79)) -> -296.24815 | H82: =-IFERROR(INDEX($M24:$Q24,MATCH(YEAR(H$55),$M$21:$Q$21,0)),$Q$24)*(SUM(H$73,H$79)) -> -296.98877 | I82: =-IFERROR(INDEX($M24:$Q24,MATCH(YEAR(I$55),$M$21:$Q$21,0)),$Q$24)*(SUM(I$73,I$79)) -> -297.73124 | J82: =-IFERROR(INDEX($M24:$Q24,MATCH(YEAR(J$55),$M$21:$Q$21,0)),$Q$24)*(SUM(J$73,J$79)) -> -298.47557 | K82: =-IFERROR(INDEX($M24:$Q24,MATCH(YEAR(K$55),$M$21:$Q$21,0)),$Q$24)*(SUM(K$73,K$79)) -> -299.22176 | L82: =-IFERROR(INDEX($M24:$Q24,MATCH(YEAR(L$55),$M$21:$Q$21,0)),$Q$24)*(SUM(L$73,L$79)) -> -299.96981 | M82: =-IFERROR(INDEX($M24:$Q24,MATCH(YEAR(M$55),$M$21:$Q$21,0)),$Q$24)*(SUM(M$73,M$79)) -> -300.71974 | N82: =-IFERROR(INDEX($M24:$Q24,MATCH(YEAR(N$55),$M$21:$Q$21,0)),$Q$24)*(SUM(N$73,N$79)) -> -301.47154 | ... FF82: =-IFERROR(INDEX($M24:$Q24,MATCH(YEAR(FF$55),$M$21:$Q$21,0)),$Q$24)*(SUM(FF$73,FF$79)) -> -436.2493 | FH82: =SUMIF($F$54:$FF$54,FH$54,$F82:$FF82) -> -1788.6353 | FI82: =SUMIF($F$54:$FF$54,FI$54,$F82:$FF82) -> -3658.6714 | FJ82: =SUMIF($F$54:$FF$54,FJ$54,$F82:$FF82) -> -3769.9534 | FK82: =SUMIF($F$54:$FF$54,FK$54,$F82:$FF82) -> -3884.6202 | FL82: =SUMIF($F$54:$FF$54,FL$54,$F82:$FF82) -> -4002.7746 | FM82: =SUMIF($F$54:$FF$54,FM$54,$F82:$FF82) -> -4124.5228 | FN82: =SUMIF($F$54:$FF$54,FN$54,$F82:$FF82) -> -4249.9741 | FO82: =SUMIF($F$54:$FF$54,FO$54,$F82:$FF82) -> -4379.2412 | ... FU82: =SUMIF($F$54:$FF$54,FU$54,$F82:$FF82) -> -2601.2314
C83: Concessions | D83: =M25 -> 0.0025 | E83: =SUM(F83:FF83) -> -56436.711 | F83: 0 | G83: =-IFERROR(INDEX($M25:$Q25,MATCH(YEAR(G$55),$M$21:$Q$21,0)),$Q$25)*(SUM(G$73,G$79)) -> -296.24815 | H83: =-IFERROR(INDEX($M25:$Q25,MATCH(YEAR(H$55),$M$21:$Q$21,0)),$Q$25)*(SUM(H$73,H$79)) -> -296.98877 | I83: =-IFERROR(INDEX($M25:$Q25,MATCH(YEAR(I$55),$M$21:$Q$21,0)),$Q$25)*(SUM(I$73,I$79)) -> -297.73124 | J83: =-IFERROR(INDEX($M25:$Q25,MATCH(YEAR(J$55),$M$21:$Q$21,0)),$Q$25)*(SUM(J$73,J$79)) -> -298.47557 | K83: =-IFERROR(INDEX($M25:$Q25,MATCH(YEAR(K$55),$M$21:$Q$21,0)),$Q$25)*(SUM(K$73,K$79)) -> -299.22176 | L83: =-IFERROR(INDEX($M25:$Q25,MATCH(YEAR(L$55),$M$21:$Q$21,0)),$Q$25)*(SUM(L$73,L$79)) -> -299.96981 | M83: =-IFERROR(INDEX($M25:$Q25,MATCH(YEAR(M$55),$M$21:$Q$21,0)),$Q$25)*(SUM(M$73,M$79)) -> -300.71974 | N83: =-IFERROR(INDEX($M25:$Q25,MATCH(YEAR(N$55),$M$21:$Q$21,0)),$Q$25)*(SUM(N$73,N$79)) -> -301.47154 | ... FF83: =-IFERROR(INDEX($M25:$Q25,MATCH(YEAR(FF$55),$M$21:$Q$21,0)),$Q$25)*(SUM(FF$73,FF$79)) -> -436.2493 | FH83: =SUMIF($F$54:$FF$54,FH$54,$F83:$FF83) -> -1788.6353 | FI83: =SUMIF($F$54:$FF$54,FI$54,$F83:$FF83) -> -3658.6714 | FJ83: =SUMIF($F$54:$FF$54,FJ$54,$F83:$FF83) -> -3769.9534 | FK83: =SUMIF($F$54:$FF$54,FK$54,$F83:$FF83) -> -3884.6202 | FL83: =SUMIF($F$54:$FF$54,FL$54,$F83:$FF83) -> -4002.7746 | FM83: =SUMIF($F$54:$FF$54,FM$54,$F83:$FF83) -> -4124.5228 | FN83: =SUMIF($F$54:$FF$54,FN$54,$F83:$FF83) -> -4249.9741 | FO83: =SUMIF($F$54:$FF$54,FO$54,$F83:$FF83) -> -4379.2412 | ... FU83: =SUMIF($F$54:$FF$54,FU$54,$F83:$FF83) -> -2601.2314
C84: Model Unit Loss | E84: =SUM(F84:FF84) -> 0 | F84: =-IFERROR(INDEX($M26:$Q26,MATCH(YEAR(F$55),$M$21:$Q$21,0)),$Q$26)*F68 -> 0 | G84: =-IFERROR(INDEX($M26:$Q26,MATCH(YEAR(G$55),$M$21:$Q$21,0)),$Q$26)*G68 -> 0 | H84: =-IFERROR(INDEX($M26:$Q26,MATCH(YEAR(H$55),$M$21:$Q$21,0)),$Q$26)*H68 -> 0 | I84: =-IFERROR(INDEX($M26:$Q26,MATCH(YEAR(I$55),$M$21:$Q$21,0)),$Q$26)*I68 -> 0 | J84: =-IFERROR(INDEX($M26:$Q26,MATCH(YEAR(J$55),$M$21:$Q$21,0)),$Q$26)*J68 -> 0 | K84: =-IFERROR(INDEX($M26:$Q26,MATCH(YEAR(K$55),$M$21:$Q$21,0)),$Q$26)*K68 -> 0 | L84: =-IFERROR(INDEX($M26:$Q26,MATCH(YEAR(L$55),$M$21:$Q$21,0)),$Q$26)*L68 -> 0 | M84: =-IFERROR(INDEX($M26:$Q26,MATCH(YEAR(M$55),$M$21:$Q$21,0)),$Q$26)*M68 -> 0 | ... FF84: =-IFERROR(INDEX($M26:$Q26,MATCH(YEAR(FF$55),$M$21:$Q$21,0)),$Q$26)*FF68 -> 0 | FH84: =SUMIF($F$54:$FF$54,FH$54,$F84:$FF84) -> 0 | FI84: =SUMIF($F$54:$FF$54,FI$54,$F84:$FF84) -> 0 | FJ84: =SUMIF($F$54:$FF$54,FJ$54,$F84:$FF84) -> 0 | FK84: =SUMIF($F$54:$FF$54,FK$54,$F84:$FF84) -> 0 | FL84: =SUMIF($F$54:$FF$54,FL$54,$F84:$FF84) -> 0 | FM84: =SUMIF($F$54:$FF$54,FM$54,$F84:$FF84) -> 0 | FN84: =SUMIF($F$54:$FF$54,FN$54,$F84:$FF84) -> 0 | FO84: =SUMIF($F$54:$FF$54,FO$54,$F84:$FF84) -> 0 | ... FU84: =SUMIF($F$54:$FF$54,FU$54,$F84:$FF84) -> 0
C85: Total Vacancy & Collection | E85: =SUM(F85:FF85) -> -1241607.6 | F85: =SUM(F81:F84) -> 0 | G85: =SUM(G81:G84) -> -6517.4593 | H85: =SUM(H81:H84) -> -6533.7529 | I85: =SUM(I81:I84) -> -6550.0873 | J85: =SUM(J81:J84) -> -6566.4625 | K85: =SUM(K81:K84) -> -6582.8787 | L85: =SUM(L81:L84) -> -6599.3359 | M85: =SUM(M81:M84) -> -6615.8342 | ... FF85: =SUM(FF81:FF84) -> -9597.4846 | FH85: =SUMIF($F$54:$FF$54,FH$54,$F85:$FF85) -> -39349.977 | FI85: =SUMIF($F$54:$FF$54,FI$54,$F85:$FF85) -> -80490.771 | FJ85: =SUMIF($F$54:$FF$54,FJ$54,$F85:$FF85) -> -82938.975 | FK85: =SUMIF($F$54:$FF$54,FK$54,$F85:$FF85) -> -85461.643 | FL85: =SUMIF($F$54:$FF$54,FL$54,$F85:$FF85) -> -88061.041 | FM85: =SUMIF($F$54:$FF$54,FM$54,$F85:$FF85) -> -90739.502 | FN85: =SUMIF($F$54:$FF$54,FN$54,$F85:$FF85) -> -93499.431 | FO85: =SUMIF($F$54:$FF$54,FO$54,$F85:$FF85) -> -96343.305 | ... FU85: =SUMIF($F$54:$FF$54,FU$54,$F85:$FF85) -> -57227.091
C87: Effective Gross Income | E87: =SUM(F87:FF87) -> 21333077 | F87: =SUM(F73,F79,F85) -> 0 | G87: =SUM(G73,G79,G85) -> 111981.8 | H87: =SUM(H73,H79,H85) -> 112261.75 | I87: =SUM(I73,I79,I85) -> 112542.41 | J87: =SUM(J73,J79,J85) -> 112823.77 | K87: =SUM(K73,K79,K85) -> 113105.82 | L87: =SUM(L73,L79,L85) -> 113388.59 | M87: =SUM(M73,M79,M85) -> 113672.06 | ... FF87: =SUM(FF73,FF79,FF85) -> 164902.24 | FH87: =SUMIF($F$54:$FF$54,FH$54,$F87:$FF87) -> 676104.14 | FI87: =SUMIF($F$54:$FF$54,FI$54,$F87:$FF87) -> 1382977.8 | FJ87: =SUMIF($F$54:$FF$54,FJ$54,$F87:$FF87) -> 1425042.4 | FK87: =SUMIF($F$54:$FF$54,FK$54,$F87:$FF87) -> 1468386.4 | FL87: =SUMIF($F$54:$FF$54,FL$54,$F87:$FF87) -> 1513048.8 | FM87: =SUMIF($F$54:$FF$54,FM$54,$F87:$FF87) -> 1559069.6 | FN87: =SUMIF($F$54:$FF$54,FN$54,$F87:$FF87) -> 1606490.2 | FO87: =SUMIF($F$54:$FF$54,FO$54,$F87:$FF87) -> 1655353.2 | ... FU87: =SUMIF($F$54:$FF$54,FU$54,$F87:$FF87) -> 983265.48
C89: Operating Expenses
C90: Controllable Expenses | D90: $/Unit | E90: Total
C91: =IF(S28<>"",S28,"") -> Payroll | D91: =V28 -> 6850 | E91: =SUM(F91:FF91) -> 6868158.4 | F91: 0 | G91: =$D91/12*G$63*$N$13 -> 36052.406 | H91: =$D91/12*H$63*$N$13 -> 36142.537 | I91: =$D91/12*I$63*$N$13 -> 36232.894 | J91: =$D91/12*J$63*$N$13 -> 36323.476 | K91: =$D91/12*K$63*$N$13 -> 36414.285 | L91: =$D91/12*L$63*$N$13 -> 36505.32 | M91: =$D91/12*M$63*$N$13 -> 36596.584 | N91: =$D91/12*N$63*$N$13 -> 36688.075 | ... FF91: =$D91/12*FF$63*$N$13 -> 53090.077 | FH91: =SUMIF($F$54:$FF$54,FH$54,$F91:$FF91) -> 217670.92 | FI91: =SUMIF($F$54:$FF$54,FI$54,$F91:$FF91) -> 445248.04 | FJ91: =SUMIF($F$54:$FF$54,FJ$54,$F91:$FF91) -> 458790.69 | FK91: =SUMIF($F$54:$FF$54,FK$54,$F91:$FF91) -> 472745.25 | FL91: =SUMIF($F$54:$FF$54,FL$54,$F91:$FF91) -> 487124.25 | FM91: =SUMIF($F$54:$FF$54,FM$54,$F91:$FF91) -> 501940.6 | FN91: =SUMIF($F$54:$FF$54,FN$54,$F91:$FF91) -> 517207.6 | FO91: =SUMIF($F$54:$FF$54,FO$54,$F91:$FF91) -> 532938.96 | ... FU91: =SUMIF($F$54:$FF$54,FU$54,$F91:$FF91) -> 316561.14
C92: =IF(S29<>"",S29,"") -> Admin | D92: =V29 -> 0 | E92: =SUM(F92:FF92) -> 0 | F92: 0 | G92: =$D92/12*G$63*$N$13 -> 0 | H92: =$D92/12*H$63*$N$13 -> 0 | I92: =$D92/12*I$63*$N$13 -> 0 | J92: =$D92/12*J$63*$N$13 -> 0 | K92: =$D92/12*K$63*$N$13 -> 0 | L92: =$D92/12*L$63*$N$13 -> 0 | M92: =$D92/12*M$63*$N$13 -> 0 | N92: =$D92/12*N$63*$N$13 -> 0 | ... FF92: =$D92/12*FF$63*$N$13 -> 0 | FH92: =SUMIF($F$54:$FF$54,FH$54,$F92:$FF92) -> 0 | FI92: =SUMIF($F$54:$FF$54,FI$54,$F92:$FF92) -> 0 | FJ92: =SUMIF($F$54:$FF$54,FJ$54,$F92:$FF92) -> 0 | FK92: =SUMIF($F$54:$FF$54,FK$54,$F92:$FF92) -> 0 | FL92: =SUMIF($F$54:$FF$54,FL$54,$F92:$FF92) -> 0 | FM92: =SUMIF($F$54:$FF$54,FM$54,$F92:$FF92) -> 0 | FN92: =SUMIF($F$54:$FF$54,FN$54,$F92:$FF92) -> 0 | FO92: =SUMIF($F$54:$FF$54,FO$54,$F92:$FF92) -> 0 | ... FU92: =SUMIF($F$54:$FF$54,FU$54,$F92:$FF92) -> 0
C93: =IF(S30<>"",S30,"") -> Marketing | D93: =V30 -> 0 | E93: =SUM(F93:FF93) -> 0 | F93: 0 | G93: =$D93/12*G$63*$N$13 -> 0 | H93: =$D93/12*H$63*$N$13 -> 0 | I93: =$D93/12*I$63*$N$13 -> 0 | J93: =$D93/12*J$63*$N$13 -> 0 | K93: =$D93/12*K$63*$N$13 -> 0 | L93: =$D93/12*L$63*$N$13 -> 0 | M93: =$D93/12*M$63*$N$13 -> 0 | N93: =$D93/12*N$63*$N$13 -> 0 | ... FF93: =$D93/12*FF$63*$N$13 -> 0 | FH93: =SUMIF($F$54:$FF$54,FH$54,$F93:$FF93) -> 0 | FI93: =SUMIF($F$54:$FF$54,FI$54,$F93:$FF93) -> 0 | FJ93: =SUMIF($F$54:$FF$54,FJ$54,$F93:$FF93) -> 0 | FK93: =SUMIF($F$54:$FF$54,FK$54,$F93:$FF93) -> 0 | FL93: =SUMIF($F$54:$FF$54,FL$54,$F93:$FF93) -> 0 | FM93: =SUMIF($F$54:$FF$54,FM$54,$F93:$FF93) -> 0 | FN93: =SUMIF($F$54:$FF$54,FN$54,$F93:$FF93) -> 0 | FO93: =SUMIF($F$54:$FF$54,FO$54,$F93:$FF93) -> 0 | ... FU93: =SUMIF($F$54:$FF$54,FU$54,$F93:$FF93) -> 0
C94: =IF(S31<>"",S31,"") -> R&M | D94: =V31 -> 0 | E94: =SUM(F94:FF94) -> 0 | F94: 0 | G94: =$D94/12*G$63*$N$13 -> 0 | H94: =$D94/12*H$63*$N$13 -> 0 | I94: =$D94/12*I$63*$N$13 -> 0 | J94: =$D94/12*J$63*$N$13 -> 0 | K94: =$D94/12*K$63*$N$13 -> 0 | L94: =$D94/12*L$63*$N$13 -> 0 | M94: =$D94/12*M$63*$N$13 -> 0 | N94: =$D94/12*N$63*$N$13 -> 0 | ... FF94: =$D94/12*FF$63*$N$13 -> 0 | FH94: =SUMIF($F$54:$FF$54,FH$54,$F94:$FF94) -> 0 | FI94: =SUMIF($F$54:$FF$54,FI$54,$F94:$FF94) -> 0 | FJ94: =SUMIF($F$54:$FF$54,FJ$54,$F94:$FF94) -> 0 | FK94: =SUMIF($F$54:$FF$54,FK$54,$F94:$FF94) -> 0 | FL94: =SUMIF($F$54:$FF$54,FL$54,$F94:$FF94) -> 0 | FM94: =SUMIF($F$54:$FF$54,FM$54,$F94:$FF94) -> 0 | FN94: =SUMIF($F$54:$FF$54,FN$54,$F94:$FF94) -> 0 | FO94: =SUMIF($F$54:$FF$54,FO$54,$F94:$FF94) -> 0 | ... FU94: =SUMIF($F$54:$FF$54,FU$54,$F94:$FF94) -> 0
C95: =IF(S32<>"",S32,"") -> Contract Service | D95: =V32 -> 0 | E95: =SUM(F95:FF95) -> 0 | F95: 0 | G95: =$D95/12*G$63*$N$13 -> 0 | H95: =$D95/12*H$63*$N$13 -> 0 | I95: =$D95/12*I$63*$N$13 -> 0 | J95: =$D95/12*J$63*$N$13 -> 0 | K95: =$D95/12*K$63*$N$13 -> 0 | L95: =$D95/12*L$63*$N$13 -> 0 | M95: =$D95/12*M$63*$N$13 -> 0 | N95: =$D95/12*N$63*$N$13 -> 0 | ... FF95: =$D95/12*FF$63*$N$13 -> 0 | FH95: =SUMIF($F$54:$FF$54,FH$54,$F95:$FF95) -> 0 | FI95: =SUMIF($F$54:$FF$54,FI$54,$F95:$FF95) -> 0 | FJ95: =SUMIF($F$54:$FF$54,FJ$54,$F95:$FF95) -> 0 | FK95: =SUMIF($F$54:$FF$54,FK$54,$F95:$FF95) -> 0 | FL95: =SUMIF($F$54:$FF$54,FL$54,$F95:$FF95) -> 0 | FM95: =SUMIF($F$54:$FF$54,FM$54,$F95:$FF95) -> 0 | FN95: =SUMIF($F$54:$FF$54,FN$54,$F95:$FF95) -> 0 | FO95: =SUMIF($F$54:$FF$54,FO$54,$F95:$FF95) -> 0 | ... FU95: =SUMIF($F$54:$FF$54,FU$54,$F95:$FF95) -> 0
C96: =IF(S33<>"",S33,"") -> Turnover | D96: =V33 -> 0 | E96: =SUM(F96:FF96) -> 0 | F96: 0 | G96: =$D96/12*G$63*$N$13 -> 0 | H96: =$D96/12*H$63*$N$13 -> 0 | I96: =$D96/12*I$63*$N$13 -> 0 | J96: =$D96/12*J$63*$N$13 -> 0 | K96: =$D96/12*K$63*$N$13 -> 0 | L96: =$D96/12*L$63*$N$13 -> 0 | M96: =$D96/12*M$63*$N$13 -> 0 | N96: =$D96/12*N$63*$N$13 -> 0 | ... FF96: =$D96/12*FF$63*$N$13 -> 0 | FH96: =SUMIF($F$54:$FF$54,FH$54,$F96:$FF96) -> 0 | FI96: =SUMIF($F$54:$FF$54,FI$54,$F96:$FF96) -> 0 | FJ96: =SUMIF($F$54:$FF$54,FJ$54,$F96:$FF96) -> 0 | FK96: =SUMIF($F$54:$FF$54,FK$54,$F96:$FF96) -> 0 | FL96: =SUMIF($F$54:$FF$54,FL$54,$F96:$FF96) -> 0 | FM96: =SUMIF($F$54:$FF$54,FM$54,$F96:$FF96) -> 0 | FN96: =SUMIF($F$54:$FF$54,FN$54,$F96:$FF96) -> 0 | FO96: =SUMIF($F$54:$FF$54,FO$54,$F96:$FF96) -> 0 | ... FU96: =SUMIF($F$54:$FF$54,FU$54,$F96:$FF96) -> 0
C97: =IF(S34<>"",S34,"") -> Other | D97: =V34 -> 0 | E97: =SUM(F97:FF97) -> 0 | F97: 0 | G97: =$D97/12*G$63*$N$13 -> 0 | H97: =$D97/12*H$63*$N$13 -> 0 | I97: =$D97/12*I$63*$N$13 -> 0 | J97: =$D97/12*J$63*$N$13 -> 0 | K97: =$D97/12*K$63*$N$13 -> 0 | L97: =$D97/12*L$63*$N$13 -> 0 | M97: =$D97/12*M$63*$N$13 -> 0 | N97: =$D97/12*N$63*$N$13 -> 0 | ... FF97: =$D97/12*FF$63*$N$13 -> 0 | FH97: =SUMIF($F$54:$FF$54,FH$54,$F97:$FF97) -> 0 | FI97: =SUMIF($F$54:$FF$54,FI$54,$F97:$FF97) -> 0 | FJ97: =SUMIF($F$54:$FF$54,FJ$54,$F97:$FF97) -> 0 | FK97: =SUMIF($F$54:$FF$54,FK$54,$F97:$FF97) -> 0 | FL97: =SUMIF($F$54:$FF$54,FL$54,$F97:$FF97) -> 0 | FM97: =SUMIF($F$54:$FF$54,FM$54,$F97:$FF97) -> 0 | FN97: =SUMIF($F$54:$FF$54,FN$54,$F97:$FF97) -> 0 | FO97: =SUMIF($F$54:$FF$54,FO$54,$F97:$FF97) -> 0 | ... FU97: =SUMIF($F$54:$FF$54,FU$54,$F97:$FF97) -> 0
C98: Total Controllable Opex | E98: =SUM(F98:FF98) -> 6868158.4 | F98: =SUM(F91:F97) -> 0 | G98: =SUM(G91:G97) -> 36052.406 | H98: =SUM(H91:H97) -> 36142.537 | I98: =SUM(I91:I97) -> 36232.894 | J98: =SUM(J91:J97) -> 36323.476 | K98: =SUM(K91:K97) -> 36414.285 | L98: =SUM(L91:L97) -> 36505.32 | M98: =SUM(M91:M97) -> 36596.584 | ... FF98: =SUM(FF91:FF97) -> 53090.077 | FH98: =SUMIF($F$54:$FF$54,FH$54,$F98:$FF98) -> 217670.92 | FI98: =SUMIF($F$54:$FF$54,FI$54,$F98:$FF98) -> 445248.04 | FJ98: =SUMIF($F$54:$FF$54,FJ$54,$F98:$FF98) -> 458790.69 | FK98: =SUMIF($F$54:$FF$54,FK$54,$F98:$FF98) -> 472745.25 | FL98: =SUMIF($F$54:$FF$54,FL$54,$F98:$FF98) -> 487124.25 | FM98: =SUMIF($F$54:$FF$54,FM$54,$F98:$FF98) -> 501940.6 | FN98: =SUMIF($F$54:$FF$54,FN$54,$F98:$FF98) -> 517207.6 | FO98: =SUMIF($F$54:$FF$54,FO$54,$F98:$FF98) -> 532938.96 | ... FU98: =SUMIF($F$54:$FF$54,FU$54,$F98:$FF98) -> 316561.14
C100: Non-controllable Expenses | D100: $/Unit | E100: Total
C101: =IF(S37<>"",S37,"") -> Insurance | D101: =V37 -> 200 | E101: =SUM(F101:FF101) -> 200530.17 | F101: 0 | G101: =$D101/12*G$63*$N$13 -> 1052.625 | H101: =$D101/12*H$63*$N$13 -> 1055.2566 | I101: =$D101/12*I$63*$N$13 -> 1057.8947 | J101: =$D101/12*J$63*$N$13 -> 1060.5394 | K101: =$D101/12*K$63*$N$13 -> 1063.1908 | L101: =$D101/12*L$63*$N$13 -> 1065.8488 | M101: =$D101/12*M$63*$N$13 -> 1068.5134 | N101: =$D101/12*N$63*$N$13 -> 1071.1847 | ... FF101: =$D101/12*FF$63*$N$13 -> 1550.0752 | FH101: =SUMIF($F$54:$FF$54,FH$54,$F101:$FF101) -> 6355.3553 | FI101: =SUMIF($F$54:$FF$54,FI$54,$F101:$FF101) -> 12999.943 | FJ101: =SUMIF($F$54:$FF$54,FJ$54,$F101:$FF101) -> 13395.349 | FK101: =SUMIF($F$54:$FF$54,FK$54,$F101:$FF101) -> 13802.781 | FL101: =SUMIF($F$54:$FF$54,FL$54,$F101:$FF101) -> 14222.606 | FM101: =SUMIF($F$54:$FF$54,FM$54,$F101:$FF101) -> 14655.2 | FN101: =SUMIF($F$54:$FF$54,FN$54,$F101:$FF101) -> 15100.952 | FO101: =SUMIF($F$54:$FF$54,FO$54,$F101:$FF101) -> 15560.262 | ... FU101: =SUMIF($F$54:$FF$54,FU$54,$F101:$FF101) -> 9242.661
C102: =IF(S38<>"",S38,"") -> Utilities | D102: =V38 -> 0 | E102: =SUM(F102:FF102) -> 0 | F102: 0 | G102: =$D102/12*G$63*$N$13 -> 0 | H102: =$D102/12*H$63*$N$13 -> 0 | I102: =$D102/12*I$63*$N$13 -> 0 | J102: =$D102/12*J$63*$N$13 -> 0 | K102: =$D102/12*K$63*$N$13 -> 0 | L102: =$D102/12*L$63*$N$13 -> 0 | M102: =$D102/12*M$63*$N$13 -> 0 | N102: =$D102/12*N$63*$N$13 -> 0 | ... FF102: =$D102/12*FF$63*$N$13 -> 0 | FH102: =SUMIF($F$54:$FF$54,FH$54,$F102:$FF102) -> 0 | FI102: =SUMIF($F$54:$FF$54,FI$54,$F102:$FF102) -> 0 | FJ102: =SUMIF($F$54:$FF$54,FJ$54,$F102:$FF102) -> 0 | FK102: =SUMIF($F$54:$FF$54,FK$54,$F102:$FF102) -> 0 | FL102: =SUMIF($F$54:$FF$54,FL$54,$F102:$FF102) -> 0 | FM102: =SUMIF($F$54:$FF$54,FM$54,$F102:$FF102) -> 0 | FN102: =SUMIF($F$54:$FF$54,FN$54,$F102:$FF102) -> 0 | FO102: =SUMIF($F$54:$FF$54,FO$54,$F102:$FF102) -> 0 | ... FU102: =SUMIF($F$54:$FF$54,FU$54,$F102:$FF102) -> 0
C103: Management (% EGI) | D103: =V39 -> 646.38 | E103: =SUM(F103:FF103) -> 639992.3 | F103: 0 | G103: =($T$39*G87) -> 3359.454 | H103: =($T$39*H87) -> 3367.8526 | I103: =($T$39*I87) -> 3376.2723 | J103: =($T$39*J87) -> 3384.713 | K103: =($T$39*K87) -> 3393.1747 | L103: =($T$39*L87) -> 3401.6577 | M103: =($T$39*M87) -> 3410.1618 | N103: =($T$39*N87) -> 3418.6872 | ... FF103: =($T$39*FF87) -> 4947.0671 | FH103: =SUMIF($F$54:$FF$54,FH$54,$F103:$FF103) -> 20283.124 | FI103: =SUMIF($F$54:$FF$54,FI$54,$F103:$FF103) -> 41489.334 | FJ103: =SUMIF($F$54:$FF$54,FJ$54,$F103:$FF103) -> 42751.272 | FK103: =SUMIF($F$54:$FF$54,FK$54,$F103:$FF103) -> 44051.593 | FL103: =SUMIF($F$54:$FF$54,FL$54,$F103:$FF103) -> 45391.464 | FM103: =SUMIF($F$54:$FF$54,FM$54,$F103:$FF103) -> 46772.089 | FN103: =SUMIF($F$54:$FF$54,FN$54,$F103:$FF103) -> 48194.707 | FO103: =SUMIF($F$54:$FF$54,FO$54,$F103:$FF103) -> 49660.595 | ... FU103: =SUMIF($F$54:$FF$54,FU$54,$F103:$FF103) -> 29497.964
C104: Property Taxes | D104: =Underwriting!V40 -> 700 | E104: =SUM(F104:FF104) -> 701855.61 | F104: 0 | G104: =$D104/12*G$63*$N$13 -> 3684.1875 | H104: =$D104/12*H$63*$N$13 -> 3693.398 | I104: =$D104/12*I$63*$N$13 -> 3702.6315 | J104: =$D104/12*J$63*$N$13 -> 3711.888 | K104: =$D104/12*K$63*$N$13 -> 3721.1678 | L104: =$D104/12*L$63*$N$13 -> 3730.4707 | M104: =$D104/12*M$63*$N$13 -> 3739.7969 | N104: =$D104/12*N$63*$N$13 -> 3749.1464 | ... FF104: =$D104/12*FF$63*$N$13 -> 5425.2634 | FH104: =SUMIF($F$54:$FF$54,FH$54,$F104:$FF104) -> 22243.743 | FI104: =SUMIF($F$54:$FF$54,FI$54,$F104:$FF104) -> 45499.8 | FJ104: =SUMIF($F$54:$FF$54,FJ$54,$F104:$FF104) -> 46883.72 | FK104: =SUMIF($F$54:$FF$54,FK$54,$F104:$FF104) -> 48309.733 | FL104: =SUMIF($F$54:$FF$54,FL$54,$F104:$FF104) -> 49779.12 | FM104: =SUMIF($F$54:$FF$54,FM$54,$F104:$FF104) -> 51293.2 | FN104: =SUMIF($F$54:$FF$54,FN$54,$F104:$FF104) -> 52853.331 | FO104: =SUMIF($F$54:$FF$54,FO$54,$F104:$FF104) -> 54460.916 | ... FU104: =SUMIF($F$54:$FF$54,FU$54,$F104:$FF104) -> 32349.314
C105: Total Non-controllable Opex | E105: =SUM(F105:FF105) -> 1542378.1 | F105: =SUM(F101:F104) -> 0 | G105: =SUM(G101:G104) -> 8096.2665 | H105: =SUM(H101:H104) -> 8116.5072 | I105: =SUM(I101:I104) -> 8136.7984 | J105: =SUM(J101:J104) -> 8157.1404 | K105: =SUM(K101:K104) -> 8177.5333 | L105: =SUM(L101:L104) -> 8197.9771 | M105: =SUM(M101:M104) -> 8218.4721 | ... FF105: =SUM(FF101:FF104) -> 11922.406 | FH105: =SUMIF($F$54:$FF$54,FH$54,$F105:$FF105) -> 48882.223 | FI105: =SUMIF($F$54:$FF$54,FI$54,$F105:$FF105) -> 99989.077 | FJ105: =SUMIF($F$54:$FF$54,FJ$54,$F105:$FF105) -> 103030.34 | FK105: =SUMIF($F$54:$FF$54,FK$54,$F105:$FF105) -> 106164.11 | FL105: =SUMIF($F$54:$FF$54,FL$54,$F105:$FF105) -> 109393.19 | FM105: =SUMIF($F$54:$FF$54,FM$54,$F105:$FF105) -> 112720.49 | FN105: =SUMIF($F$54:$FF$54,FN$54,$F105:$FF105) -> 116148.99 | FO105: =SUMIF($F$54:$FF$54,FO$54,$F105:$FF105) -> 119681.77 | ... FU105: =SUMIF($F$54:$FF$54,FU$54,$F105:$FF105) -> 71089.939
C107: Total Opex | E107: =SUM(F107:FF107) -> 8410536.5 | F107: =SUM(F98,F105) -> 0 | G107: =SUM(G98,G105) -> 44148.673 | H107: =SUM(H98,H105) -> 44259.044 | I107: =SUM(I98,I105) -> 44369.692 | J107: =SUM(J98,J105) -> 44480.616 | K107: =SUM(K98,K105) -> 44591.818 | L107: =SUM(L98,L105) -> 44703.297 | M107: =SUM(M98,M105) -> 44815.056 | ... FF107: =SUM(FF98,FF105) -> 65012.483 | FH107: =SUMIF($F$54:$FF$54,FH$54,$F107:$FF107) -> 266553.14 | FI107: =SUMIF($F$54:$FF$54,FI$54,$F107:$FF107) -> 545237.12 | FJ107: =SUMIF($F$54:$FF$54,FJ$54,$F107:$FF107) -> 561821.03 | FK107: =SUMIF($F$54:$FF$54,FK$54,$F107:$FF107) -> 578909.35 | FL107: =SUMIF($F$54:$FF$54,FL$54,$F107:$FF107) -> 596517.44 | FM107: =SUMIF($F$54:$FF$54,FM$54,$F107:$FF107) -> 614661.08 | FN107: =SUMIF($F$54:$FF$54,FN$54,$F107:$FF107) -> 633356.59 | FO107: =SUMIF($F$54:$FF$54,FO$54,$F107:$FF107) -> 652620.74 | ... FU107: =SUMIF($F$54:$FF$54,FU$54,$F107:$FF107) -> 387651.08
C108: Opex Margin | F108: =IFERROR(F107/SUM(F73,F79),0) -> 0 | G108: =IFERROR(G107/SUM(G73,G79),0) -> 0.37256497 | H108: =IFERROR(H107/SUM(H73,H79),0) -> 0.37256497 | I108: =IFERROR(I107/SUM(I73,I79),0) -> 0.37256497 | J108: =IFERROR(J107/SUM(J73,J79),0) -> 0.37256497 | K108: =IFERROR(K107/SUM(K73,K79),0) -> 0.37256497 | L108: =IFERROR(L107/SUM(L73,L79),0) -> 0.37256497 | M108: =IFERROR(M107/SUM(M73,M79),0) -> 0.37256497 | ... FF108: =IFERROR(FF107/SUM(FF73,FF79),0) -> 0.37256497 | FH108: =IFERROR(FH107/SUM(FH73,FH79),0) -> 0.37256497 | FM108: =IFERROR(FM107/SUM(FM73,FM79),0) -> 0.37256497 | FN108: =IFERROR(FN107/SUM(FN73,FN79),0) -> 0.37256497 | FO108: =IFERROR(FO107/SUM(FO73,FO79),0) -> 0.37256497 | FP108: =IFERROR(FP107/SUM(FP73,FP79),0) -> 0.37256497
C110: Resi NOI | E110: =SUM(F110:FF110) -> 12922540 | F110: =F87-F107 -> 0 | G110: =G87-G107 -> 67833.127 | H110: =H87-H107 -> 68002.71 | I110: =I87-I107 -> 68172.717 | J110: =J87-J107 -> 68343.149 | K110: =K87-K107 -> 68514.007 | L110: =L87-L107 -> 68685.292 | M110: =M87-M107 -> 68857.005 | ... FF110: =FF87-FF107 -> 99889.753 | FH110: =SUMIF($F$54:$FF$54,FH$54,$F110:$FF110) -> 409551 | FI110: =SUMIF($F$54:$FF$54,FI$54,$F110:$FF110) -> 837740.68 | FJ110: =SUMIF($F$54:$FF$54,FJ$54,$F110:$FF110) -> 863221.36 | FK110: =SUMIF($F$54:$FF$54,FK$54,$F110:$FF110) -> 889477.07 | FL110: =SUMIF($F$54:$FF$54,FL$54,$F110:$FF110) -> 916531.36 | FM110: =SUMIF($F$54:$FF$54,FM$54,$F110:$FF110) -> 944408.54 | FN110: =SUMIF($F$54:$FF$54,FN$54,$F110:$FF110) -> 973133.63 | FO110: =SUMIF($F$54:$FF$54,FO$54,$F110:$FF110) -> 1002732.4 | ... FU110: =SUMIF($F$54:$FF$54,FU$54,$F110:$FF110) -> 595614.4
...

Sheet Other Inputs>>

Sheet Pro Forma Template
E1: Mo | F1: =F56 -> 0 | G1: =G56 -> 1 | H1: =H56 -> 2 | I1: =I56 -> 3 | J1: =J56 -> 4 | K1: =K56 -> 5 | L1: =L56 -> 6 | M1: =M56 -> 7 | ... FD1: =FD56 -> 154
E2: Date | F2: =F58 -> 46174 | G2: =G58 -> 46203 | H2: =H58 -> 46234 | I2: =I58 -> 46265 | J2: =J58 -> 46295 | K2: =K58 -> 46326 | L2: =L58 -> 46356 | M2: =M58 -> 46387 | ... FD2: =FD58 -> 50860
C3: Base Assumptions
C4: # | D4: 101 | AN4: Under Construction
C5: Property Name:
C6: Address: | AN6: In Lease Up
C7: Timeline | K7: Income Analysis | S7: ACF Analysis
E8: BOP Mo | F8: BOP Date | G8: Duration | H8: EOP Date | I8: EOP Mo | K8: MR Unit Breakdown | N8: Unit Count | O8: Rent/Unit | P8: Average Size | Q8: Rent PSF | U8: Pro Forma | AA8: Historical Financials
C9: Acquisition Date | E9: 0 | F9: 46174 | G9: 1 | H9: =EOMONTH(F9,E9) -> 46203 | I9: =INDEX($F$56:$FV$56,MATCH(H9,$F$58:$FV$58,0)) -> 1 | K9: Studio | N9: 100 | O9: 2150 | P9: 1000 | Q9: =+O9/P9 -> 2.15 | U9: Untrended | V9: $/Unit | W9: Refinance | X9: $/Unit | Y9: At Exit | Z9: $/Unit | AA9: T-3 | AB9: $/Unit | AC9: T-6 | AD9: $/Unit | AE9: T-12 | AF9: $/Unit
C10: Hold Period | E10: =INDEX($F$56:$FV$56,MATCH(F10,$F$58:$FV$58,0)) -> 2 | F10: =EOMONTH(H9,1) -> 46234 | G10: 36 | H10: =EOMONTH(F10,G10-1) -> 47299 | I10: =INDEX($F$56:$FV$56,MATCH(H10,$F$58:$FV$58,0)) -> 37 | K10: 1 Bedroom | N10: 0 | O10: 0 | P10: 0 | Q10: =IFERROR(+O10/P10,0) -> 0 | S10: Potential Market Rent | U10: =V10*$N$13*12 -> 2580000 | V10: =O13 -> 2150 | W10: =SUM(OFFSET(F74,0,$G$40,1,-12)) -> 2791218.6 | X10: =W10/$N$13 -> 27912.186 | Y10: =SUM(OFFSET(F74,0,$I$40,1,-12)) -> 3234240.8 | Z10: =Y10/$N$13 -> 32342.408 | AA10: 0 | AB10: =AA10/$N$13 -> 0 | AC10: 0 | AD10: =AC10/$N$13 -> 0 | AE10: 0 | AF10: =AE10/$N$13 -> 0
C11: Refinance | E11: =INDEX($F$56:$FV$56,MATCH(F11,$F$58:$FV$58,0)) -> 37 | F11: =EOMONTH(H10,0) -> 47299 | G11: 1 | H11: =EOMONTH(F11,G11-1) -> 47299 | I11: =INDEX($F$56:$FV$56,MATCH(H11,$F$58:$FV$58,0)) -> 37 | K11: 2 Bedroom | N11: 0 | O11: 0 | P11: 0 | Q11: =IFERROR(+O11/P11,0) -> 0 | S11: Loss to Lease | U11: 0 | V11: =U11/$N$13 -> 0 | W11: =SUM(OFFSET(F75,0,$G$40,1,-12)) -> -6978.0465 | X11: =W11/$N$13 -> -69.780465 | Y11: =SUM(OFFSET(F75,0,$I$40,1,-12)) -> -8085.6019 | Z11: =Y11/$N$13 -> -80.856019 | AA11: 0 | AB11: =AA11/$N$13 -> 0 | AC11: 0 | AD11: =AC11/$N$13 -> 0 | AE11: 0 | AF11: =AE11/$N$13 -> 0
C12: Hold Period | D12: 8 | E12: =INDEX($F$56:$FV$56,MATCH(F12,$F$58:$FV$58,0)) -> 38 | F12: =EOMONTH(H11,1) -> 47330 | G12: =I12-E12+1 -> 59 | H12: =EOMONTH(F9,D12*12) -> 49125 | I12: =D12*12 -> 96 | K12: 3 Bedroom | N12: 0 | O12: 0 | P12: 0 | Q12: =IFERROR(+O12/P12,0) -> 0 | S12: Gross Potential Rent | U12: =SUM(U10:U11) -> 2580000 | V12: =SUM(V10:V11) -> 2150 | W12: =SUM(W10:W11) -> 2784240.5 | X12: =W12/$N$13 -> 27842.405 | Y12: =SUM(Y10:Y11) -> 3226155.2 | Z12: =Y12/$N$13 -> 32261.552 | AA12: =SUM(AA10:AA11) -> 0 | AB12: =AA12/$N$13 -> 0 | AC12: =SUM(AC10:AC11) -> 0 | AD12: =AC12/$N$13 -> 0 | AE12: =SUM(AE10:AE11) -> 0 | AF12: =AE12/$N$13 -> 0
K13: Total/Avg (MR+BMR) | N13: =SUM(N9:N12) -> 100 | O13: =SUMPRODUCT(O9:O12,$N$9:$N$12)/$N$13 -> 2150 | P13: =SUMPRODUCT(P9:P12,$N$9:$N$12)/$N$13 -> 1000 | Q13: =SUMPRODUCT(Q9:Q12,$N$9:$N$12)/$N$13 -> 2.15
C14: Project Costs | S14: =K16 -> RUBS | U14: =U38*$N$16 -> 70000 | V14: =U14/$N$13 -> 700 | W14: =SUM(OFFSET(F79,0,$G$40,1,-12)) -> 75730.737 | X14: =W14/$N$13 -> 757.30737 | Y14: =SUM(OFFSET(F79,0,$I$40,1,-12)) -> 87750.718 | Z14: =Y14/$N$13 -> 877.50718 | AA14: 0 | AB14: =AA14/$N$13 -> 0 | AC14: 0 | AD14: =AC14/$N$13 -> 0 | AE14: 0 | AF14: =AE14/$N$13 -> 0
D15: Total Costs | E15: $/Unit | F15: $/RSF | G15: % at Closing | H15: Start Date | I15: Duration | K15: Other Income | N15: % | O15: Count | P15: $ / Unit / Mo | Q15: Annual Total | S15: =K17 -> Parking | U15: =O17*P17*12 -> 0 | V15: =U15/$N$13 -> 0 | W15: =SUM(OFFSET(F80,0,$G$40,1,-12)) -> 0 | X15: =W15/$N$13 -> 0 | Y15: =SUM(OFFSET(F80,0,$I$40,1,-12)) -> 0 | Z15: =Y15/$N$13 -> 0 | AA15: 0 | AB15: =AA15/$N$13 -> 0 | AC15: 0 | AD15: =AC15/$N$13 -> 0 | AE15: 0 | AF15: =AE15/$N$13 -> 0
C16: Acquisition Cost | D16: 25000000 | E16: =D16/$N$13 -> 250000 | F16: =D16/($P$13*$N$13) -> 250 | G16: 1 | H16: =$H$9 -> 46203 | I16: 0 | K16: RUBS | N16: 0.7 | O16: =$N$13 -> 100 | P16: =IFERROR(Q16/O16,0) -> 700 | Q16: =N16*U38 -> 70000 | S16: =K18 -> Other | U16: =Q18 -> 150000 | V16: =U16/$N$13 -> 1500 | W16: =SUM(OFFSET(F81,0,$G$40,1,-12)) -> 162280.15 | X16: =W16/$N$13 -> 1622.8015 | Y16: =SUM(OFFSET(F81,0,$I$40,1,-12)) -> 188037.25 | Z16: =Y16/$N$13 -> 1880.3725 | AA16: 0 | AB16: =AA16/$N$13 -> 0 | AC16: 0 | AD16: =AC16/$N$13 -> 0 | AE16: 0 | AF16: =AE16/$N$13 -> 0
C17: Closing Cost | D17: =D16*1% -> 250000 | E17: =D17/$N$13 -> 2500 | F17: =D17/($P$13*$N$13) -> 2.5 | G17: 1 | H17: =$H$9 -> 46203 | I17: 0 | K17: Parking | O17: =$N$13 -> 100 | P17: 0 | Q17: =P17*O17*12 -> 0 | S17: Total Other Income | U17: =SUM(U14:U16) -> 220000 | V17: =SUM(V14:V16) -> 2200 | W17: =SUM(W14:W16) -> 238010.89 | X17: =W17/$N$13 -> 2380.1089 | Y17: =SUM(Y14:Y16) -> 275787.97 | Z17: =Y17/$N$13 -> 2757.8797 | AA17: =SUM(AA14:AA16) -> 0 | AB17: =AA17/$N$13 -> 0 | AC17: =SUM(AC14:AC16) -> 0 | AD17: =AC17/$N$13 -> 0 | AE17: =SUM(AE14:AE16) -> 0 | AF17: =AE17/$N$13 -> 0
C18: Acquisition Fee | D18: =D16*1% -> 250000 | E18: =D18/$N$13 -> 2500 | F18: =D18/($P$13*$N$13) -> 2.5 | G18: 1 | H18: =$H$9 -> 46203 | I18: 0 | K18: Other | N18: =Q18/U10 -> 0.058139535 | O18: =$N$13 -> 100 | P18: 125 | Q18: =O18*P18*12 -> 150000
C19: Capital Improvements | D19: =E19*N13 -> 1500000 | E19: 15000 | F19: =D19/($P$13*$N$13) -> 15 | G19: 0 | H19: =$H$9 -> 46203 | I19: 12 | K19: Total Other Income | Q19: =SUM(Q16:Q18) -> 220000 | S19: =K23 -> Vacancy Loss | U19: =-SUM($U$12,$U$17)*$M23 -> -140000 | V19: =U19/$N$13 -> -1400 | W19: =SUM(OFFSET(F84,0,$G$40,1,-12)) -> -151112.57 | X19: =W19/$N$13 -> -1511.1257 | Y19: =SUM(OFFSET(F84,0,$I$40,1,-12)) -> -175097.16 | Z19: =Y19/$N$13 -> -1750.9716 | AA19: 0 | AB19: =AA19/$N$13 -> 0 | AC19: 0 | AD19: =AC19/$N$13 -> 0 | AE19: 0 | AF19: =AE19/$N$13 -> 0
C20: Other | D20: =E20*$N$13 -> 0 | E20: 0 | F20: =D20/($P$13*$N$13) -> 0 | G20: 0 | H20: =$H$9 -> 46203 | I20: 0 | S20: =K24 -> Bad Debt | U20: =-SUM($U$12,$U$17)*$M24 -> -7000 | V20: =U20/$N$13 -> -70 | W20: =SUM(OFFSET(F85,0,$G$40,1,-12)) -> -7555.6286 | X20: =W20/$N$13 -> -75.556286 | Y20: =SUM(OFFSET(F85,0,$I$40,1,-12)) -> -8754.8578 | Z20: =Y20/$N$13 -> -87.548578 | AA20: 0 | AB20: =AA20/$N$13 -> 0 | AC20: 0 | AD20: =AC20/$N$13 -> 0 | AE20: 0 | AF20: =AE20/$N$13 -> 0
C21: Other | D21: =E21*$N$13 -> 0 | E21: 0 | F21: =D21/($P$13*$N$13) -> 0 | G21: 0 | H21: =$H$9 -> 46203 | I21: 0 | K21: Income Adjustments | M21: =IF(MONTH(F9)=12,YEAR(F9)+1,YEAR(F9)) -> 2026 | N21: =M21+1 -> 2027 | O21: =N21+1 -> 2028 | P21: =O21+1 -> 2029 | Q21: =P21+1 -> 2030 | S21: =K25 -> Concessions | U21: =-SUM($U$12,$U$17)*$M25 -> -7000 | V21: =U21/$N$13 -> -70 | W21: =SUM(OFFSET(F86,0,$G$40,1,-12)) -> -7555.6286 | X21: =W21/$N$13 -> -75.556286 | Y21: =SUM(OFFSET(F86,0,$I$40,1,-12)) -> -8754.8578 | Z21: =Y21/$N$13 -> -87.548578 | AA21: 0 | AB21: =AA21/$N$13 -> 0 | AC21: 0 | AD21: =AC21/$N$13 -> 0 | AE21: 0 | AF21: =AE21/$N$13 -> 0
C22: Other | D22: 0 | E22: =D22/$N$13 -> 0 | F22: =D22/($P$13*$N$13) -> 0 | G22: 0 | H22: =$H$9 -> 46203 | I22: 0 | K22: Loss to Lease | M22: 0.0025 | N22: 0.0025 | O22: 0.0025 | P22: 0.0025 | Q22: 0.0025 | S22: =K26 -> Model Units | U22: =-O13*M26*12 -> -25800 | V22: =U22/$N$13 -> -258 | W22: =SUM(OFFSET(F87,0,$G$40,1,-12)) -> -27912.186 | X22: =W22/$N$13 -> -279.12186 | Y22: =SUM(OFFSET(F87,0,$I$40,1,-12)) -> -32342.408 | Z22: =Y22/$N$13 -> -323.42408 | AA22: 0 | AB22: =AA22/$N$13 -> 0 | AC22: 0 | AD22: =AC22/$N$13 -> 0 | AE22: 0 | AF22: =AE22/$N$13 -> 0
C23: Total Project Costs | D23: =SUM(D16:D22) -> 27000000 | E23: =D23/$N$13 -> 270000 | F23: =D23/($P$13*$N$13) -> 270 | H23: Cost Schedule | I23: Straight Line | K23: Vacancy Loss | M23: 0.05 | N23: 0.05 | O23: 0.05 | P23: 0.05 | Q23: 0.05 | S23: Total Income Adjustments | U23: =SUM(U19:U22) -> -179800 | V23: =SUM(V19:V22) -> -1798 | W23: =SUM(W19:W22) -> -194136.01 | X23: =W23/$N$13 -> -1941.3601 | Y23: =SUM(Y19:Y22) -> -224949.28 | Z23: =Y23/$N$13 -> -2249.4928 | AA23: =SUM(AA19:AA22) -> 0 | AB23: =AA23/$N$13 -> 0 | AC23: =SUM(AC19:AC22) -> 0 | AD23: =AC23/$N$13 -> 0 | AE23: =SUM(AE19:AE22) -> 0 | AF23: =AE23/$N$13 -> 0
K24: Bad Debt | M24: 0.0025 | N24: 0.0025 | O24: 0.0025 | P24: 0.0025 | Q24: 0.0025
C25: Financing Assumptions | K25: Concessions | M25: 0.0025 | N25: 0.0025 | O25: 0.0025 | P25: 0.0025 | Q25: 0.0025 | S25: EGI | U25: =SUM(U12,U17,U23) -> 2620200 | V25: =SUM(V12,V17,V23) -> 2552 | W25: =SUM(W12,W17,W23) -> 2828115.4 | X25: =SUM(X12,X17,X23) -> 28281.154 | Y25: =SUM(Y12,Y17,Y23) -> 3276993.8 | Z25: =SUM(Z12,Z17,Z23) -> 32769.938 | AA25: =SUM(AA12,AA17,AA23) -> 0 | AB25: =SUM(AB12,AB17,AB23) -> 0 | ... AF25: =SUM(AF12,AF17,AF23) -> 0
C26: Senior Financing | E26: Senior Financing | H26: Refinance | K26: Model Units | M26: 1 | N26: 1 | O26: 1 | P26: 1 | Q26: 1
C27: Lender | F27: TBD | G27: Lender | I27: TBD | K27: Growth Assumptions | M27: =IF(MONTH(F9)=12,YEAR(F9)+1,YEAR(F9)) -> 2026 | N27: =M27+1 -> 2027 | O27: =N27+1 -> 2028 | P27: =O27+1 -> 2029 | Q27: =P27+1 -> 2030 | S27: Opex
C28: Loan Proceeds | E28: 0.55 | F28: =E28*$D$23 -> 14850000 | G28: Loan Proceeds | H28: DSCR | I28: =INDEX($I$34:$I$36,MATCH(H28,$G$34:$G$36,0)) -> 21662073 | K28: Market Rent | M28: 0.03 | N28: 0.03 | O28: 0.03 | P28: 0.03 | Q28: 0.03 | S28: Payroll | U28: =V28*$N$13 -> 150000 | V28: 1500 | W28: =SUM(OFFSET(F94,0,$G$40,1,-12)) -> 162280.15 | X28: =W28/$N$13 -> 1622.8015 | Y28: =SUM(OFFSET(F94,0,$I$40,1,-12)) -> 188037.25 | Z28: =Y28/$N$13 -> 1880.3725 | AA28: 0 | AB28: =AA28/$N$13 -> 0 | AC28: 0 | AD28: =AC28/$N$13 -> 0 | AE28: 0 | AF28: =AE28/$N$13 -> 0
C29: Term | E29: 36 | F29: =EOMONTH(F9,E29) -> 47299 | G29: Term | H29: 360 | I29: =EOMONTH(F29,H29-1) -> 58226 | K29: Other Income | M29: 0.03 | N29: 0.03 | O29: 0.03 | P29: 0.03 | Q29: 0.03 | S29: Admin | U29: =V29*$N$13 -> 30000 | V29: 300 | W29: =SUM(OFFSET(F95,0,$G$40,1,-12)) -> 32456.03 | X29: =W29/$N$13 -> 324.5603 | Y29: =SUM(OFFSET(F95,0,$I$40,1,-12)) -> 37607.451 | Z29: =Y29/$N$13 -> 376.07451 | AA29: 0 | AB29: =AA29/$N$13 -> 0 | AC29: 0 | AD29: =AC29/$N$13 -> 0 | AE29: 0 | AF29: =AE29/$N$13 -> 0
C30: Interest Rate | E30: Fixed | F30: 0.07 | G30: Interest Rate | H30: Fixed | I30: 0.06 | K30: Operating Expenses | M30: 0.03 | N30: 0.03 | O30: 0.03 | P30: 0.03 | Q30: 0.03 | S30: Marketing | U30: =V30*$N$13 -> 30000 | V30: 300 | W30: =SUM(OFFSET(F96,0,$G$40,1,-12)) -> 32456.03 | X30: =W30/$N$13 -> 324.5603 | Y30: =SUM(OFFSET(F96,0,$I$40,1,-12)) -> 37607.451 | Z30: =Y30/$N$13 -> 376.07451 | AA30: 0 | AB30: =AA30/$N$13 -> 0 | AC30: 0 | AD30: =AC30/$N$13 -> 0 | AE30: 0 | AF30: =AE30/$N$13 -> 0
C31: Financing Costs | E31: 0.01 | F31: =E31*F28 -> 148500 | G31: Financing Costs | H31: 0.005 | I31: =H31*I28 -> 108310.36 | K31: Property Taxes | M31: 0.03 | N31: 0.03 | O31: 0.03 | P31: 0.03 | Q31: 0.03 | S31: R&M | U31: =V31*$N$13 -> 30000 | V31: 300 | W31: =SUM(OFFSET(F97,0,$G$40,1,-12)) -> 32456.03 | X31: =W31/$N$13 -> 324.5603 | Y31: =SUM(OFFSET(F97,0,$I$40,1,-12)) -> 37607.451 | Z31: =Y31/$N$13 -> 376.07451 | AA31: 0 | AB31: =AA31/$N$13 -> 0 | AC31: 0 | AD31: =AC31/$N$13 -> 0 | AE31: 0 | AF31: =AE31/$N$13 -> 0
C32: IO Periods/Amortization | E32: 24 | F32: =PMT(F30/12,360,-F28,0,) -> 98797.421 | G32: IO Periods/Amortization | H32: 24 | I32: =PMT(I30/12,360,-I28,0,) -> 129875.07 | S32: Contract Service | U32: =V32*$N$13 -> 30000 | V32: 300 | W32: =SUM(OFFSET(F98,0,$G$40,1,-12)) -> 32456.03 | X32: =W32/$N$13 -> 324.5603 | Y32: =SUM(OFFSET(F98,0,$I$40,1,-12)) -> 37607.451 | Z32: =Y32/$N$13 -> 376.07451 | AA32: 0 | AB32: =AA32/$N$13 -> 0 | AC32: 0 | AD32: =AC32/$N$13 -> 0 | AE32: 0 | AF32: =AE32/$N$13 -> 0
C33: Debt Metrics | G33: Debt Metrics | K33: Property Taxes | S33: Turnover | U33: =V33*$N$13 -> 30000 | V33: 300 | W33: =SUM(OFFSET(F99,0,$G$40,1,-12)) -> 32456.03 | X33: =W33/$N$13 -> 324.5603 | Y33: =SUM(OFFSET(F99,0,$I$40,1,-12)) -> 37607.451 | Z33: =Y33/$N$13 -> 376.07451 | AA33: 0 | AB33: =AA33/$N$13 -> 0 | AC33: 0 | AD33: =AC33/$N$13 -> 0 | AE33: 0 | AF33: =AE33/$N$13 -> 0
C34: DSCR | F34: =U48/(PMT(6%/12,360,-F28,0)*12) -> 1.6909589 | G34: DSCR | H34: 1.25 | I34: =PV(I30/12,H29,-F41/12/H34) -> 21662073 | M34: Current | N34: Next Buyer | O34: Note | S34: Other | U34: =V34*$N$13 -> 0 | V34: 0 | W34: =SUM(OFFSET(F100,0,$G$40,1,-12)) -> 0 | X34: =W34/$N$13 -> 0 | Y34: =SUM(OFFSET(F100,0,$I$40,1,-12)) -> 0 | Z34: =Y34/$N$13 -> 0 | AA34: 0 | AB34: =AA34/$N$13 -> 0 | AC34: 0 | AD34: =AC34/$N$13 -> 0 | AE34: 0 | AF34: =AE34/$N$13 -> 0
C35: DY | F35: =U48/F28 -> 0.12165783 | G35: DY | H35: 0.08 | I35: =F41/H35 -> 24351576 | K35: Assessed Value | M35: =M36*N13 -> 14000000 | N35: =N36*N13 -> 14000000 | S35: Total Controllable Expenses | U35: =SUM(U28:U34) -> 300000 | V35: =SUM(V28:V34) -> 3000 | W35: =SUM(W28:W34) -> 324560.3 | X35: =SUM(X28:X34) -> 3245.603 | Y35: =SUM(Y28:Y34) -> 376074.51 | Z35: =SUM(Z28:Z34) -> 3760.7451 | AA35: =SUM(AA28:AA34) -> 0 | AB35: =AA35/$N$13 -> 0 | AC35: =SUM(AC28:AC34) -> 0 | AD35: =AC35/$N$13 -> 0 | AE35: =SUM(AE28:AE34) -> 0 | AF35: =AE35/$N$13 -> 0
C36: LTV | G36: LTV | H36: 0.75 | I36: =H36*F45 -> 25410340 | K36: Assessed Value/Unit | M36: 140000 | N36: =M36 -> 140000
K37: Assessment % | M37: 1 | N37: =M37 -> 1 | S37: Insurance | U37: =V37*$N$13 -> 50000 | V37: 500 | W37: =SUM(OFFSET(F104,0,$G$40,1,-12)) -> 54093.384 | X37: =W37/$N$13 -> 540.93384 | Y37: =SUM(OFFSET(F104,0,$I$40,1,-12)) -> 62679.084 | Z37: =Y37/$N$13 -> 626.79084 | AA37: 0 | AB37: =AA37/$N$13 -> 0 | AC37: 0 | AD37: =AC37/$N$13 -> 0 | AE37: 0 | AF37: =AE37/$N$13 -> 0 | AI37: 1 | AJ37: =AI37*(1+AJ31) -> 1 | AK37: =AJ37*(1+AK31) -> 1 | AL37: =AK37*(1+AL31) -> 1 | AM37: =AL37*(1+AM31) -> 1 | AN37: =AM37*(1+AN31) -> 1
C38: Residual Analysis | K38: Millage Rate | M38: 0.018926798 | N38: 0.018926798 | S38: Utilities | U38: =V38*$N$13 -> 100000 | V38: 1000 | W38: =SUM(OFFSET(F105,0,$G$40,1,-12)) -> 108186.77 | X38: =W38/$N$13 -> 1081.8677 | Y38: =SUM(OFFSET(F105,0,$I$40,1,-12)) -> 125358.17 | Z38: =Y38/$N$13 -> 1253.5817 | AA38: 0 | AB38: =AA38/$N$13 -> 0 | AC38: 0 | AD38: =AC38/$N$13 -> 0 | AE38: 0 | AF38: =AE38/$N$13 -> 0
F39: Refinance | G39: $/Unit | H39: Exit | I39: $/Unit | K39: Special Assessment | M39: 0 | N39: 0 | S39: Management Fee | T39: 0.03 | U39: =T39*U25 -> 78606 | V39: =U39/N13 -> 786.06 | W39: =SUM(OFFSET(F106,0,$G$40,1,-12)) -> 84843.463 | X39: =W39/$N$13 -> 848.43463 | Y39: =SUM(OFFSET(F106,0,$I$40,1,-12)) -> 98309.815 | Z39: =Y39/$N$13 -> 983.09815 | AA39: 0 | AB39: =AA39/$N$13 -> 0 | AC39: 0 | AD39: =AC39/$N$13 -> 0 | AE39: 0 | AF39: =AE39/$N$13 -> 0
C40: Date | Month | F40: =F11 -> 47299 | G40: =E11 -> 37 | H40: =H12 -> 49125 | I40: =I12 -> 96 | K40: Total Property Tax | M40: =M35*M38 -> 264975.17 | N40: =N35*N38 -> 264975.17 | S40: Property Tax | U40: =V40*$N$13 -> 264975.17 | V40: =N41 -> 2649.7517 | W40: =SUM(OFFSET(F107,0,$G$40,1,-12)) -> 286668.07 | X40: =W40/$N$13 -> 2866.6807 | Y40: =SUM(OFFSET(F107,0,$I$40,1,-12)) -> 332168.02 | Z40: =Y40/$N$13 -> 3321.6802 | AA40: 0 | AB40: =AA40/$N$13 -> 0 | AC40: 0 | AD40: =AC40/$N$13 -> 0 | AE40: 0 | AF40: =AE40/$N$13 -> 0
C41: NOI (TTM) | F41: =INDEX($F$125:$FV$125,MATCH(G40,$F$56:$FV$56,0)) -> 1948126.1 | H41: =INDEX($F$125:$FV$125,MATCH(I40,$F$56:$FV$56,0)) -> 2257332.6 | K41: Total Property Tax/Unit | M41: =M40/$N$13 -> 2649.7517 | N41: =N40/$N$13 -> 2649.7517 | S41: Total Non-controllable Expenses | U41: =SUM(U37:U40) -> 493581.17 | V41: =SUM(V37:V40) -> 4935.8117 | W41: =SUM(W37:W40) -> 533791.69 | X41: =W41/$N$13 -> 5337.9169 | Y41: =SUM(Y37:Y40) -> 618515.09 | Z41: =Y41/$N$13 -> 6185.1509 | AA41: =SUM(AA37:AA40) -> 0 | AB41: =AA41/$N$13 -> 0 | AC41: =SUM(AC37:AC40) -> 0 | AD41: =AC41/$N$13 -> 0 | AE41: =SUM(AE37:AE40) -> 0 | AF41: =AE41/$N$13 -> 0
C42: Cap Rate | F42: 0.0575 | H42: 0.0575 | S42: Total Opex | U42: =SUM(U35,U41) -> 793581.17 | V42: =SUM(V35,V41) -> 7935.8117 | W42: =SUM(W35,W41) -> 858351.99 | X42: =W42/$N$13 -> 8583.5199 | Y42: =SUM(Y35,Y41) -> 994589.6 | Z42: =Y42/$N$13 -> 9945.896 | AA42: =SUM(AA35,AA41) -> 0 | AB42: =AA42/$N$13 -> 0 | AC42: =SUM(AC35,AC41) -> 0 | AD42: =AC42/$N$13 -> 0 | AE42: =SUM(AE35,AE41) -> 0 | AF42: =AE42/$N$13 -> 0
C43: Gross Value | F43: =F41/F42 -> 33880454 | G43: =F43/$N$13 -> 338804.54 | H43: =H41/H42 -> 39257958 | I43: =H43/$N$13 -> 392579.58 | K43: Returns Metrics | S43: Opex Margin | U43: =U42/U25 -> 0.30287046 | W43: =W42/W25 -> 0.3035067 | Y43: =Y42/Y25 -> 0.3035067
C44: Value Adjustments | F44: 0 | H44: 0 | L44: Unlevered CF | M44: Levered CF
C45: Net Gross Value | F45: =F43+F44 -> 33880454 | G45: =F45/$N$13 -> 338804.54 | H45: =H43+H44 -> 39257958 | I45: =H45/$N$13 -> 392579.58 | K45: Net Profit | L45: =SUM((F153:FC153)) -> 28164511 | M45: =SUM(F162:FC162) -> 18717683 | S45: NOI | U45: =U25-U42 -> 1826618.8 | V45: =V25+V42 -> 10487.812 | W45: =W25-W42 -> 1969763.4 | X45: =W45/$N$13 -> 19697.634 | Y45: =Y25-Y42 -> 2282404.2 | Z45: =Y45/$N$13 -> 22824.042 | AA45: =AA25-AA42 -> 0 | AB45: =AA45/$N$13 -> 0 | AC45: =AC25-AC42 -> 0 | AD45: =AC45/$N$13 -> 0 | AE45: =AE25-AE42 -> 0 | AF45: =AE45/$N$13 -> 0
K46: Peak Equity | L46: =SUMIF($F$153:$FC$153,"<0",$F$153:$FC$153) -> -25500000 | M46: =SUMIF($F$162:$FC$162,"<0",$F$162:$FC$162) -> -33846439
C47: Sales Costs | E47: % | F47: Total | G47: $/Unit | H47: Total | I47: $/Unit | K47: IRR | L47: =(1+IRR(F153:FC153,0))^12-1 -> 0.11501071 | M47: =(1+IRR(F162:FC162,0))^12-1 -> 0.17620049 | S47: Cap Reserve | U47: =V47*$N$13 -> 20000 | V47: 200 | W47: =SUM(OFFSET(F119,0,$G$40,1,-12)) -> 21637.353 | X47: =W47/$N$13 -> 216.37353 | Y47: =SUM(OFFSET(F119,0,$I$40,1,-12)) -> 25071.634 | Z47: =Y47/$N$13 -> 250.71634 | AA47: 0 | AB47: =AA47/$N$13 -> 0 | AC47: 0 | AD47: =AC47/$N$13 -> 0 | AE47: 0 | AF47: =AE47/$N$13 -> 0
C48: Transfer Tax | E48: 0.0025 | F48: =F$45*$E48 -> 84701.134 | G48: =F48/$N$13 -> 847.01134 | H48: =H$45*$E48 -> 98144.896 | I48: =H48/$N$13 -> 981.44896 | K48: Equity Multiple | L48: =(L45-L46)/-L46 -> 2.1044906 | M48: =(M45-M46)/-M46 -> 1.5530178 | S48: NOI after Cap Reserve | U48: =U45-U47 -> 1806618.8 | V48: =V45-V47 -> 10287.812 | W48: =W45-W47 -> 1948126.1 | X48: =W48/$N$13 -> 19481.261 | Y48: =Y45-Y47 -> 2257332.6 | Z48: =Y48/$N$13 -> 22573.326 | AA48: =AA45-AA47 -> 0 | AB48: =AA48/$N$13 -> 0 | AC48: =AC45-AC47 -> 0 | AD48: =AC48/$N$13 -> 0 | AE48: =AE45-AE47 -> 0 | AF48: =AE48/$N$13 -> 0
C49: Broker Fee | E49: 0.0025 | F49: =F$45*$E49 -> 84701.134 | G49: =F49/$N$13 -> 847.01134 | H49: =H$45*$E49 -> 98144.896 | I49: =H49/$N$13 -> 981.44896 | S49: ROC | U49: =U48/$D$23 -> 0.066911808 | W49: =W48/$D$23 -> 0.072152818 | Y49: =Y48/$D$23 -> 0.083604912
C50: Escrow | E50: 0.0025 | F50: =F$45*$E50 -> 84701.134 | G50: =F50/$N$13 -> 847.01134 | H50: =H$45*$E50 -> 98144.896 | I50: =H50/$N$13 -> 981.44896 | K50: FALSE | S50: % Growth
C51: Misc. | E51: 0.0025 | F51: =F$45*$E51 -> 84701.134 | G51: =F51/$N$13 -> 847.01134 | H51: =H$45*$E51 -> 98144.896 | I51: =H51/$N$13 -> 981.44896
C52: Total Sales Costs | E52: =SUM(E48:E51) -> 0.01 | F52: =SUM(F48:F51) -> 338804.54 | G52: =F52/$N$13 -> 3388.0454 | H52: =SUM(H48:H51) -> 392579.58 | I52: =H52/$N$13 -> 3925.7958
C53: Net Sales Proceeds | F53: =F45-F52 -> 33541649 | G53: =G45-G52 -> 335416.49 | H53: =H45-H52 -> 38865379 | I53: =I45-I52 -> 388653.79
C55: Yr | F55: 0 | G55: 1 | H55: 1 | I55: 1 | J55: 1 | K55: 1 | L55: 1 | M55: 1 | N55: 1 | O55: 1 | P55: 1 | Q55: 1 | R55: 1 | S55: =G55+1 -> 2 | T55: =H55+1 -> 2 | U55: =I55+1 -> 2 | V55: =J55+1 -> 2 | W55: =K55+1 -> 2 | X55: =L55+1 -> 2 | Y55: =M55+1 -> 2 | Z55: =N55+1 -> 2 | ... FF55: =ET55+1 -> 13 | FH55: Annual Cash Flow
C56: Mo | F56: 0 | G56: =F56+1 -> 1 | H56: =G56+1 -> 2 | I56: =H56+1 -> 3 | J56: =I56+1 -> 4 | K56: =J56+1 -> 5 | L56: =K56+1 -> 6 | M56: =L56+1 -> 7 | N56: =M56+1 -> 8 | ... FF56: =FE56+1 -> 156
C57: Calendar Year | F57: =YEAR(F58) -> 2026 | G57: =YEAR(G58) -> 2026 | H57: =YEAR(H58) -> 2026 | I57: =YEAR(I58) -> 2026 | J57: =YEAR(J58) -> 2026 | K57: =YEAR(K58) -> 2026 | L57: =YEAR(L58) -> 2026 | M57: =YEAR(M58) -> 2026 | ... FF57: =YEAR(FF58) -> 2039 | FH57: =YEAR(F9) -> 2026 | FI57: =FH57+1 -> 2027 | FJ57: =FI57+1 -> 2028 | FK57: =FJ57+1 -> 2029 | FL57: =FK57+1 -> 2030 | FM57: =FL57+1 -> 2031 | FN57: =FM57+1 -> 2032 | FO57: =FN57+1 -> 2033 | FP57: =FO57+1 -> 2034 | ... FU57: =FT57+1 -> 2039
C58: Property Cash Flows | E58: Total | F58: =F9 -> 46174 | G58: =EOMONTH(F58,0) -> 46203 | H58: =EOMONTH(G58,1) -> 46234 | I58: =EOMONTH(H58,1) -> 46265 | J58: =EOMONTH(I58,1) -> 46295 | K58: =EOMONTH(J58,1) -> 46326 | L58: =EOMONTH(K58,1) -> 46356 | M58: =EOMONTH(L58,1) -> 46387 | N58: =EOMONTH(M58,1) -> 46418 | O58: =EOMONTH(N58,1) -> 46446 | ... FF58: =EOMONTH(FE58,1) -> 50921
C59: Pro Forma
C60: Growth Assumptions
C61: =K28 -> Market Rent | F61: 0 | G61: =IFERROR(INDEX($M28:$Q28,MATCH(YEAR(G$58),$M$27:$Q$27,0))/12,F61) -> 0.0025 | H61: =IFERROR(INDEX($M28:$Q28,MATCH(YEAR(H$58),$M$27:$Q$27,0))/12,G61) -> 0.0025 | I61: =IFERROR(INDEX($M28:$Q28,MATCH(YEAR(I$58),$M$27:$Q$27,0))/12,H61) -> 0.0025 | J61: =IFERROR(INDEX($M28:$Q28,MATCH(YEAR(J$58),$M$27:$Q$27,0))/12,I61) -> 0.0025 | K61: =IFERROR(INDEX($M28:$Q28,MATCH(YEAR(K$58),$M$27:$Q$27,0))/12,J61) -> 0.0025 | L61: =IFERROR(INDEX($M28:$Q28,MATCH(YEAR(L$58),$M$27:$Q$27,0))/12,K61) -> 0.0025 | M61: =IFERROR(INDEX($M28:$Q28,MATCH(YEAR(M$58),$M$27:$Q$27,0))/12,L61) -> 0.0025 | N61: =IFERROR(INDEX($M28:$Q28,MATCH(YEAR(N$58),$M$27:$Q$27,0))/12,M61) -> 0.0025 | ... FF61: =IFERROR(INDEX($M28:$Q28,MATCH(YEAR(FF$58),$M$27:$Q$27,0))/12,FE61) -> 0.0025 | FH61: =IFERROR(INDEX($M28:$Q28,MATCH(YEAR(FH$58),$M$27:$Q$27,0))/12,EZ61) -> 0.0025 | FM61: =IFERROR(INDEX($M28:$Q28,MATCH(YEAR(FM$58),$M$27:$Q$27,0))/12,FA61) -> 0.0025 | FN61: =IFERROR(INDEX($M28:$Q28,MATCH(YEAR(FN$58),$M$27:$Q$27,0))/12,FB61) -> 0.0025 | FO61: =IFERROR(INDEX($M28:$Q28,MATCH(YEAR(FO$58),$M$27:$Q$27,0))/12,FC61) -> 0.0025 | FP61: =IFERROR(INDEX($M28:$Q28,MATCH(YEAR(FP$58),$M$27:$Q$27,0))/12,FD61) -> 0.0025
C62: Compounded Rate | F62: 1 | G62: =F62*(1+G61) -> 1.0025 | H62: =G62*(1+H61) -> 1.0050062 | I62: =H62*(1+I61) -> 1.0075188 | J62: =I62*(1+J61) -> 1.0100376 | K62: =J62*(1+K61) -> 1.0125627 | L62: =K62*(1+L61) -> 1.0150941 | M62: =L62*(1+M61) -> 1.0176318 | N62: =M62*(1+N61) -> 1.0201759 | ... FF62: =FE62*(1+FF61) -> 1.4762621 | FH62: =EZ62*(1+FH61) -> 1.4579465 | FM62: =FA62*(1+FM61) -> 1.4615913 | FN62: =FB62*(1+FN61) -> 1.4652453 | FO62: =FC62*(1+FO61) -> 1.4689084 | FP62: =FD62*(1+FP61) -> 1.4725807
C63: =K29 -> Other Income | F63: 0 | G63: =IFERROR(INDEX($M29:$Q29,MATCH(YEAR(G$58),$M$27:$Q$27,0))/12,F63) -> 0.0025 | H63: =IFERROR(INDEX($M29:$Q29,MATCH(YEAR(H$58),$M$27:$Q$27,0))/12,G63) -> 0.0025 | I63: =IFERROR(INDEX($M29:$Q29,MATCH(YEAR(I$58),$M$27:$Q$27,0))/12,H63) -> 0.0025 | J63: =IFERROR(INDEX($M29:$Q29,MATCH(YEAR(J$58),$M$27:$Q$27,0))/12,I63) -> 0.0025 | K63: =IFERROR(INDEX($M29:$Q29,MATCH(YEAR(K$58),$M$27:$Q$27,0))/12,J63) -> 0.0025 | L63: =IFERROR(INDEX($M29:$Q29,MATCH(YEAR(L$58),$M$27:$Q$27,0))/12,K63) -> 0.0025 | M63: =IFERROR(INDEX($M29:$Q29,MATCH(YEAR(M$58),$M$27:$Q$27,0))/12,L63) -> 0.0025 | N63: =IFERROR(INDEX($M29:$Q29,MATCH(YEAR(N$58),$M$27:$Q$27,0))/12,M63) -> 0.0025 | ... FF63: =IFERROR(INDEX($M29:$Q29,MATCH(YEAR(FF$58),$M$27:$Q$27,0))/12,FE63) -> 0.0025 | FH63: =IFERROR(INDEX($M29:$Q29,MATCH(YEAR(FH$58),$M$27:$Q$27,0))/12,EZ63) -> 0.0025 | FM63: =IFERROR(INDEX($M29:$Q29,MATCH(YEAR(FM$58),$M$27:$Q$27,0))/12,FA63) -> 0.0025 | FN63: =IFERROR(INDEX($M29:$Q29,MATCH(YEAR(FN$58),$M$27:$Q$27,0))/12,FB63) -> 0.0025 | FO63: =IFERROR(INDEX($M29:$Q29,MATCH(YEAR(FO$58),$M$27:$Q$27,0))/12,FC63) -> 0.0025 | FP63: =IFERROR(INDEX($M29:$Q29,MATCH(YEAR(FP$58),$M$27:$Q$27,0))/12,FD63) -> 0.0025
C64: Compounded Rate | F64: 1 | G64: =F64*(1+G63) -> 1.0025 | H64: =G64*(1+H63) -> 1.0050062 | I64: =H64*(1+I63) -> 1.0075188 | J64: =I64*(1+J63) -> 1.0100376 | K64: =J64*(1+K63) -> 1.0125627 | L64: =K64*(1+L63) -> 1.0150941 | M64: =L64*(1+M63) -> 1.0176318 | N64: =M64*(1+N63) -> 1.0201759 | ... FF64: =FE64*(1+FF63) -> 1.4762621 | FH64: =EZ64*(1+FH63) -> 1.4579465 | FM64: =FA64*(1+FM63) -> 1.4615913 | FN64: =FB64*(1+FN63) -> 1.4652453 | FO64: =FC64*(1+FO63) -> 1.4689084 | FP64: =FD64*(1+FP63) -> 1.4725807
C65: =K30 -> Operating Expenses | F65: 0 | G65: =IFERROR(INDEX($M30:$Q30,MATCH(YEAR(G$58),$M$27:$Q$27,0))/12,F65) -> 0.0025 | H65: =IFERROR(INDEX($M30:$Q30,MATCH(YEAR(H$58),$M$27:$Q$27,0))/12,G65) -> 0.0025 | I65: =IFERROR(INDEX($M30:$Q30,MATCH(YEAR(I$58),$M$27:$Q$27,0))/12,H65) -> 0.0025 | J65: =IFERROR(INDEX($M30:$Q30,MATCH(YEAR(J$58),$M$27:$Q$27,0))/12,I65) -> 0.0025 | K65: =IFERROR(INDEX($M30:$Q30,MATCH(YEAR(K$58),$M$27:$Q$27,0))/12,J65) -> 0.0025 | L65: =IFERROR(INDEX($M30:$Q30,MATCH(YEAR(L$58),$M$27:$Q$27,0))/12,K65) -> 0.0025 | M65: =IFERROR(INDEX($M30:$Q30,MATCH(YEAR(M$58),$M$27:$Q$27,0))/12,L65) -> 0.0025 | N65: =IFERROR(INDEX($M30:$Q30,MATCH(YEAR(N$58),$M$27:$Q$27,0))/12,M65) -> 0.0025 | ... FF65: =IFERROR(INDEX($M30:$Q30,MATCH(YEAR(FF$58),$M$27:$Q$27,0))/12,FE65) -> 0.0025 | FH65: =IFERROR(INDEX($M30:$Q30,MATCH(YEAR(FH$58),$M$27:$Q$27,0))/12,EZ65) -> 0.0025 | FM65: =IFERROR(INDEX($M30:$Q30,MATCH(YEAR(FM$58),$M$27:$Q$27,0))/12,FA65) -> 0.0025 | FN65: =IFERROR(INDEX($M30:$Q30,MATCH(YEAR(FN$58),$M$27:$Q$27,0))/12,FB65) -> 0.0025 | FO65: =IFERROR(INDEX($M30:$Q30,MATCH(YEAR(FO$58),$M$27:$Q$27,0))/12,FC65) -> 0.0025 | FP65: =IFERROR(INDEX($M30:$Q30,MATCH(YEAR(FP$58),$M$27:$Q$27,0))/12,FD65) -> 0.0025
C66: Compounded Rate | F66: 1 | G66: =F66*(1+G65) -> 1.0025 | H66: =G66*(1+H65) -> 1.0050062 | I66: =H66*(1+I65) -> 1.0075188 | J66: =I66*(1+J65) -> 1.0100376 | K66: =J66*(1+K65) -> 1.0125627 | L66: =K66*(1+L65) -> 1.0150941 | M66: =L66*(1+M65) -> 1.0176318 | N66: =M66*(1+N65) -> 1.0201759 | ... FF66: =FE66*(1+FF65) -> 1.4762621 | FH66: =EZ66*(1+FH65) -> 1.4579465 | FM66: =FA66*(1+FM65) -> 1.4615913 | FN66: =FB66*(1+FN65) -> 1.4652453 | FO66: =FC66*(1+FO65) -> 1.4689084 | FP66: =FD66*(1+FP65) -> 1.4725807
C67: =K31 -> Property Taxes | F67: 0 | G67: =IFERROR(INDEX($M31:$Q31,MATCH(YEAR(G$58),$M$27:$Q$27,0))/12,F67) -> 0.0025 | H67: =IFERROR(INDEX($M31:$Q31,MATCH(YEAR(H$58),$M$27:$Q$27,0))/12,G67) -> 0.0025 | I67: =IFERROR(INDEX($M31:$Q31,MATCH(YEAR(I$58),$M$27:$Q$27,0))/12,H67) -> 0.0025 | J67: =IFERROR(INDEX($M31:$Q31,MATCH(YEAR(J$58),$M$27:$Q$27,0))/12,I67) -> 0.0025 | K67: =IFERROR(INDEX($M31:$Q31,MATCH(YEAR(K$58),$M$27:$Q$27,0))/12,J67) -> 0.0025 | L67: =IFERROR(INDEX($M31:$Q31,MATCH(YEAR(L$58),$M$27:$Q$27,0))/12,K67) -> 0.0025 | M67: =IFERROR(INDEX($M31:$Q31,MATCH(YEAR(M$58),$M$27:$Q$27,0))/12,L67) -> 0.0025 | N67: =IFERROR(INDEX($M31:$Q31,MATCH(YEAR(N$58),$M$27:$Q$27,0))/12,M67) -> 0.0025 | ... FF67: =IFERROR(INDEX($M31:$Q31,MATCH(YEAR(FF$58),$M$27:$Q$27,0))/12,FE67) -> 0.0025 | FH67: =IFERROR(INDEX($M31:$Q31,MATCH(YEAR(FH$58),$M$27:$Q$27,0))/12,EZ67) -> 0.0025 | FM67: =IFERROR(INDEX($M31:$Q31,MATCH(YEAR(FM$58),$M$27:$Q$27,0))/12,FA67) -> 0.0025 | FN67: =IFERROR(INDEX($M31:$Q31,MATCH(YEAR(FN$58),$M$27:$Q$27,0))/12,FB67) -> 0.0025 | FO67: =IFERROR(INDEX($M31:$Q31,MATCH(YEAR(FO$58),$M$27:$Q$27,0))/12,FC67) -> 0.0025 | FP67: =IFERROR(INDEX($M31:$Q31,MATCH(YEAR(FP$58),$M$27:$Q$27,0))/12,FD67) -> 0.0025
C68: Compounded Rate | F68: 1 | G68: =F68*(1+G67) -> 1.0025 | H68: =G68*(1+H67) -> 1.0050062 | I68: =H68*(1+I67) -> 1.0075188 | J68: =I68*(1+J67) -> 1.0100376 | K68: =J68*(1+K67) -> 1.0125627 | L68: =K68*(1+L67) -> 1.0150941 | M68: =L68*(1+M67) -> 1.0176318 | N68: =M68*(1+N67) -> 1.0201759 | ... FF68: =FE68*(1+FF67) -> 1.4762621 | FH68: =EZ68*(1+FH67) -> 1.4579465 | FM68: =FA68*(1+FM67) -> 1.4615913 | FN68: =FB68*(1+FN67) -> 1.4652453 | FO68: =FC68*(1+FO67) -> 1.4689084 | FP68: =FD68*(1+FP67) -> 1.4725807
C70: Rent Analysis
C71: Potential Gross MR Rent/Unit | F71: =O13 -> 2150 | G71: =F71*(1+G61) -> 2155.375 | H71: =G71*(1+H61) -> 2160.7634 | I71: =H71*(1+I61) -> 2166.1653 | J71: =I71*(1+J61) -> 2171.5808 | K71: =J71*(1+K61) -> 2177.0097 | L71: =K71*(1+L61) -> 2182.4522 | M71: =L71*(1+M61) -> 2187.9084 | N71: =M71*(1+N61) -> 2193.3781 | ... FF71: =FE71*(1+FF61) -> 3173.9636 | FH71: =EZ71*(1+FH61) -> 3134.5849 | FM71: =FA71*(1+FM61) -> 3142.4213 | FN71: =FB71*(1+FN61) -> 3150.2774 | FO71: =FC71*(1+FO61) -> 3158.1531 | FP71: =FD71*(1+FP61) -> 3166.0485
C73: Gross Potential Rent
C74: Gross Potential Revenue (Market Rate Units) | E74: =SUM(F74:FF74) -> 41060940 | F74: 0 | G74: =G71*$N$13 -> 215537.5 | H74: =H71*$N$13 -> 216076.34 | I74: =I71*$N$13 -> 216616.53 | J74: =J71*$N$13 -> 217158.08 | K74: =K71*$N$13 -> 217700.97 | L74: =L71*$N$13 -> 218245.22 | M74: =M71*$N$13 -> 218790.84 | N74: =N71*$N$13 -> 219337.81 | ... FF74: =FF71*$N$13 -> 317396.36 | FH74: =SUMIF($F$57:$FF$57,FH$57,$F74:$FF74) -> 1520125.5 | FI74: =SUMIF($F$57:$FF$57,FI$57,$F74:$FF74) -> 2668547.8 | FJ74: =SUMIF($F$57:$FF$57,FJ$57,$F74:$FF74) -> 2749714.2 | FK74: =SUMIF($F$57:$FF$57,FK$57,$F74:$FF74) -> 2833349.4 | FL74: =SUMIF($F$57:$FF$57,FL$57,$F74:$FF74) -> 2919528.5 | FM74: =SUMIF($F$57:$FF$57,FM$57,$F74:$FF74) -> 3008328.7 | FN74: =SUMIF($F$57:$FF$57,FN$57,$F74:$FF74) -> 3099829.9 | FO74: =SUMIF($F$57:$FF$57,FO$57,$F74:$FF74) -> 3194114.2 | ... FU74: =SUMIF($F$57:$FF$57,FU$57,$F74:$FF74) -> 1579086.4
C75: Loss-to-Lease (Market Rate Units) | E75: =SUM(F75:FF75) -> -102652.35 | F75: 0 | G75: =G74*-IFERROR(INDEX($M$22:$Q$22,MATCH(YEAR(G58),$M$21:$Q$21,0)),$Q$22) -> -538.84375 | H75: =H74*-IFERROR(INDEX($M$22:$Q$22,MATCH(YEAR(H58),$M$21:$Q$21,0)),$Q$22) -> -540.19086 | I75: =I74*-IFERROR(INDEX($M$22:$Q$22,MATCH(YEAR(I58),$M$21:$Q$21,0)),$Q$22) -> -541.54134 | J75: =J74*-IFERROR(INDEX($M$22:$Q$22,MATCH(YEAR(J58),$M$21:$Q$21,0)),$Q$22) -> -542.89519 | K75: =K74*-IFERROR(INDEX($M$22:$Q$22,MATCH(YEAR(K58),$M$21:$Q$21,0)),$Q$22) -> -544.25243 | L75: =L74*-IFERROR(INDEX($M$22:$Q$22,MATCH(YEAR(L58),$M$21:$Q$21,0)),$Q$22) -> -545.61306 | M75: =M74*-IFERROR(INDEX($M$22:$Q$22,MATCH(YEAR(M58),$M$21:$Q$21,0)),$Q$22) -> -546.97709 | N75: =N74*-IFERROR(INDEX($M$22:$Q$22,MATCH(YEAR(N58),$M$21:$Q$21,0)),$Q$22) -> -548.34453 | ... FF75: =FF74*-IFERROR(INDEX($M$22:$Q$22,MATCH(YEAR(FF58),$M$21:$Q$21,0)),$Q$22) -> -793.4909 | FH75: =SUMIF($F$57:$FF$57,FH$57,$F75:$FF75) -> -3800.3137 | FI75: =SUMIF($F$57:$FF$57,FI$57,$F75:$FF75) -> -6671.3695 | FJ75: =SUMIF($F$57:$FF$57,FJ$57,$F75:$FF75) -> -6874.2856 | FK75: =SUMIF($F$57:$FF$57,FK$57,$F75:$FF75) -> -7083.3736 | FL75: =SUMIF($F$57:$FF$57,FL$57,$F75:$FF75) -> -7298.8211 | FM75: =SUMIF($F$57:$FF$57,FM$57,$F75:$FF75) -> -7520.8218 | FN75: =SUMIF($F$57:$FF$57,FN$57,$F75:$FF75) -> -7749.5748 | FO75: =SUMIF($F$57:$FF$57,FO$57,$F75:$FF75) -> -7985.2855 | ... FU75: =SUMIF($F$57:$FF$57,FU$57,$F75:$FF75) -> -3947.716
C76: Gross Potential Rent | E76: =SUM(F76:FF76) -> 40958288 | F76: 0 | G76: =SUM(G74:G75) -> 214998.66 | H76: =SUM(H74:H75) -> 215536.15 | I76: =SUM(I74:I75) -> 216074.99 | J76: =SUM(J74:J75) -> 216615.18 | K76: =SUM(K74:K75) -> 217156.72 | L76: =SUM(L74:L75) -> 217699.61 | M76: =SUM(M74:M75) -> 218243.86 | N76: =SUM(N74:N75) -> 218789.47 | ... FF76: =SUM(FF74:FF75) -> 316602.87 | FH76: =SUMIF($F$57:$FF$57,FH$57,$F76:$FF76) -> 1516325.2 | FI76: =SUMIF($F$57:$FF$57,FI$57,$F76:$FF76) -> 2661876.4 | FJ76: =SUMIF($F$57:$FF$57,FJ$57,$F76:$FF76) -> 2742839.9 | FK76: =SUMIF($F$57:$FF$57,FK$57,$F76:$FF76) -> 2826266 | FL76: =SUMIF($F$57:$FF$57,FL$57,$F76:$FF76) -> 2912229.6 | FM76: =SUMIF($F$57:$FF$57,FM$57,$F76:$FF76) -> 3000807.9 | FN76: =SUMIF($F$57:$FF$57,FN$57,$F76:$FF76) -> 3092080.3 | FO76: =SUMIF($F$57:$FF$57,FO$57,$F76:$FF76) -> 3186128.9 | ... FU76: =SUMIF($F$57:$FF$57,FU$57,$F76:$FF76) -> 1575138.7
C78: Other Income
C79: RUBS | D79: =N16 -> 0.7 | E79: =SUM(F79:FF79) -> 1114056.5 | F79: 0 | G79: =$D$79*G105 -> 5847.9167 | H79: =$D$79*H105 -> 5862.5365 | I79: =$D$79*I105 -> 5877.1928 | J79: =$D$79*J105 -> 5891.8858 | K79: =$D$79*K105 -> 5906.6155 | L79: =$D$79*L105 -> 5921.382 | M79: =$D$79*M105 -> 5936.1855 | N79: =$D$79*N105 -> 5951.026 | ... FF79: =$D$79*FF105 -> 8611.5291 | FH79: =SUMIF($F$57:$FF$57,FH$57,$F79:$FF79) -> 41243.715 | FI79: =SUMIF($F$57:$FF$57,FI$57,$F79:$FF79) -> 72402.46 | FJ79: =SUMIF($F$57:$FF$57,FJ$57,$F79:$FF79) -> 74604.65 | FK79: =SUMIF($F$57:$FF$57,FK$57,$F79:$FF79) -> 76873.821 | FL79: =SUMIF($F$57:$FF$57,FL$57,$F79:$FF79) -> 79212.012 | FM79: =SUMIF($F$57:$FF$57,FM$57,$F79:$FF79) -> 81621.321 | FN79: =SUMIF($F$57:$FF$57,FN$57,$F79:$FF79) -> 84103.912 | FO79: =SUMIF($F$57:$FF$57,FO$57,$F79:$FF79) -> 86662.013 | ... FU79: =SUMIF($F$57:$FF$57,FU$57,$F79:$FF79) -> 42843.429
C80: Parking Income | D80: =P17 -> 0 | E80: =SUM(F80:FF80) -> 0 | F80: 0 | G80: =IFERROR($P$17*$O$17*G64*(G58>=$F$13),0) -> 0 | H80: =IFERROR($P$17*$O$17*H64*(H58>=$F$13),0) -> 0 | I80: =IFERROR($P$17*$O$17*I64*(I58>=$F$13),0) -> 0 | J80: =IFERROR($P$17*$O$17*J64*(J58>=$F$13),0) -> 0 | K80: =IFERROR($P$17*$O$17*K64*(K58>=$F$13),0) -> 0 | L80: =IFERROR($P$17*$O$17*L64*(L58>=$F$13),0) -> 0 | M80: =IFERROR($P$17*$O$17*M64*(M58>=$F$13),0) -> 0 | N80: =IFERROR($P$17*$O$17*N64*(N58>=$F$13),0) -> 0 | ... FF80: =IFERROR($P$17*$O$17*FF64*(FF58>=$F$13),0) -> 0 | FH80: =SUMIF($F$57:$FF$57,FH$57,$F80:$FF80) -> 0 | FI80: =SUMIF($F$57:$FF$57,FI$57,$F80:$FF80) -> 0 | FJ80: =SUMIF($F$57:$FF$57,FJ$57,$F80:$FF80) -> 0 | FK80: =SUMIF($F$57:$FF$57,FK$57,$F80:$FF80) -> 0 | FL80: =SUMIF($F$57:$FF$57,FL$57,$F80:$FF80) -> 0 | FM80: =SUMIF($F$57:$FF$57,FM$57,$F80:$FF80) -> 0 | FN80: =SUMIF($F$57:$FF$57,FN$57,$F80:$FF80) -> 0 | FO80: =SUMIF($F$57:$FF$57,FO$57,$F80:$FF80) -> 0 | ... FU80: =SUMIF($F$57:$FF$57,FU$57,$F80:$FF80) -> 0
C81: Other Income | D81: =P18 -> 125 | E81: =SUM(F81:FF81) -> 2387264 | F81: 0 | G81: =IFERROR($P$18*$O$18*G64*(G58>=$F$13),0) -> 12531.25 | H81: =IFERROR($P$18*$O$18*H64*(H58>=$F$13),0) -> 12562.578 | I81: =IFERROR($P$18*$O$18*I64*(I58>=$F$13),0) -> 12593.985 | J81: =IFERROR($P$18*$O$18*J64*(J58>=$F$13),0) -> 12625.47 | K81: =IFERROR($P$18*$O$18*K64*(K58>=$F$13),0) -> 12657.033 | L81: =IFERROR($P$18*$O$18*L64*(L58>=$F$13),0) -> 12688.676 | M81: =IFERROR($P$18*$O$18*M64*(M58>=$F$13),0) -> 12720.397 | N81: =IFERROR($P$18*$O$18*N64*(N58>=$F$13),0) -> 12752.198 | ... FF81: =IFERROR($P$18*$O$18*FF64*(FF58>=$F$13),0) -> 18453.277 | FH81: =SUMIF($F$57:$FF$57,FH$57,$F81:$FF81) -> 88379.389 | FI81: =SUMIF($F$57:$FF$57,FI$57,$F81:$FF81) -> 155148.13 | FJ81: =SUMIF($F$57:$FF$57,FJ$57,$F81:$FF81) -> 159867.11 | FK81: =SUMIF($F$57:$FF$57,FK$57,$F81:$FF81) -> 164729.62 | FL81: =SUMIF($F$57:$FF$57,FL$57,$F81:$FF81) -> 169740.03 | FM81: =SUMIF($F$57:$FF$57,FM$57,$F81:$FF81) -> 174902.83 | FN81: =SUMIF($F$57:$FF$57,FN$57,$F81:$FF81) -> 180222.67 | FO81: =SUMIF($F$57:$FF$57,FO$57,$F81:$FF81) -> 185704.31 | ... FU81: =SUMIF($F$57:$FF$57,FU$57,$F81:$FF81) -> 91807.348
C82: Total Other Income | E82: =SUM(F82:FF82) -> 3501320.5 | F82: 0 | G82: =SUM(G79:G81) -> 18379.167 | H82: =SUM(H79:H81) -> 18425.115 | I82: =SUM(I79:I81) -> 18471.177 | J82: =SUM(J79:J81) -> 18517.355 | K82: =SUM(K79:K81) -> 18563.649 | L82: =SUM(L79:L81) -> 18610.058 | M82: =SUM(M79:M81) -> 18656.583 | N82: =SUM(N79:N81) -> 18703.224 | ... FF82: =SUM(FF79:FF81) -> 27064.806 | FH82: =SUMIF($F$57:$FF$57,FH$57,$F82:$FF82) -> 129623.1 | FI82: =SUMIF($F$57:$FF$57,FI$57,$F82:$FF82) -> 227550.59 | FJ82: =SUMIF($F$57:$FF$57,FJ$57,$F82:$FF82) -> 234471.76 | FK82: =SUMIF($F$57:$FF$57,FK$57,$F82:$FF82) -> 241603.44 | FL82: =SUMIF($F$57:$FF$57,FL$57,$F82:$FF82) -> 248952.04 | FM82: =SUMIF($F$57:$FF$57,FM$57,$F82:$FF82) -> 256524.15 | FN82: =SUMIF($F$57:$FF$57,FN$57,$F82:$FF82) -> 264326.58 | FO82: =SUMIF($F$57:$FF$57,FO$57,$F82:$FF82) -> 272366.33 | ... FU82: =SUMIF($F$57:$FF$57,FU$57,$F82:$FF82) -> 134650.78
C84: Vacancy Loss | E84: =SUM(F84:FF84) -> -2222980.4 | F84: 0 | G84: =-IFERROR(INDEX($M23:$Q23,MATCH(YEAR(G$58),$M$21:$Q$21,0)),$Q$23)*(SUM(G$76,G$82)) -> -11668.891 | H84: =-IFERROR(INDEX($M23:$Q23,MATCH(YEAR(H$58),$M$21:$Q$21,0)),$Q$23)*(SUM(H$76,H$82)) -> -11698.063 | I84: =-IFERROR(INDEX($M23:$Q23,MATCH(YEAR(I$58),$M$21:$Q$21,0)),$Q$23)*(SUM(I$76,I$82)) -> -11727.309 | J84: =-IFERROR(INDEX($M23:$Q23,MATCH(YEAR(J$58),$M$21:$Q$21,0)),$Q$23)*(SUM(J$76,J$82)) -> -11756.627 | K84: =-IFERROR(INDEX($M23:$Q23,MATCH(YEAR(K$58),$M$21:$Q$21,0)),$Q$23)*(SUM(K$76,K$82)) -> -11786.018 | L84: =-IFERROR(INDEX($M23:$Q23,MATCH(YEAR(L$58),$M$21:$Q$21,0)),$Q$23)*(SUM(L$76,L$82)) -> -11815.483 | M84: =-IFERROR(INDEX($M23:$Q23,MATCH(YEAR(M$58),$M$21:$Q$21,0)),$Q$23)*(SUM(M$76,M$82)) -> -11845.022 | N84: =-IFERROR(INDEX($M23:$Q23,MATCH(YEAR(N$58),$M$21:$Q$21,0)),$Q$23)*(SUM(N$76,N$82)) -> -11874.635 | ... FF84: =-IFERROR(INDEX($M23:$Q23,MATCH(YEAR(FF$58),$M$21:$Q$21,0)),$Q$23)*(SUM(FF$76,FF$82)) -> -17183.384 | FH84: =SUMIF($F$57:$FF$57,FH$57,$F84:$FF84) -> -82297.414 | FI84: =SUMIF($F$57:$FF$57,FI$57,$F84:$FF84) -> -144471.35 | FJ84: =SUMIF($F$57:$FF$57,FJ$57,$F84:$FF84) -> -148865.59 | FK84: =SUMIF($F$57:$FF$57,FK$57,$F84:$FF84) -> -153393.47 | FL84: =SUMIF($F$57:$FF$57,FL$57,$F84:$FF84) -> -158059.08 | FM84: =SUMIF($F$57:$FF$57,FM$57,$F84:$FF84) -> -162866.6 | FN84: =SUMIF($F$57:$FF$57,FN$57,$F84:$FF84) -> -167820.35 | FO84: =SUMIF($F$57:$FF$57,FO$57,$F84:$FF84) -> -172924.76 | ... FU84: =SUMIF($F$57:$FF$57,FU$57,$F84:$FF84) -> -85489.473
C85: Bad Debt | D85: =M24 -> 0.0025 | E85: =SUM(F85:FF85) -> -111149.02 | F85: 0 | G85: =-IFERROR(INDEX($M24:$Q24,MATCH(YEAR(G$58),$M$21:$Q$21,0)),$Q$24)*(SUM(G$76,G$82)) -> -583.44456 | H85: =-IFERROR(INDEX($M24:$Q24,MATCH(YEAR(H$58),$M$21:$Q$21,0)),$Q$24)*(SUM(H$76,H$82)) -> -584.90317 | I85: =-IFERROR(INDEX($M24:$Q24,MATCH(YEAR(I$58),$M$21:$Q$21,0)),$Q$24)*(SUM(I$76,I$82)) -> -586.36543 | J85: =-IFERROR(INDEX($M24:$Q24,MATCH(YEAR(J$58),$M$21:$Q$21,0)),$Q$24)*(SUM(J$76,J$82)) -> -587.83134 | K85: =-IFERROR(INDEX($M24:$Q24,MATCH(YEAR(K$58),$M$21:$Q$21,0)),$Q$24)*(SUM(K$76,K$82)) -> -589.30092 | L85: =-IFERROR(INDEX($M24:$Q24,MATCH(YEAR(L$58),$M$21:$Q$21,0)),$Q$24)*(SUM(L$76,L$82)) -> -590.77417 | M85: =-IFERROR(INDEX($M24:$Q24,MATCH(YEAR(M$58),$M$21:$Q$21,0)),$Q$24)*(SUM(M$76,M$82)) -> -592.25111 | N85: =-IFERROR(INDEX($M24:$Q24,MATCH(YEAR(N$58),$M$21:$Q$21,0)),$Q$24)*(SUM(N$76,N$82)) -> -593.73173 | ... FF85: =-IFERROR(INDEX($M24:$Q24,MATCH(YEAR(FF$58),$M$21:$Q$21,0)),$Q$24)*(SUM(FF$76,FF$82)) -> -859.16919 | FH85: =SUMIF($F$57:$FF$57,FH$57,$F85:$FF85) -> -4114.8707 | FI85: =SUMIF($F$57:$FF$57,FI$57,$F85:$FF85) -> -7223.5675 | FJ85: =SUMIF($F$57:$FF$57,FJ$57,$F85:$FF85) -> -7443.2793 | FK85: =SUMIF($F$57:$FF$57,FK$57,$F85:$FF85) -> -7669.6737 | FL85: =SUMIF($F$57:$FF$57,FL$57,$F85:$FF85) -> -7902.9542 | FM85: =SUMIF($F$57:$FF$57,FM$57,$F85:$FF85) -> -8143.3301 | FN85: =SUMIF($F$57:$FF$57,FN$57,$F85:$FF85) -> -8391.0173 | FO85: =SUMIF($F$57:$FF$57,FO$57,$F85:$FF85) -> -8646.2381 | ... FU85: =SUMIF($F$57:$FF$57,FU$57,$F85:$FF85) -> -4274.4736
C86: Concessions | D86: =M25 -> 0.0025 | E86: =SUM(F86:FF86) -> -111149.02 | F86: 0 | G86: =-IFERROR(INDEX($M25:$Q25,MATCH(YEAR(G$58),$M$21:$Q$21,0)),$Q$25)*(SUM(G$76,G$82)) -> -583.44456 | H86: =-IFERROR(INDEX($M25:$Q25,MATCH(YEAR(H$58),$M$21:$Q$21,0)),$Q$25)*(SUM(H$76,H$82)) -> -584.90317 | I86: =-IFERROR(INDEX($M25:$Q25,MATCH(YEAR(I$58),$M$21:$Q$21,0)),$Q$25)*(SUM(I$76,I$82)) -> -586.36543 | J86: =-IFERROR(INDEX($M25:$Q25,MATCH(YEAR(J$58),$M$21:$Q$21,0)),$Q$25)*(SUM(J$76,J$82)) -> -587.83134 | K86: =-IFERROR(INDEX($M25:$Q25,MATCH(YEAR(K$58),$M$21:$Q$21,0)),$Q$25)*(SUM(K$76,K$82)) -> -589.30092 | L86: =-IFERROR(INDEX($M25:$Q25,MATCH(YEAR(L$58),$M$21:$Q$21,0)),$Q$25)*(SUM(L$76,L$82)) -> -590.77417 | M86: =-IFERROR(INDEX($M25:$Q25,MATCH(YEAR(M$58),$M$21:$Q$21,0)),$Q$25)*(SUM(M$76,M$82)) -> -592.25111 | N86: =-IFERROR(INDEX($M25:$Q25,MATCH(YEAR(N$58),$M$21:$Q$21,0)),$Q$25)*(SUM(N$76,N$82)) -> -593.73173 | ... FF86: =-IFERROR(INDEX($M25:$Q25,MATCH(YEAR(FF$58),$M$21:$Q$21,0)),$Q$25)*(SUM(FF$76,FF$82)) -> -859.16919 | FH86: =SUMIF($F$57:$FF$57,FH$57,$F86:$FF86) -> -4114.8707 | FI86: =SUMIF($F$57:$FF$57,FI$57,$F86:$FF86) -> -7223.5675 | FJ86: =SUMIF($F$57:$FF$57,FJ$57,$F86:$FF86) -> -7443.2793 | FK86: =SUMIF($F$57:$FF$57,FK$57,$F86:$FF86) -> -7669.6737 | FL86: =SUMIF($F$57:$FF$57,FL$57,$F86:$FF86) -> -7902.9542 | FM86: =SUMIF($F$57:$FF$57,FM$57,$F86:$FF86) -> -8143.3301 | FN86: =SUMIF($F$57:$FF$57,FN$57,$F86:$FF86) -> -8391.0173 | FO86: =SUMIF($F$57:$FF$57,FO$57,$F86:$FF86) -> -8646.2381 | ... FU86: =SUMIF($F$57:$FF$57,FU$57,$F86:$FF86) -> -4274.4736
C87: Model Unit Loss | E87: =SUM(F87:FF87) -> -410609.4 | F87: 0 | G87: =-IFERROR(INDEX($M26:$Q26,MATCH(YEAR(G$58),$M$21:$Q$21,0)),$Q$26)*G71 -> -2155.375 | H87: =-IFERROR(INDEX($M26:$Q26,MATCH(YEAR(H$58),$M$21:$Q$21,0)),$Q$26)*H71 -> -2160.7634 | I87: =-IFERROR(INDEX($M26:$Q26,MATCH(YEAR(I$58),$M$21:$Q$21,0)),$Q$26)*I71 -> -2166.1653 | J87: =-IFERROR(INDEX($M26:$Q26,MATCH(YEAR(J$58),$M$21:$Q$21,0)),$Q$26)*J71 -> -2171.5808 | K87: =-IFERROR(INDEX($M26:$Q26,MATCH(YEAR(K$58),$M$21:$Q$21,0)),$Q$26)*K71 -> -2177.0097 | L87: =-IFERROR(INDEX($M26:$Q26,MATCH(YEAR(L$58),$M$21:$Q$21,0)),$Q$26)*L71 -> -2182.4522 | M87: =-IFERROR(INDEX($M26:$Q26,MATCH(YEAR(M$58),$M$21:$Q$21,0)),$Q$26)*M71 -> -2187.9084 | N87: =-IFERROR(INDEX($M26:$Q26,MATCH(YEAR(N$58),$M$21:$Q$21,0)),$Q$26)*N71 -> -2193.3781 | ... FF87: =-IFERROR(INDEX($M26:$Q26,MATCH(YEAR(FF$58),$M$21:$Q$21,0)),$Q$26)*FF71 -> -3173.9636 | FH87: =SUMIF($F$57:$FF$57,FH$57,$F87:$FF87) -> -15201.255 | FI87: =SUMIF($F$57:$FF$57,FI$57,$F87:$FF87) -> -26685.478 | FJ87: =SUMIF($F$57:$FF$57,FJ$57,$F87:$FF87) -> -27497.142 | FK87: =SUMIF($F$57:$FF$57,FK$57,$F87:$FF87) -> -28333.494 | FL87: =SUMIF($F$57:$FF$57,FL$57,$F87:$FF87) -> -29195.285 | FM87: =SUMIF($F$57:$FF$57,FM$57,$F87:$FF87) -> -30083.287 | FN87: =SUMIF($F$57:$FF$57,FN$57,$F87:$FF87) -> -30998.299 | FO87: =SUMIF($F$57:$FF$57,FO$57,$F87:$FF87) -> -31941.142 | ... FU87: =SUMIF($F$57:$FF$57,FU$57,$F87:$FF87) -> -15790.864
C88: Total Vacancy & Collection | E88: =SUM(F88:FF88) -> -2855887.9 | F88: =SUM(F84:F87) -> 0 | G88: =SUM(G84:G87) -> -14991.155 | H88: =SUM(H84:H87) -> -15028.633 | I88: =SUM(I84:I87) -> -15066.205 | J88: =SUM(J84:J87) -> -15103.87 | K88: =SUM(K84:K87) -> -15141.63 | L88: =SUM(L84:L87) -> -15179.484 | M88: =SUM(M84:M87) -> -15217.433 | ... FF88: =SUM(FF84:FF87) -> -22075.686 | FH88: =SUMIF($F$57:$FF$57,FH$57,$F88:$FF88) -> -105728.41 | FI88: =SUMIF($F$57:$FF$57,FI$57,$F88:$FF88) -> -185603.96 | FJ88: =SUMIF($F$57:$FF$57,FJ$57,$F88:$FF88) -> -191249.29 | FK88: =SUMIF($F$57:$FF$57,FK$57,$F88:$FF88) -> -197066.32 | FL88: =SUMIF($F$57:$FF$57,FL$57,$F88:$FF88) -> -203060.28 | FM88: =SUMIF($F$57:$FF$57,FM$57,$F88:$FF88) -> -209236.55 | FN88: =SUMIF($F$57:$FF$57,FN$57,$F88:$FF88) -> -215600.68 | FO88: =SUMIF($F$57:$FF$57,FO$57,$F88:$FF88) -> -222158.38 | ... FU88: =SUMIF($F$57:$FF$57,FU$57,$F88:$FF88) -> -109829.28
C90: Effective Gross Income | E90: =SUM(F90:FF90) -> 41603721 | F90: =SUM(F76,F82,F88) -> 0 | G90: =SUM(G76,G82,G88) -> 218386.67 | H90: =SUM(H76,H82,H88) -> 218932.63 | I90: =SUM(I76,I82,I88) -> 219479.97 | J90: =SUM(J76,J82,J88) -> 220028.67 | K90: =SUM(K76,K82,K88) -> 220578.74 | L90: =SUM(L76,L82,L88) -> 221130.18 | M90: =SUM(M76,M82,M88) -> 221683.01 | ... FF90: =SUM(FF76,FF82,FF88) -> 321591.99 | FH90: =SUMIF($F$57:$FF$57,FH$57,$F90:$FF90) -> 1540219.9 | FI90: =SUMIF($F$57:$FF$57,FI$57,$F90:$FF90) -> 2703823.1 | FJ90: =SUMIF($F$57:$FF$57,FJ$57,$F90:$FF90) -> 2786062.4 | FK90: =SUMIF($F$57:$FF$57,FK$57,$F90:$FF90) -> 2870803.2 | FL90: =SUMIF($F$57:$FF$57,FL$57,$F90:$FF90) -> 2958121.4 | FM90: =SUMIF($F$57:$FF$57,FM$57,$F90:$FF90) -> 3048095.5 | FN90: =SUMIF($F$57:$FF$57,FN$57,$F90:$FF90) -> 3140806.2 | FO90: =SUMIF($F$57:$FF$57,FO$57,$F90:$FF90) -> 3236336.9 | ... FU90: =SUMIF($F$57:$FF$57,FU$57,$F90:$FF90) -> 1599960.2
C92: Operating Expenses
C93: Controllable Expenses | D93: $/Unit | E93: Total
C94: =IF(S28<>"",S28,"") -> Payroll | D94: =V28 -> 1500 | E94: =SUM(F94:FF94) -> 2387264 | F94: 0 | G94: =$D94/12*G$66*$N$13 -> 12531.25 | H94: =$D94/12*H$66*$N$13 -> 12562.578 | I94: =$D94/12*I$66*$N$13 -> 12593.985 | J94: =$D94/12*J$66*$N$13 -> 12625.47 | K94: =$D94/12*K$66*$N$13 -> 12657.033 | L94: =$D94/12*L$66*$N$13 -> 12688.676 | M94: =$D94/12*M$66*$N$13 -> 12720.397 | N94: =$D94/12*N$66*$N$13 -> 12752.198 | ... FF94: =$D94/12*FF$66*$N$13 -> 18453.277 | FH94: =SUMIF($F$57:$FF$57,FH$57,$F94:$FF94) -> 88379.389 | FI94: =SUMIF($F$57:$FF$57,FI$57,$F94:$FF94) -> 155148.13 | FJ94: =SUMIF($F$57:$FF$57,FJ$57,$F94:$FF94) -> 159867.11 | FK94: =SUMIF($F$57:$FF$57,FK$57,$F94:$FF94) -> 164729.62 | FL94: =SUMIF($F$57:$FF$57,FL$57,$F94:$FF94) -> 169740.03 | FM94: =SUMIF($F$57:$FF$57,FM$57,$F94:$FF94) -> 174902.83 | FN94: =SUMIF($F$57:$FF$57,FN$57,$F94:$FF94) -> 180222.67 | FO94: =SUMIF($F$57:$FF$57,FO$57,$F94:$FF94) -> 185704.31 | ... FU94: =SUMIF($F$57:$FF$57,FU$57,$F94:$FF94) -> 91807.348
C95: =IF(S29<>"",S29,"") -> Admin | D95: =V29 -> 300 | E95: =SUM(F95:FF95) -> 477452.79 | F95: 0 | G95: =$D95/12*G$66*$N$13 -> 2506.25 | H95: =$D95/12*H$66*$N$13 -> 2512.5156 | I95: =$D95/12*I$66*$N$13 -> 2518.7969 | J95: =$D95/12*J$66*$N$13 -> 2525.0939 | K95: =$D95/12*K$66*$N$13 -> 2531.4066 | L95: =$D95/12*L$66*$N$13 -> 2537.7352 | M95: =$D95/12*M$66*$N$13 -> 2544.0795 | N95: =$D95/12*N$66*$N$13 -> 2550.4397 | ... FF95: =$D95/12*FF$66*$N$13 -> 3690.6553 | FH95: =SUMIF($F$57:$FF$57,FH$57,$F95:$FF95) -> 17675.878 | FI95: =SUMIF($F$57:$FF$57,FI$57,$F95:$FF95) -> 31029.626 | FJ95: =SUMIF($F$57:$FF$57,FJ$57,$F95:$FF95) -> 31973.421 | FK95: =SUMIF($F$57:$FF$57,FK$57,$F95:$FF95) -> 32945.923 | FL95: =SUMIF($F$57:$FF$57,FL$57,$F95:$FF95) -> 33948.005 | FM95: =SUMIF($F$57:$FF$57,FM$57,$F95:$FF95) -> 34980.566 | FN95: =SUMIF($F$57:$FF$57,FN$57,$F95:$FF95) -> 36044.534 | FO95: =SUMIF($F$57:$FF$57,FO$57,$F95:$FF95) -> 37140.863 | ... FU95: =SUMIF($F$57:$FF$57,FU$57,$F95:$FF95) -> 18361.47
C96: =IF(S30<>"",S30,"") -> Marketing | D96: =V30 -> 300 | E96: =SUM(F96:FF96) -> 477452.79 | F96: 0 | G96: =$D96/12*G$66*$N$13 -> 2506.25 | H96: =$D96/12*H$66*$N$13 -> 2512.5156 | I96: =$D96/12*I$66*$N$13 -> 2518.7969 | J96: =$D96/12*J$66*$N$13 -> 2525.0939 | K96: =$D96/12*K$66*$N$13 -> 2531.4066 | L96: =$D96/12*L$66*$N$13 -> 2537.7352 | M96: =$D96/12*M$66*$N$13 -> 2544.0795 | N96: =$D96/12*N$66*$N$13 -> 2550.4397 | ... FF96: =$D96/12*FF$66*$N$13 -> 3690.6553 | FH96: =SUMIF($F$57:$FF$57,FH$57,$F96:$FF96) -> 17675.878 | FI96: =SUMIF($F$57:$FF$57,FI$57,$F96:$FF96) -> 31029.626 | FJ96: =SUMIF($F$57:$FF$57,FJ$57,$F96:$FF96) -> 31973.421 | FK96: =SUMIF($F$57:$FF$57,FK$57,$F96:$FF96) -> 32945.923 | FL96: =SUMIF($F$57:$FF$57,FL$57,$F96:$FF96) -> 33948.005 | FM96: =SUMIF($F$57:$FF$57,FM$57,$F96:$FF96) -> 34980.566 | FN96: =SUMIF($F$57:$FF$57,FN$57,$F96:$FF96) -> 36044.534 | FO96: =SUMIF($F$57:$FF$57,FO$57,$F96:$FF96) -> 37140.863 | ... FU96: =SUMIF($F$57:$FF$57,FU$57,$F96:$FF96) -> 18361.47
C97: =IF(S31<>"",S31,"") -> R&M | D97: =V31 -> 300 | E97: =SUM(F97:FF97) -> 477452.79 | F97: 0 | G97: =$D97/12*G$66*$N$13 -> 2506.25 | H97: =$D97/12*H$66*$N$13 -> 2512.5156 | I97: =$D97/12*I$66*$N$13 -> 2518.7969 | J97: =$D97/12*J$66*$N$13 -> 2525.0939 | K97: =$D97/12*K$66*$N$13 -> 2531.4066 | L97: =$D97/12*L$66*$N$13 -> 2537.7352 | M97: =$D97/12*M$66*$N$13 -> 2544.0795 | N97: =$D97/12*N$66*$N$13 -> 2550.4397 | ... FF97: =$D97/12*FF$66*$N$13 -> 3690.6553 | FH97: =SUMIF($F$57:$FF$57,FH$57,$F97:$FF97) -> 17675.878 | FI97: =SUMIF($F$57:$FF$57,FI$57,$F97:$FF97) -> 31029.626 | FJ97: =SUMIF($F$57:$FF$57,FJ$57,$F97:$FF97) -> 31973.421 | FK97: =SUMIF($F$57:$FF$57,FK$57,$F97:$FF97) -> 32945.923 | FL97: =SUMIF($F$57:$FF$57,FL$57,$F97:$FF97) -> 33948.005 | FM97: =SUMIF($F$57:$FF$57,FM$57,$F97:$FF97) -> 34980.566 | FN97: =SUMIF($F$57:$FF$57,FN$57,$F97:$FF97) -> 36044.534 | FO97: =SUMIF($F$57:$FF$57,FO$57,$F97:$FF97) -> 37140.863 | ... FU97: =SUMIF($F$57:$FF$57,FU$57,$F97:$FF97) -> 18361.47
C98: =IF(S32<>"",S32,"") -> Contract Service | D98: =V32 -> 300 | E98: =SUM(F98:FF98) -> 477452.79 | F98: 0 | G98: =$D98/12*G$66*$N$13 -> 2506.25 | H98: =$D98/12*H$66*$N$13 -> 2512.5156 | I98: =$D98/12*I$66*$N$13 -> 2518.7969 | J98: =$D98/12*J$66*$N$13 -> 2525.0939 | K98: =$D98/12*K$66*$N$13 -> 2531.4066 | L98: =$D98/12*L$66*$N$13 -> 2537.7352 | M98: =$D98/12*M$66*$N$13 -> 2544.0795 | N98: =$D98/12*N$66*$N$13 -> 2550.4397 | ... FF98: =$D98/12*FF$66*$N$13 -> 3690.6553 | FH98: =SUMIF($F$57:$FF$57,FH$57,$F98:$FF98) -> 17675.878 | FI98: =SUMIF($F$57:$FF$57,FI$57,$F98:$FF98) -> 31029.626 | FJ98: =SUMIF($F$57:$FF$57,FJ$57,$F98:$FF98) -> 31973.421 | FK98: =SUMIF($F$57:$FF$57,FK$57,$F98:$FF98) -> 32945.923 | FL98: =SUMIF($F$57:$FF$57,FL$57,$F98:$FF98) -> 33948.005 | FM98: =SUMIF($F$57:$FF$57,FM$57,$F98:$FF98) -> 34980.566 | FN98: =SUMIF($F$57:$FF$57,FN$57,$F98:$FF98) -> 36044.534 | FO98: =SUMIF($F$57:$FF$57,FO$57,$F98:$FF98) -> 37140.863 | ... FU98: =SUMIF($F$57:$FF$57,FU$57,$F98:$FF98) -> 18361.47
C99: =IF(S33<>"",S33,"") -> Turnover | D99: =V33 -> 300 | E99: =SUM(F99:FF99) -> 477452.79 | F99: 0 | G99: =$D99/12*G$66*$N$13 -> 2506.25 | H99: =$D99/12*H$66*$N$13 -> 2512.5156 | I99: =$D99/12*I$66*$N$13 -> 2518.7969 | J99: =$D99/12*J$66*$N$13 -> 2525.0939 | K99: =$D99/12*K$66*$N$13 -> 2531.4066 | L99: =$D99/12*L$66*$N$13 -> 2537.7352 | M99: =$D99/12*M$66*$N$13 -> 2544.0795 | N99: =$D99/12*N$66*$N$13 -> 2550.4397 | ... FF99: =$D99/12*FF$66*$N$13 -> 3690.6553 | FH99: =SUMIF($F$57:$FF$57,FH$57,$F99:$FF99) -> 17675.878 | FI99: =SUMIF($F$57:$FF$57,FI$57,$F99:$FF99) -> 31029.626 | FJ99: =SUMIF($F$57:$FF$57,FJ$57,$F99:$FF99) -> 31973.421 | FK99: =SUMIF($F$57:$FF$57,FK$57,$F99:$FF99) -> 32945.923 | FL99: =SUMIF($F$57:$FF$57,FL$57,$F99:$FF99) -> 33948.005 | FM99: =SUMIF($F$57:$FF$57,FM$57,$F99:$FF99) -> 34980.566 | FN99: =SUMIF($F$57:$FF$57,FN$57,$F99:$FF99) -> 36044.534 | FO99: =SUMIF($F$57:$FF$57,FO$57,$F99:$FF99) -> 37140.863 | ... FU99: =SUMIF($F$57:$FF$57,FU$57,$F99:$FF99) -> 18361.47
C100: =IF(S34<>"",S34,"") -> Other | D100: =V34 -> 0 | E100: =SUM(F100:FF100) -> 0 | F100: 0 | G100: =$D100/12*G$66*$N$13 -> 0 | H100: =$D100/12*H$66*$N$13 -> 0 | I100: =$D100/12*I$66*$N$13 -> 0 | J100: =$D100/12*J$66*$N$13 -> 0 | K100: =$D100/12*K$66*$N$13 -> 0 | L100: =$D100/12*L$66*$N$13 -> 0 | M100: =$D100/12*M$66*$N$13 -> 0 | N100: =$D100/12*N$66*$N$13 -> 0 | ... FF100: =$D100/12*FF$66*$N$13 -> 0 | FH100: =SUMIF($F$57:$FF$57,FH$57,$F100:$FF100) -> 0 | FI100: =SUMIF($F$57:$FF$57,FI$57,$F100:$FF100) -> 0 | FJ100: =SUMIF($F$57:$FF$57,FJ$57,$F100:$FF100) -> 0 | FK100: =SUMIF($F$57:$FF$57,FK$57,$F100:$FF100) -> 0 | FL100: =SUMIF($F$57:$FF$57,FL$57,$F100:$FF100) -> 0 | FM100: =SUMIF($F$57:$FF$57,FM$57,$F100:$FF100) -> 0 | FN100: =SUMIF($F$57:$FF$57,FN$57,$F100:$FF100) -> 0 | FO100: =SUMIF($F$57:$FF$57,FO$57,$F100:$FF100) -> 0 | ... FU100: =SUMIF($F$57:$FF$57,FU$57,$F100:$FF100) -> 0
C101: Total Controllable Opex | E101: =SUM(F101:FF101) -> 4774527.9 | F101: =SUM(F94:F100) -> 0 | G101: =SUM(G94:G100) -> 25062.5 | H101: =SUM(H94:H100) -> 25125.156 | I101: =SUM(I94:I100) -> 25187.969 | J101: =SUM(J94:J100) -> 25250.939 | K101: =SUM(K94:K100) -> 25314.066 | L101: =SUM(L94:L100) -> 25377.352 | M101: =SUM(M94:M100) -> 25440.795 | ... FF101: =SUM(FF94:FF100) -> 36906.553 | FH101: =SUMIF($F$57:$FF$57,FH$57,$F101:$FF101) -> 176758.78 | FI101: =SUMIF($F$57:$FF$57,FI$57,$F101:$FF101) -> 310296.26 | FJ101: =SUMIF($F$57:$FF$57,FJ$57,$F101:$FF101) -> 319734.21 | FK101: =SUMIF($F$57:$FF$57,FK$57,$F101:$FF101) -> 329459.23 | FL101: =SUMIF($F$57:$FF$57,FL$57,$F101:$FF101) -> 339480.05 | FM101: =SUMIF($F$57:$FF$57,FM$57,$F101:$FF101) -> 349805.66 | FN101: =SUMIF($F$57:$FF$57,FN$57,$F101:$FF101) -> 360445.34 | FO101: =SUMIF($F$57:$FF$57,FO$57,$F101:$FF101) -> 371408.63 | ... FU101: =SUMIF($F$57:$FF$57,FU$57,$F101:$FF101) -> 183614.7
C103: Non-controllable Expenses | D103: $/Unit | E103: Total
C104: =IF(S37<>"",S37,"") -> Insurance | D104: =V37 -> 500 | E104: =SUM(F104:FF104) -> 795754.66 | F104: 0 | G104: =$D104/12*G$66*$N$13 -> 4177.0833 | H104: =$D104/12*H$66*$N$13 -> 4187.526 | I104: =$D104/12*I$66*$N$13 -> 4197.9949 | J104: =$D104/12*J$66*$N$13 -> 4208.4898 | K104: =$D104/12*K$66*$N$13 -> 4219.0111 | L104: =$D104/12*L$66*$N$13 -> 4229.5586 | M104: =$D104/12*M$66*$N$13 -> 4240.1325 | N104: =$D104/12*N$66*$N$13 -> 4250.7328 | ... FF104: =$D104/12*FF$66*$N$13 -> 6151.0922 | FH104: =SUMIF($F$57:$FF$57,FH$57,$F104:$FF104) -> 29459.796 | FI104: =SUMIF($F$57:$FF$57,FI$57,$F104:$FF104) -> 51716.043 | FJ104: =SUMIF($F$57:$FF$57,FJ$57,$F104:$FF104) -> 53289.035 | FK104: =SUMIF($F$57:$FF$57,FK$57,$F104:$FF104) -> 54909.872 | FL104: =SUMIF($F$57:$FF$57,FL$57,$F104:$FF104) -> 56580.009 | FM104: =SUMIF($F$57:$FF$57,FM$57,$F104:$FF104) -> 58300.944 | FN104: =SUMIF($F$57:$FF$57,FN$57,$F104:$FF104) -> 60074.223 | FO104: =SUMIF($F$57:$FF$57,FO$57,$F104:$FF104) -> 61901.438 | ... FU104: =SUMIF($F$57:$FF$57,FU$57,$F104:$FF104) -> 30602.449
C105: =IF(S38<>"",S38,"") -> Utilities | D105: =V38 -> 1000 | E105: =SUM(F105:FF105) -> 1591509.3 | F105: 0 | G105: =$D105/12*G$66*$N$13 -> 8354.1667 | H105: =$D105/12*H$66*$N$13 -> 8375.0521 | I105: =$D105/12*I$66*$N$13 -> 8395.9897 | J105: =$D105/12*J$66*$N$13 -> 8416.9797 | K105: =$D105/12*K$66*$N$13 -> 8438.0221 | L105: =$D105/12*L$66*$N$13 -> 8459.1172 | M105: =$D105/12*M$66*$N$13 -> 8480.265 | N105: =$D105/12*N$66*$N$13 -> 8501.4656 | ... FF105: =$D105/12*FF$66*$N$13 -> 12302.184 | FH105: =SUMIF($F$57:$FF$57,FH$57,$F105:$FF105) -> 58919.592 | FI105: =SUMIF($F$57:$FF$57,FI$57,$F105:$FF105) -> 103432.09 | FJ105: =SUMIF($F$57:$FF$57,FJ$57,$F105:$FF105) -> 106578.07 | FK105: =SUMIF($F$57:$FF$57,FK$57,$F105:$FF105) -> 109819.74 | FL105: =SUMIF($F$57:$FF$57,FL$57,$F105:$FF105) -> 113160.02 | FM105: =SUMIF($F$57:$FF$57,FM$57,$F105:$FF105) -> 116601.89 | FN105: =SUMIF($F$57:$FF$57,FN$57,$F105:$FF105) -> 120148.45 | FO105: =SUMIF($F$57:$FF$57,FO$57,$F105:$FF105) -> 123802.88 | ... FU105: =SUMIF($F$57:$FF$57,FU$57,$F105:$FF105) -> 61204.899
C106: Management (% EGI) | D106: =V39 -> 786.06 | E106: =SUM(F106:FF106) -> 1248111.6 | F106: 0 | G106: =($T$39*G90) -> 6551.6 | H106: =($T$39*H90) -> 6567.979 | I106: =($T$39*I90) -> 6584.399 | J106: =($T$39*J90) -> 6600.86 | K106: =($T$39*K90) -> 6617.3621 | L106: =($T$39*L90) -> 6633.9055 | M106: =($T$39*M90) -> 6650.4903 | N106: =($T$39*N90) -> 6667.1165 | ... FF106: =($T$39*FF90) -> 9647.7597 | FH106: =SUMIF($F$57:$FF$57,FH$57,$F106:$FF106) -> 46206.596 | FI106: =SUMIF($F$57:$FF$57,FI$57,$F106:$FF106) -> 81114.692 | FJ106: =SUMIF($F$57:$FF$57,FJ$57,$F106:$FF106) -> 83581.872 | FK106: =SUMIF($F$57:$FF$57,FK$57,$F106:$FF106) -> 86124.095 | FL106: =SUMIF($F$57:$FF$57,FL$57,$F106:$FF106) -> 88743.642 | FM106: =SUMIF($F$57:$FF$57,FM$57,$F106:$FF106) -> 91442.865 | FN106: =SUMIF($F$57:$FF$57,FN$57,$F106:$FF106) -> 94224.187 | FO106: =SUMIF($F$57:$FF$57,FO$57,$F106:$FF106) -> 97090.106 | ... FU106: =SUMIF($F$57:$FF$57,FU$57,$F106:$FF106) -> 47998.805
C107: Property Taxes | D107: ='Pro Forma Template'!V40 -> 2649.7517 | E107: =SUM(F107:FF107) -> 4217104.5 | F107: 0 | G107: =$D107/12*G$66*$N$13 -> 22136.468 | H107: =$D107/12*H$66*$N$13 -> 22191.809 | I107: =$D107/12*I$66*$N$13 -> 22247.288 | J107: =$D107/12*J$66*$N$13 -> 22302.906 | K107: =$D107/12*K$66*$N$13 -> 22358.664 | L107: =$D107/12*L$66*$N$13 -> 22414.56 | M107: =$D107/12*M$66*$N$13 -> 22470.597 | N107: =$D107/12*N$66*$N$13 -> 22526.773 | ... FF107: =$D107/12*FF$66*$N$13 -> 32597.735 | FH107: =SUMIF($F$57:$FF$57,FH$57,$F107:$FF107) -> 156122.29 | FI107: =SUMIF($F$57:$FF$57,FI$57,$F107:$FF107) -> 274069.35 | FJ107: =SUMIF($F$57:$FF$57,FJ$57,$F107:$FF107) -> 282405.43 | FK107: =SUMIF($F$57:$FF$57,FK$57,$F107:$FF107) -> 290995.06 | FL107: =SUMIF($F$57:$FF$57,FL$57,$F107:$FF107) -> 299845.95 | FM107: =SUMIF($F$57:$FF$57,FM$57,$F107:$FF107) -> 308966.05 | FN107: =SUMIF($F$57:$FF$57,FN$57,$F107:$FF107) -> 318363.55 | FO107: =SUMIF($F$57:$FF$57,FO$57,$F107:$FF107) -> 328046.88 | ... FU107: =SUMIF($F$57:$FF$57,FU$57,$F107:$FF107) -> 162177.79
C108: Total Non-controllable Opex | E108: =SUM(F108:FF108) -> 7852480.1 | F108: =SUM(F104:F107) -> 0 | G108: =SUM(G104:G107) -> 41219.318 | H108: =SUM(H104:H107) -> 41322.366 | I108: =SUM(I104:I107) -> 41425.672 | J108: =SUM(J104:J107) -> 41529.236 | K108: =SUM(K104:K107) -> 41633.059 | L108: =SUM(L104:L107) -> 41737.142 | M108: =SUM(M104:M107) -> 41841.485 | ... FF108: =SUM(FF104:FF107) -> 60698.771 | FH108: =SUMIF($F$57:$FF$57,FH$57,$F108:$FF108) -> 290708.28 | FI108: =SUMIF($F$57:$FF$57,FI$57,$F108:$FF108) -> 510332.17 | FJ108: =SUMIF($F$57:$FF$57,FJ$57,$F108:$FF108) -> 525854.41 | FK108: =SUMIF($F$57:$FF$57,FK$57,$F108:$FF108) -> 541848.77 | FL108: =SUMIF($F$57:$FF$57,FL$57,$F108:$FF108) -> 558329.62 | FM108: =SUMIF($F$57:$FF$57,FM$57,$F108:$FF108) -> 575311.75 | FN108: =SUMIF($F$57:$FF$57,FN$57,$F108:$FF108) -> 592810.41 | FO108: =SUMIF($F$57:$FF$57,FO$57,$F108:$FF108) -> 610841.3 | ... FU108: =SUMIF($F$57:$FF$57,FU$57,$F108:$FF108) -> 301983.94
...

Sheet SOFR
B2: EOM | C2: Date | D2: 1 Month Term SOFR Forward Curve
B3: =EOMONTH(C3,0) -> 46081 | C3: 46070 | D3: 0.0366293
B4: =EOMONTH(C4,0) -> 46112 | C4: 46098 | D4: 0.0365167
B5: =EOMONTH(C5,0) -> 46142 | C5: 46129 | D5: 0.0361732
B6: =EOMONTH(C6,0) -> 46173 | C6: 46160 | D6: 0.0357834
B7: =EOMONTH(C7,0) -> 46203 | C7: 46190 | D7: 0.0349209
B8: =EOMONTH(C8,0) -> 46234 | C8: 46220 | D8: 0.0341197
B9: =EOMONTH(C9,0) -> 46265 | C9: 46251 | D9: 0.0334921
B10: =EOMONTH(C10,0) -> 46295 | C10: 46282 | D10: 0.0319517
B11: =EOMONTH(C11,0) -> 46326 | C11: 46314 | D11: 0.0319503
B12: =EOMONTH(C12,0) -> 46356 | C12: 46343 | D12: 0.0319137
B13: =EOMONTH(C13,0) -> 46387 | C13: 46373 | D13: 0.0308998
B14: =EOMONTH(C14,0) -> 46418 | C14: 46406 | D14: 0.0308972
... B123: =EOMONTH(C123,0) -> 49734 | C123: 49724 | D123: 0.0428121

Sheet Exclude ->

Sheet Cost Curve
B2: Construction Cost Curve
B3: Month | C3: 1 | D3: =C3+1 -> 2 | E3: =D3+1 -> 3 | F3: =E3+1 -> 4 | G3: =F3+1 -> 5 | H3: =G3+1 -> 6 | I3: =H3+1 -> 7 | J3: =I3+1 -> 8 | K3: =J3+1 -> 9 | ... AL3: =AK3+1 -> 36
B4: =B5-1 -> 1 | C4: 1
B5: =B6-1 -> 2 | C5: 0.5 | D5: 0.5
B6: =B7-1 -> 3 | C6: 0.33333333 | D6: 0.33333333 | E6: 0.33333333
B7: =B8-1 -> 4 | C7: 0.2 | D7: 0.3 | E7: 0.3 | F7: 0.2
B8: =B9-1 -> 5 | C8: 0.15 | D8: 0.2 | E8: 0.3 | F8: 0.2 | G8: 0.15
B9: =B10-1 -> 6 | C9: 0.1 | D9: 0.15 | E9: 0.25 | F9: 0.25 | G9: 0.15 | H9: 0.1
B10: =B11-1 -> 7 | C10: 0.075 | D10: 0.125 | E10: 0.175 | F10: 0.25 | G10: 0.175 | H10: 0.125 | I10: 0.075
B11: =B12-1 -> 8 | C11: 0.05 | D11: 0.1 | E11: 0.15 | F11: 0.2 | G11: 0.2 | H11: 0.15 | I11: 0.1 | J11: 0.05
B12: =B13-1 -> 9 | C12: 0.05 | D12: 0.075 | E12: 0.125 | F12: 0.15 | G12: 0.2 | H12: 0.15 | I12: 0.125 | J12: 0.075 | K12: 0.05
B13: 10 | C13: 0.04 | D13: 0.065 | E13: 0.1 | F13: 0.125 | G13: 0.17 | H13: 0.17 | I13: 0.125 | J13: 0.1 | K13: 0.065 | L13: 0.04
B14: 11 | C14: 0.035 | D14: 0.05 | E14: 0.09 | F14: 0.12 | G14: 0.13 | H14: 0.15 | I14: 0.13 | J14: 0.12 | K14: 0.09 | L14: 0.05 | M14: 0.035
B15: 12 | C15: 0.03 | D15: 0.05 | E15: 0.07 | F15: 0.1 | G15: 0.12 | H15: 0.13 | I15: 0.13 | J15: 0.12 | K15: 0.1 | L15: 0.07 | M15: 0.05 | N15: 0.03
B16: =+B15+1 -> 13 | C16: 0.025 | D16: 0.04 | E16: 0.06 | F16: 0.09 | G16: 0.11 | H16: 0.11 | I16: 0.13 | J16: 0.11 | K16: 0.11 | L16: 0.09 | M16: 0.06 | N16: 0.04 | O16: 0.025
B17: =+B16+1 -> 14 | C17: 0.02 | D17: 0.04 | E17: 0.06 | F17: 0.08 | G17: 0.08 | H17: 0.1 | I17: 0.12 | J17: 0.12 | K17: 0.1 | L17: 0.08 | M17: 0.08 | N17: 0.06 | O17: 0.04 | P17: 0.02
B18: =+B17+1 -> 15 | C18: 0.02 | D18: 0.03 | E18: 0.05 | F18: 0.07 | G18: 0.08 | H18: 0.09 | I18: 0.1 | J18: 0.12 | K18: 0.1 | L18: 0.09 | M18: 0.08 | N18: 0.07 | O18: 0.05 | P18: 0.03 | Q18: 0.02
B19: =+B18+1 -> 16 | C19: 0.02 | D19: 0.03 | E19: 0.05 | F19: 0.06 | G19: 0.07 | H19: 0.08 | I19: 0.09 | J19: 0.1 | K19: 0.1 | L19: 0.09 | M19: 0.08 | N19: 0.07 | O19: 0.06 | P19: 0.05 | Q19: 0.03 | R19: 0.02
B20: =+B19+1 -> 17 | C20: 0.02 | D20: 0.03 | E20: 0.04 | F20: 0.05 | G20: 0.06 | H20: 0.07 | I20: 0.09 | J20: 0.09 | K20: 0.1 | L20: 0.09 | M20: 0.09 | N20: 0.07 | O20: 0.06 | P20: 0.05 | Q20: 0.04 | R20: 0.03 | S20: 0.02
B21: =+B20+1 -> 18 | C21: 0.015 | D21: 0.025 | E21: 0.025 | F21: 0.025 | G21: 0.03 | H21: 0.04 | I21: 0.05 | J21: 0.08 | K21: 0.1 | L21: 0.1 | M21: 0.08 | N21: 0.08 | O21: 0.08 | P21: 0.08 | Q21: 0.08 | R21: 0.06 | S21: 0.03 | T21: 0.02
B22: =+B21+1 -> 19 | C22: 0.015 | D22: 0.025 | E22: 0.025 | F22: 0.025 | G22: 0.025 | H22: 0.03 | I22: 0.05 | J22: 0.065 | K22: 0.08 | L22: 0.08 | M22: 0.08 | N22: 0.08 | O22: 0.08 | P22: 0.08 | Q22: 0.08 | R22: 0.08 | S22: 0.06 | T22: 0.03 | U22: 0.01
B23: =+B22+1 -> 20 | C23: 0.015 | D23: 0.015 | E23: 0.025 | F23: 0.025 | G23: 0.03 | H23: 0.03 | I23: 0.04 | J23: 0.05 | K23: 0.07 | L23: 0.07 | M23: 0.08 | N23: 0.08 | O23: 0.08 | P23: 0.08 | Q23: 0.08 | R23: 0.08 | S23: 0.07 | T23: 0.05 | U23: 0.02 | V23: 0.01
B24: =+B23+1 -> 21 | C24: 0.01 | D24: 0.01 | E24: 0.02 | F24: 0.02 | G24: 0.02 | H24: 0.03 | I24: 0.04 | J24: 0.05 | K24: 0.07 | L24: 0.07 | M24: 0.07 | N24: 0.08 | O24: 0.08 | P24: 0.08 | Q24: 0.08 | R24: 0.08 | S24: 0.08 | T24: 0.05 | U24: 0.03 | V24: 0.02 | W24: 0.01
B25: =+B24+1 -> 22 | C25: 0.01 | D25: 0.01 | E25: 0.01 | F25: 0.02 | G25: 0.02 | H25: 0.02 | I25: 0.03 | J25: 0.04 | K25: 0.05 | L25: 0.07 | M25: 0.07 | N25: 0.08 | O25: 0.08 | P25: 0.08 | Q25: 0.08 | R25: 0.08 | S25: 0.08 | T25: 0.08 | U25: 0.05 | V25: 0.02 | W25: 0.01 | X25: 0.01
B26: =+B25+1 -> 23 | C26: 0.01 | D26: 0.01 | E26: 0.01 | F26: 0.01 | G26: 0.02 | H26: 0.02 | I26: 0.02 | J26: 0.03 | K26: 0.04 | L26: 0.06 | M26: 0.07 | N26: 0.07 | O26: 0.08 | P26: 0.08 | Q26: 0.08 | R26: 0.08 | S26: 0.08 | T26: 0.08 | U26: 0.06 | V26: 0.03 | W26: 0.03 | X26: 0.02 | Y26: 0.01
B27: =+B26+1 -> 24 | C27: 0.01 | D27: 0.01 | E27: 0.01 | F27: 0.01 | G27: 0.01 | H27: 0.02 | I27: 0.02 | J27: 0.02 | K27: 0.03 | L27: 0.05 | M27: 0.06 | N27: 0.07 | O27: 0.07 | P27: 0.08 | Q27: 0.08 | R27: 0.08 | S27: 0.08 | T27: 0.08 | U27: 0.08 | V27: 0.05 | W27: 0.03 | X27: 0.02 | Y27: 0.02 | Z27: 0.01
B28: =+B27+1 -> 25 | C28: 0.0032051282 | D28: 0.0096153846 | E28: 0.016025641 | F28: 0.022435897 | G28: 0.028846154 | H28: 0.03525641 | I28: 0.041666667 | J28: 0.048076923 | K28: 0.054487179 | L28: 0.060897436 | M28: 0.067307692 | N28: 0.073717949 | O28: 0.076923077 | P28: 0.073717949 | Q28: 0.067307692 | R28: 0.060897436 | S28: 0.054487179 | T28: 0.048076923 | U28: 0.041666667 | V28: 0.03525641 | W28: 0.028846154 | X28: 0.022435897 | Y28: 0.016025641 | Z28: 0.0096153846 | AA28: 0.0032051282
B29: =+B28+1 -> 26 | C29: 0.0054945055 | D29: 0.010989011 | E29: 0.016483516 | F29: 0.021978022 | G29: 0.027472527 | H29: 0.032967033 | I29: 0.038461538 | J29: 0.043956044 | K29: 0.049450549 | L29: 0.054945055 | M29: 0.06043956 | N29: 0.065934066 | O29: 0.071428571 | P29: 0.071428571 | Q29: 0.065934066 | R29: 0.06043956 | S29: 0.054945055 | T29: 0.049450549 | U29: 0.043956044 | V29: 0.038461538 | W29: 0.032967033 | X29: 0.027472527 | Y29: 0.021978022 | Z29: 0.016483516 | AA29: 0.010989011 | AB29: 0.0054945055
B30: =+B29+1 -> 27 | C30: 0.0027472527 | D30: 0.0082417582 | E30: 0.013736264 | F30: 0.019230769 | G30: 0.024725275 | H30: 0.03021978 | I30: 0.035714286 | J30: 0.041208791 | K30: 0.046703297 | L30: 0.052197802 | M30: 0.057692308 | N30: 0.063186813 | O30: 0.068681319 | P30: 0.071428571 | Q30: 0.068681319 | R30: 0.063186813 | S30: 0.057692308 | T30: 0.052197802 | U30: 0.046703297 | V30: 0.041208791 | W30: 0.035714286 | X30: 0.03021978 | Y30: 0.024725275 | Z30: 0.019230769 | AA30: 0.013736264 | AB30: 0.0082417582 | AC30: 0.0027472527
B31: =+B30+1 -> 28 | C31: 0.0047619048 | D31: 0.0095238095 | E31: 0.014285714 | F31: 0.019047619 | G31: 0.023809524 | H31: 0.028571429 | I31: 0.033333333 | J31: 0.038095238 | K31: 0.042857143 | L31: 0.047619048 | M31: 0.052380952 | N31: 0.057142857 | O31: 0.061904762 | P31: 0.066666667 | Q31: 0.066666667 | R31: 0.061904762 | S31: 0.057142857 | T31: 0.052380952 | U31: 0.047619048 | V31: 0.042857143 | W31: 0.038095238 | X31: 0.033333333 | Y31: 0.028571429 | Z31: 0.023809524 | AA31: 0.019047619 | AB31: 0.014285714 | AC31: 0.0095238095 | AD31: 0.0047619048
B32: =+B31+1 -> 29 | C32: 0.0023809524 | D32: 0.0071428571 | E32: 0.011904762 | F32: 0.016666667 | G32: 0.021428571 | H32: 0.026190476 | I32: 0.030952381 | J32: 0.035714286 | K32: 0.04047619 | L32: 0.045238095 | M32: 0.05 | N32: 0.054761905 | O32: 0.05952381 | P32: 0.064285714 | Q32: 0.066666667 | R32: 0.064285714 | S32: 0.05952381 | T32: 0.054761905 | U32: 0.05 | V32: 0.045238095 | W32: 0.04047619 | X32: 0.035714286 | Y32: 0.030952381 | Z32: 0.026190476 | AA32: 0.021428571 | AB32: 0.016666667 | AC32: 0.011904762 | AD32: 0.0071428571 | AE32: 0.0023809524
B33: =+B32+1 -> 30 | C33: 0.0041666667 | D33: 0.0083333333 | E33: 0.0125 | F33: 0.016666667 | G33: 0.020833333 | H33: 0.025 | I33: 0.029166667 | J33: 0.033333333 | K33: 0.0375 | L33: 0.041666667 | M33: 0.045833333 | N33: 0.05 | O33: 0.054166667 | P33: 0.058333333 | Q33: 0.0625 | R33: 0.0625 | S33: 0.058333333 | T33: 0.054166667 | U33: 0.05 | V33: 0.045833333 | W33: 0.041666667 | X33: 0.0375 | Y33: 0.033333333 | Z33: 0.029166667 | AA33: 0.025 | AB33: 0.020833333 | AC33: 0.016666667 | AD33: 0.0125 | AE33: 0.0083333333 | AF33: 0.0041666667
B34: =+B33+1 -> 31 | C34: 0.0020833333 | D34: 0.00625 | E34: 0.010416667 | F34: 0.014583333 | G34: 0.01875 | H34: 0.022916667 | I34: 0.027083333 | J34: 0.03125 | K34: 0.035416667 | L34: 0.039583333 | M34: 0.04375 | N34: 0.047916667 | O34: 0.052083333 | P34: 0.05625 | Q34: 0.060416667 | R34: 0.0625 | S34: 0.060416667 | T34: 0.05625 | U34: 0.052083333 | V34: 0.047916667 | W34: 0.04375 | X34: 0.039583333 | Y34: 0.035416667 | Z34: 0.03125 | AA34: 0.027083333 | AB34: 0.022916667 | AC34: 0.01875 | AD34: 0.014583333 | AE34: 0.010416667 | AF34: 0.00625 | AG34: 0.0020833333
B35: =+B34+1 -> 32 | C35: 0.0036764706 | D35: 0.0073529412 | E35: 0.011029412 | F35: 0.014705882 | G35: 0.018382353 | H35: 0.022058824 | I35: 0.025735294 | J35: 0.029411765 | K35: 0.033088235 | L35: 0.036764706 | M35: 0.040441176 | N35: 0.044117647 | O35: 0.047794118 | P35: 0.051470588 | Q35: 0.055147059 | R35: 0.058823529 | S35: 0.058823529 | T35: 0.055147059 | U35: 0.051470588 | V35: 0.047794118 | W35: 0.044117647 | X35: 0.040441176 | Y35: 0.036764706 | Z35: 0.033088235 | AA35: 0.029411765 | AB35: 0.025735294 | AC35: 0.022058824 | AD35: 0.018382353 | AE35: 0.014705882 | AF35: 0.011029412 | AG35: 0.0073529412 | AH35: 0.0036764706
B36: =+B35+1 -> 33 | C36: 0.0018382353 | D36: 0.0055147059 | E36: 0.0091911765 | F36: 0.012867647 | G36: 0.016544118 | H36: 0.020220588 | I36: 0.023897059 | J36: 0.027573529 | K36: 0.03125 | L36: 0.034926471 | M36: 0.038602941 | N36: 0.042279412 | O36: 0.045955882 | P36: 0.049632353 | Q36: 0.053308824 | R36: 0.056985294 | S36: 0.058823529 | T36: 0.056985294 | U36: 0.053308824 | V36: 0.049632353 | W36: 0.045955882 | X36: 0.042279412 | Y36: 0.038602941 | Z36: 0.034926471 | AA36: 0.03125 | AB36: 0.027573529 | AC36: 0.023897059 | AD36: 0.020220588 | AE36: 0.016544118 | AF36: 0.012867647 | AG36: 0.0091911765 | AH36: 0.0055147059 | AI36: 0.0018382353
B37: =+B36+1 -> 34 | C37: 0.0032679739 | D37: 0.0065359477 | E37: 0.0098039216 | F37: 0.013071895 | G37: 0.016339869 | H37: 0.019607843 | I37: 0.022875817 | J37: 0.026143791 | K37: 0.029411765 | L37: 0.032679739 | M37: 0.035947712 | N37: 0.039215686 | O37: 0.04248366 | P37: 0.045751634 | Q37: 0.049019608 | R37: 0.052287582 | S37: 0.055555556 | T37: 0.055555556 | U37: 0.052287582 | V37: 0.049019608 | W37: 0.045751634 | X37: 0.04248366 | Y37: 0.039215686 | Z37: 0.035947712 | AA37: 0.032679739 | AB37: 0.029411765 | AC37: 0.026143791 | AD37: 0.022875817 | AE37: 0.019607843 | AF37: 0.016339869 | AG37: 0.013071895 | AH37: 0.0098039216 | AI37: 0.0065359477 | AJ37: 0.0032679739
B38: =+B37+1 -> 35 | C38: 0.0016339869 | D38: 0.0049019608 | E38: 0.0081699346 | F38: 0.011437908 | G38: 0.014705882 | H38: 0.017973856 | I38: 0.02124183 | J38: 0.024509804 | K38: 0.027777778 | L38: 0.031045752 | M38: 0.034313725 | N38: 0.037581699 | O38: 0.040849673 | P38: 0.044117647 | Q38: 0.047385621 | R38: 0.050653595 | S38: 0.053921569 | T38: 0.055555556 | U38: 0.053921569 | V38: 0.050653595 | W38: 0.047385621 | X38: 0.044117647 | Y38: 0.040849673 | Z38: 0.037581699 | AA38: 0.034313725 | AB38: 0.031045752 | AC38: 0.027777778 | AD38: 0.024509804 | AE38: 0.02124183 | AF38: 0.017973856 | AG38: 0.014705882 | AH38: 0.011437908 | AI38: 0.0081699346 | AJ38: 0.0049019608 | AK38: 0.0016339869
B39: =+B38+1 -> 36 | C39: 0.0029239766 | D39: 0.0058479532 | E39: 0.0087719298 | F39: 0.011695906 | G39: 0.014619883 | H39: 0.01754386 | I39: 0.020467836 | J39: 0.023391813 | K39: 0.026315789 | L39: 0.029239766 | M39: 0.032163743 | N39: 0.035087719 | O39: 0.038011696 | P39: 0.040935673 | Q39: 0.043859649 | R39: 0.046783626 | S39: 0.049707602 | T39: 0.052631579 | U39: 0.052631579 | V39: 0.049707602 | W39: 0.046783626 | X39: 0.043859649 | Y39: 0.040935673 | Z39: 0.038011696 | AA39: 0.035087719 | AB39: 0.032163743 | AC39: 0.029239766 | AD39: 0.026315789 | AE39: 0.023391813 | AF39: 0.020467836 | AG39: 0.01754386 | AH39: 0.014619883 | AI39: 0.011695906 | AJ39: 0.0087719298 | AK39: 0.0058479532 | AL39: 0.0029239766
C41: 43281 | D41: 43312 | E41: 43343 | F41: 43373 | G41: 43404 | H41: 43434 | I41: 43465 | J41: 43496 | K41: 43524 | L41: 43555 | M41: 43585 | N41: 43616 | O41: 43646 | P41: 43677 | Q41: 43708 | R41: 43738 | S41: 43769 | T41: 43799 | U41: 43830 | V41: 43861 | W41: 43890 | X41: 43921 | Y41: 43951 | Z41: 43982 | AA41: 44012 | AB41: 44043 | AC41: 44074 | AD41: 44104 | AE41: 44135 | AF41: 44165 | AG41: 44196 | AH41: 44227 | AI41: 44255 | AJ41: 44286 | AK41: 44316 | AL41: 44347 | AM41: 44377 | AN41: 44408 | AO41: 44439 | AP41: 44469 | AQ41: 44500 | AR41: 44530 | AS41: 44561 | AT41: 44592 | AU41: 44620 | AV41: 44651 | AW41: 44681 | AX41: 44712 | AY41: 44742 | AZ41: 44773 | BA41: 44804 | BB41: 44834 | BC41: 44865 | BD41: 44895 | BE41: 44926 | BF41: 44957 | BG41: 44985 | BH41: 45016 | BI41: 45046 | BJ41: 45077 | BK41: 45107 | BL41: 45138 | BM41: 45169 | BN41: 45199 | BO41: 45230 | BP41: 45260 | BQ41: 45291 | BR41: 45322 | BS41: 45351 | BT41: 45382 | BU41: 45412 | BV41: 45443 | BW41: 45473 | BX41: 45504 | BY41: 45535 | BZ41: 45565 | CA41: 45596 | CB41: 45626 | CC41: 45657 | CD41: 45688 | CE41: 45716 | CF41: 45747 | CG41: 45777 | CH41: 45808 | CI41: 45838 | CJ41: 45869 | CK41: 45900 | CL41: 45930 | CM41: 45961 | CN41: 45991 | CO41: 46022 | CP41: 46053 | CQ41: 46081 | CR41: 46112 | CS41: 46142 | CT41: 46173 | CU41: 46203 | CV41: 46234 | CW41: 46265 | CX41: 46295 | CY41: 46326 | CZ41: 46356 | DA41: 46387 | DB41: 46418 | DC41: 46446 | DD41: 46477 | DE41: 46507 | DF41: 46538 | DG41: 46568 | DH41: 46599 | DI41: 46630 | DJ41: 46660 | DK41: 46691 | DL41: 46721 | DM41: 46752 | DN41: 46783 | DO41: 46812 | DP41: 46843 | DQ41: 46873 | DR41: 46904 | DS41: 46934 | DT41: 46965 | DU41: 46996 | DV41: 47026 | DW41: 47057 | DX41: 47087 | DY41: 47118 | DZ41: 47149 | EA41: 47177 | EB41: 47208 | EC41: 47238 | ED41: 47269 | EE41: 47299 | EF41: 47330 | EG41: 47361 | EH41: 47391 | EI41: 47422 | EJ41: 47452 | EK41: 47483 | EL41: 47514 | EM41: 47542 | EN41: 47573 | EO41: 47603 | EP41: 47634 | EQ41: 47664 | ER41: 47695 | ES41: 47726 | ET41: 47756 | EU41: 47787 | EV41: 47817 | EW41: 47848 | EX41: 47879 | EY41: 47907 | EZ41: 47938 | FA41: 47968 | FB41: 47999 | FC41: 48029 | FD41: 48060 | FE41: 48091 | FF41: 48121 | FG41: 48152 | FH41: 48182 | FI41: 48213 | FJ41: 48244 | FK41: 48273 | FL41: 48304 | FM41: 48334 | FN41: 48365 | FO41: 48395 | FP41: 48426 | FQ41: 48457 | FR41: 48487 | FS41: 48518 | FT41: 48548 | FU41: 48579 | FV41: 48610 | FW41: 48638 | FX41: 48669 | FY41: 48699 | FZ41: 48730 | GA41: 48760 | GB41: 48791 | GC41: 48822 | GD41: 48852 | GE41: 48883 | GF41: 48913 | GG41: 48944 | GH41: 48975 | GI41: 49003 | GJ41: 49034 | GK41: 49064 | GL41: 49095 | GM41: 49125
B42: LIBOR Curve | C42: 0.0209025 | D42: 0.0208138 | E42: 0.0211375 | F42: 0.0226056 | G42: 0.0230688 | H42: 0.0234694 | I42: 0.0250269 | J42: 0.0251375 | K42: 0.0249038 | L42: 0.024945 | M42: 0.024805 | N42: 0.024305 | O42: 0.02398 | P42: 0.0222425 | Q42: 0.02089 | R42: 0.0201563 | S42: 0.0178488 | T42: 0.0169713 | U42: 0.017625 | V42: 0.0166188 | W42: 0.0151525 | X42: 0.0113625 | Y42: 0.0101245 | Z42: 0.0091342 | AA42: 0.0084722 | AB42: 0.0079368 | AC42: 0.0074057 | AD42: 0.0069192 | AE42: 0.0066086 | AF42: 0.0064933 | AG42: 0.0065614 | AH42: 0.0066812 | AI42: 0.0067386 | AJ42: 0.0067482 | AK42: 0.0067406 | AL42: 0.0067174 | AM42: 0.0067187 | AN42: 0.0067521 | AO42: 0.0067961 | AP42: 0.0068751 | AQ42: 0.0069825 | AR42: 0.0070909 | AS42: 0.0072186 | AT42: 0.0073642 | AU42: 0.0075058 | AV42: 0.0076563 | AW42: 0.0078098 | AX42: 0.0079447 | AY42: 0.0080764 | AZ42: 0.0082044 | BA42: 0.0083124 | BB42: 0.0084158 | BC42: 0.0085147 | BD42: 0.008594 | BE42: 0.0086696 | BF42: 0.0087424 | BG42: 0.0087974 | BH42: 0.0088535 | BI42: 0.0089152 | BJ42: 0.0089677 | BK42: 0.0090293 | BL42: 0.0091003 | BM42: 0.0091623 | BN42: 0.0092331 | BO42: 0.0093117 | BP42: 0.0093786 | BQ42: 0.0094524 | BR42: 0.0095329 | BS42: 0.0095998 | BT42: 0.0096734 | BU42: 0.0097558 | BV42: 0.0098247 | BW42: 0.0099084 | BX42: 0.0100001 | BY42: 0.0100813 | BZ42: 0.0101731 | CA42: 0.0102756 | CB42: 0.0103681 | CC42: 0.0104706 | CD42: 0.0105828 | CE42: 0.0106838 | CF42: 0.0107901 | CG42: 0.0108998 | CH42: 0.0109917 | CI42: 0.0110842 | CJ42: 0.0111774 | CK42: 0.0112532 | CL42: 0.0113304 | CM42: 0.0114084 | CN42: 0.0114703 | CO42: 0.0115347 | CP42: 0.0116014 | CQ42: 0.0116534 | CR42: 0.0117088 | CS42: 0.0117673 | CT42: 0.0118178 | CU42: 0.0118732 | CV42: 0.0119345 | CW42: 0.0119847 | CX42: 0.0120414 | CY42: 0.0121034 | CZ42: 0.0121527 | DA42: 0.0122067 | DB42: 0.0122647 | DC42: 0.0123087 | DD42: 0.0123573 | DE42: 0.0124128 | DF42: 0.0124575 | DG42: 0.0125127 | DH42: 0.0125778 | DI42: 0.012632 | DJ42: 0.012696 | DK42: 0.0127691 | DL42: 0.0128298 | DM42: 0.0128977 | DN42: 0.0129726 | DO42: 0.0130335 | DP42: 0.0130999 | DQ42: 0.0131726 | DR42: 0.0132306 | DS42: 0.0132943 | DT42: 0.0133639 | DU42: 0.0134192 | DV42: 0.0134805 | DW42: 0.013548 | DX42: 0.013601 | DY42: 0.0136603 | DZ42: 0.013726 | EA42: 0.0137759 | EB42: 0.0138298 | EC42: 0.0138883 | ED42: 0.0139299 | EE42: 0.0139785 | EF42: 0.01403 | EG42: 0.0140659 | EH42: 0.0141069 | EI42: 0.014153 | EJ42: 0.0141824 | EK42: 0.0142159 | EL42: 0.014254 | EM42: 0.0142754 | EN42: 0.0143012 | EO42: 0.0143512 | EP42: 0.0144012 | EQ42: 0.0144512 | ER42: 0.0145012 | ES42: 0.0145512 | ET42: 0.0146012 | EU42: 0.0146512 | EV42: 0.0147012 | EW42: 0.0147512 | EX42: 0.0148012 | EY42: 0.0148512 | EZ42: 0.0149012 | FA42: 0.0149512 | FB42: 0.0150012 | FC42: 0.0150512 | FD42: 0.0151012 | FE42: 0.0151512 | FF42: 0.0152012 | FG42: 0.0152512 | FH42: 0.0153012 | FI42: 0.0153512 | FJ42: 0.0154012 | FK42: 0.0154512 | FL42: 0.0155012 | FM42: 0.0155512 | FN42: 0.0156012 | FO42: 0.0156512 | FP42: 0.0157012 | FQ42: 0.0157512 | FR42: 0.0158012 | FS42: 0.0158512 | FT42: 0.0159012 | FU42: 0.0159512 | FV42: 0.0160012 | FW42: 0.0160512 | FX42: 0.0161012 | FY42: 0.0161512 | FZ42: 0.0162012 | GA42: 0.0162512 | GB42: 0.0163012 | GC42: 0.0163512 | GD42: 0.0164012 | GE42: 0.0164512 | GF42: 0.0165012 | GG42: 0.0165512 | GH42: 0.0166012 | GI42: 0.0166512 | GJ42: 0.0167012 | GK42: 0.0167512 | GL42: 0.0168012 | GM42: 0.0168512
C44: =C41 -> 43281 | D44: =EOMONTH(C44,1) -> 43312 | E44: =EOMONTH(D44,1) -> 43343 | F44: =EOMONTH(E44,1) -> 43373 | G44: =EOMONTH(F44,1) -> 43404 | H44: =EOMONTH(G44,1) -> 43434 | I44: =EOMONTH(H44,1) -> 43465 | J44: =EOMONTH(I44,1) -> 43496 | K44: =EOMONTH(J44,1) -> 43524 | ... GM44: =EOMONTH(GL44,1) -> 49125
B45: Lucia | C45: =IFERROR(INDEX($B$3:$AL$39,MATCH(#REF!,$B$3:$B$39,0),MATCH(DATEDIF(EOMONTH(#REF!,-1)+1,C44,"M"),$B$3:$AL$3,0)),0) -> 0 | D45: =IFERROR(INDEX($B$3:$AL$39,MATCH(#REF!,$B$3:$B$39,0),MATCH(DATEDIF(EOMONTH(#REF!,-1)+1,D44,"M"),$B$3:$AL$3,0)),0) -> 0 | E45: =IFERROR(INDEX($B$3:$AL$39,MATCH(#REF!,$B$3:$B$39,0),MATCH(DATEDIF(EOMONTH(#REF!,-1)+1,E44,"M"),$B$3:$AL$3,0)),0) -> 0 | F45: =IFERROR(INDEX($B$3:$AL$39,MATCH(#REF!,$B$3:$B$39,0),MATCH(DATEDIF(EOMONTH(#REF!,-1)+1,F44,"M"),$B$3:$AL$3,0)),0) -> 0 | G45: =IFERROR(INDEX($B$3:$AL$39,MATCH(#REF!,$B$3:$B$39,0),MATCH(DATEDIF(EOMONTH(#REF!,-1)+1,G44,"M"),$B$3:$AL$3,0)),0) -> 0 | H45: =IFERROR(INDEX($B$3:$AL$39,MATCH(#REF!,$B$3:$B$39,0),MATCH(DATEDIF(EOMONTH(#REF!,-1)+1,H44,"M"),$B$3:$AL$3,0)),0) -> 0 | I45: =IFERROR(INDEX($B$3:$AL$39,MATCH(#REF!,$B$3:$B$39,0),MATCH(DATEDIF(EOMONTH(#REF!,-1)+1,I44,"M"),$B$3:$AL$3,0)),0) -> 0 | J45: =IFERROR(INDEX($B$3:$AL$39,MATCH(#REF!,$B$3:$B$39,0),MATCH(DATEDIF(EOMONTH(#REF!,-1)+1,J44,"M"),$B$3:$AL$3,0)),0) -> 0 | ... GM45: =IFERROR(INDEX($B$3:$AL$39,MATCH(#REF!,$B$3:$B$39,0),MATCH(DATEDIF(EOMONTH(#REF!,-1)+1,GM44,"M"),$B$3:$AL$3,0)),0) -> 0
B46: REVO | C46: =IFERROR(INDEX($B$3:$AL$39,MATCH(#REF!,$B$3:$B$39,0),MATCH(DATEDIF(EOMONTH(#REF!,-1)+1,C44,"M"),$B$3:$AL$3,0)),0) -> 0 | D46: =IFERROR(INDEX($B$3:$AL$39,MATCH(#REF!,$B$3:$B$39,0),MATCH(DATEDIF(EOMONTH(#REF!,-1)+1,D44,"M"),$B$3:$AL$3,0)),0) -> 0 | E46: =IFERROR(INDEX($B$3:$AL$39,MATCH(#REF!,$B$3:$B$39,0),MATCH(DATEDIF(EOMONTH(#REF!,-1)+1,E44,"M"),$B$3:$AL$3,0)),0) -> 0 | F46: =IFERROR(INDEX($B$3:$AL$39,MATCH(#REF!,$B$3:$B$39,0),MATCH(DATEDIF(EOMONTH(#REF!,-1)+1,F44,"M"),$B$3:$AL$3,0)),0) -> 0 | G46: =IFERROR(INDEX($B$3:$AL$39,MATCH(#REF!,$B$3:$B$39,0),MATCH(DATEDIF(EOMONTH(#REF!,-1)+1,G44,"M"),$B$3:$AL$3,0)),0) -> 0 | H46: =IFERROR(INDEX($B$3:$AL$39,MATCH(#REF!,$B$3:$B$39,0),MATCH(DATEDIF(EOMONTH(#REF!,-1)+1,H44,"M"),$B$3:$AL$3,0)),0) -> 0 | I46: =IFERROR(INDEX($B$3:$AL$39,MATCH(#REF!,$B$3:$B$39,0),MATCH(DATEDIF(EOMONTH(#REF!,-1)+1,I44,"M"),$B$3:$AL$3,0)),0) -> 0 | J46: =IFERROR(INDEX($B$3:$AL$39,MATCH(#REF!,$B$3:$B$39,0),MATCH(DATEDIF(EOMONTH(#REF!,-1)+1,J44,"M"),$B$3:$AL$3,0)),0) -> 0 | ... GM46: =IFERROR(INDEX($B$3:$AL$39,MATCH(#REF!,$B$3:$B$39,0),MATCH(DATEDIF(EOMONTH(#REF!,-1)+1,GM44,"M"),$B$3:$AL$3,0)),0) -> 0
B47: The Current | C47: =IFERROR(INDEX($B$3:$AL$39,MATCH(#REF!,$B$3:$B$39,0),MATCH(DATEDIF(EOMONTH(#REF!,-1)+1,C44,"M"),$B$3:$AL$3,0)),0) -> 0 | D47: =IFERROR(INDEX($B$3:$AL$39,MATCH(#REF!,$B$3:$B$39,0),MATCH(DATEDIF(EOMONTH(#REF!,-1)+1,D44,"M"),$B$3:$AL$3,0)),0) -> 0 | E47: =IFERROR(INDEX($B$3:$AL$39,MATCH(#REF!,$B$3:$B$39,0),MATCH(DATEDIF(EOMONTH(#REF!,-1)+1,E44,"M"),$B$3:$AL$3,0)),0) -> 0 | F47: =IFERROR(INDEX($B$3:$AL$39,MATCH(#REF!,$B$3:$B$39,0),MATCH(DATEDIF(EOMONTH(#REF!,-1)+1,F44,"M"),$B$3:$AL$3,0)),0) -> 0 | G47: =IFERROR(INDEX($B$3:$AL$39,MATCH(#REF!,$B$3:$B$39,0),MATCH(DATEDIF(EOMONTH(#REF!,-1)+1,G44,"M"),$B$3:$AL$3,0)),0) -> 0 | H47: =IFERROR(INDEX($B$3:$AL$39,MATCH(#REF!,$B$3:$B$39,0),MATCH(DATEDIF(EOMONTH(#REF!,-1)+1,H44,"M"),$B$3:$AL$3,0)),0) -> 0 | I47: =IFERROR(INDEX($B$3:$AL$39,MATCH(#REF!,$B$3:$B$39,0),MATCH(DATEDIF(EOMONTH(#REF!,-1)+1,I44,"M"),$B$3:$AL$3,0)),0) -> 0 | J47: =IFERROR(INDEX($B$3:$AL$39,MATCH(#REF!,$B$3:$B$39,0),MATCH(DATEDIF(EOMONTH(#REF!,-1)+1,J44,"M"),$B$3:$AL$3,0)),0) -> 0 | ... GM47: =IFERROR(INDEX($B$3:$AL$39,MATCH(#REF!,$B$3:$B$39,0),MATCH(DATEDIF(EOMONTH(#REF!,-1)+1,GM44,"M"),$B$3:$AL$3,0)),0) -> 0
